Workbook

Sheet Executive Summary
B2: Refund Root-Cause Analysis - Executive Summary
A5: The cohort in numbers
B7: Total learners (Academy Intake X) | C7: =COUNTA('Master Learner Profile'!B2:B1650) -> 1649
B8: Total refund requests | C8: =COUNTA('Categorised Reasons'!A2:A1650) -> 304
B9: Refunds processed (Refunded? = Yes) | C9: =COUNTIF('Master Learner Profile'!C2:C1650,"Yes") -> 281
B10: Overall refund rate | C10: =COUNTIF('Master Learner Profile'!C2:C1650,"Yes")/COUNTA('Master Learner Profile'!B2:B1650) -> 0.17040631
B11: Avg attendance: refunders | C11: =AVERAGEIFS('Master Learner Profile'!K2:K1650,'Master Learner Profile'!C2:C1650,"Yes") -> 24.574964
B12: Avg attendance: non-refunders | C12: =AVERAGEIFS('Master Learner Profile'!K2:K1650,'Master Learner Profile'!C2:C1650,"No") -> 82.645804
B13: % of refunders who skipped DBWT | C13: =COUNTIFS('Master Learner Profile'!L2:L1650,"No",'Master Learner Profile'!C2:C1650,"Yes")/COUNTIF('Master Learner Profile'!C2:C1650,"Yes") -> 0.4519573
B14: % of refunders in Critical risk segment | C14: =COUNTIFS('Master Learner Profile'!O2:O1650,"1: Critical (No DBWT + No Wk0)",'Master Learner Profile'!C2:C1650,"Yes")/COUNTIF('Master Learner Profile'!C2:C1650,"Yes") -> 0.19928826
A17: The three takeaways
B19: Q1 - Why learners refund | C19: Three buckets cover roughly two-thirds of refund cases: Personal/Family/Medical (~26% of recorded reasons), Career events like new job or relocation (~14%), and Financial difficulty including loan rejection (~21%). The remaining third is operational: course expectation mismatch, time/work pressure, and sales process failures. The operational third is where the lever sits.
B20: Q2 - Can we reduce refund % | C20: Yes, meaningfully. The strongest predictor is whether a learner did the Dashboard Walkthrough: doers refund at ~12%, skippers refund at ~43%. Combined with no Week 0 attendance, refund rate hits ~74%. About 58% of all refunders show one or both early-disengagement signals before they request a refund, which means a precise outreach trigger could touch a small share of the cohort and reach a large share of refunders.
B21: Q3 - What else to dig into | C21: Eight hypotheses listed in the Q3 tab, of which three feel highest-priority: PS/SP rep-level performance as a hidden driver, financial pre-qualification before down payment collection, and learners from non-development backgrounds being under-screened at sales.
A24: How this workbook is organised
B26: Executive Summary | C26: This page
B27: Q1 - Refund Reasons | C27: Categorised refund-reason breakdown plus sub-themes
B28: Q2 - Reduce Refund % | C28: Engagement-vs-refund analysis and the strategies it points to
B29: Q3 - Additional Hypotheses | C29: Open questions that warrant follow-up data
B30: Categorised Reasons | C30: All 304 refund records with my primary-reason tag (data tab)
B31: Master Learner Profile | C31: All 1,649 learners with engagement signals merged + risk segment
B32: Original sheets | C32: Problem Statement, Learner IDs, Comms Tracker, Week 0 Attendance, Overall Attendance, Dashboard Walkthrough, Refund Team Tracker, Mentor Sessions - left untouched

Sheet Problem Statement
B2: Problem Statement: Find the root cause for refunds and generate so-whats
B3: Output Expectation: A clean, formatted .xlsx file answering the questions below
B4: Questions to answer:
B5: 1/ What are the primary reasons our learners request refunds?
B6: 2/ Is there potential to reduce our refund percentage in future intakes? If so, what data-driven strategies can we implement to achieve this reduction?
B7: 3/ Are there any additional hypotheses that would be valuable to explore?
B9: Context on the Problem Statement: https://www.loom.com/share/27fcbbbd010545d9b6a5e423db33815d?sid=88512954-f12c-4315-ab5a-ef89e93c0818
B10: Scaler Context for sheet navigation: https://www.loom.com/share/32019552f04a431bba6d76b92178a9ae?sid=5e280baa-6d8d-48cc-a39f-e31a24b8f00c
B12: Workbook Overview:
B14: Tab Name | C14: Description
B15: Learner IDs | C15: List of all learners in the batch with a tag of learners who requested for a refund
B16: Comms Tracker | C16: Tracker for the communications shared to a learner between the day they enrolled and the start of the program
B17: Week 0 Attendance | C17: Introductory week classes with their attendance (Slug = indication of the type of meeting)
B18: Overall Attendance | C18: Attendance of the learners for their classes (Week 0+1+2)
B19: Dashboard Walkthrough | C19: Tracker for the walkthrough of the dashboard/scaler's internal platform given to a learner before the learners start their classes
B20: Refund Team Tracker | C20: Refund tracker maintained the teams who try to retain the learner with their detailed comments on refund reasons
B21: Mentor Sessions | C21: Mentor sessions tracker for the learners for the few two weeks (booking the session is recommended but optional for the first two weeks)
B23: Additional Instructions:
B24: 1/ Please ensure data hygiene while performing the analysis
B25: 2/ Use formulas wherever possible so that we can trace back your solutions and analysis

Sheet Q1 - Refund Reasons
B2: Q1: What are the primary reasons our learners request refunds?
B4: Approach: I read all 281 free-text refund notes from the Refund Team Tracker, categorised each one into a primary driver based on keyword scoring, and then rolled them up. The full categorised list lives in the "Categorised Reasons" tab.
A6: 1.1 Refund Reasons by Primary Driver (formula-driven from Categorised Reasons tab)
B8: # | C8: Primary Reason | D8: Count | E8: % of 281 | F8: % of 304 reqs | G8: Refund Rate Impact | H8: What the notes typically say
B9: 1 | C9: Personal / Family / Medical | D9: =COUNTIF('Categorised Reasons'!H:H,"Personal / Family / Medical") -> 73 | E9: =IFERROR(D9/(COUNTA('Categorised Reasons'!H2:H305)-COUNTIF('Categorised Reasons'!H:H,"Not Recorded")),0) -> 0.25978648 | F9: =IFERROR(D9/COUNTA('Categorised Reasons'!A2:A305),0) -> 0.24013158 | G9: Drives refunds | H9: Health emergencies, family illness, deaths, marriages, pregnancies, parents not supporting, vague "personal issues"
B10: 2 | C10: New Job / Career Change / Relocation | D10: =COUNTIF('Categorised Reasons'!H:H,"New Job / Career Change / Relocation") -> 38 | E10: =IFERROR(D10/(COUNTA('Categorised Reasons'!H2:H305)-COUNTIF('Categorised Reasons'!H:H,"Not Recorded")),0) -> 0.13523132 | F10: =IFERROR(D10/COUNTA('Categorised Reasons'!A2:A305),0) -> 0.125 | G10: Drives refunds | H10: Got a new job, promotion, onsite project abroad, leaving for US/UK/Germany/Canada, switching domain
B11: 3 | C11: Financial Difficulty / Affordability | D11: =COUNTIF('Categorised Reasons'!H:H,"Financial Difficulty / Affordability") -> 34 | E11: =IFERROR(D11/(COUNTA('Categorised Reasons'!H2:H305)-COUNTIF('Categorised Reasons'!H:H,"Not Recorded")),0) -> 0.12099644 | F11: =IFERROR(D11/COUNTA('Categorised Reasons'!A2:A305),0) -> 0.11184211 | G11: Drives refunds | H11: Sole earner, low salary, lost job, already has loans, can't afford EMI even after enrolling
B12: 4 | C12: Course Expectation / Curriculum Mismatch | D12: =COUNTIF('Categorised Reasons'!H:H,"Course Expectation / Curriculum Mismatch") -> 32 | E12: =IFERROR(D12/(COUNTA('Categorised Reasons'!H2:H305)-COUNTIF('Categorised Reasons'!H:H,"Not Recorded")),0) -> 0.113879 | F12: =IFERROR(D12/COUNTA('Categorised Reasons'!A2:A305),0) -> 0.10526316 | G12: Drives refunds | H12: Wrong fit (QA / testing / non-IT / Project Manager bg), expected ML not DSA, wanted morning batch, said could self-learn
B13: 5 | C13: Time / Work Pressure | D13: =COUNTIF('Categorised Reasons'!H:H,"Time / Work Pressure") -> 32 | E13: =IFERROR(D13/(COUNTA('Categorised Reasons'!H2:H305)-COUNTIF('Categorised Reasons'!H:H,"Not Recorded")),0) -> 0.113879 | F13: =IFERROR(D13/COUNTA('Categorised Reasons'!A2:A305),0) -> 0.10526316 | G13: Drives refunds | H13: 12-13 hour workdays, multiple projects, can't carve out 9-12 hrs/week for live classes
B14: 6 | C14: Loan / NBFC / Financing Issue | D14: =COUNTIF('Categorised Reasons'!H:H,"Loan / NBFC / Financing Issue") -> 24 | E14: =IFERROR(D14/(COUNTA('Categorised Reasons'!H2:H305)-COUNTIF('Categorised Reasons'!H:H,"Not Recorded")),0) -> 0.085409253 | F14: =IFERROR(D14/COUNTA('Categorised Reasons'!A2:A305),0) -> 0.078947368 | G14: Drives refunds | H14: Loan rejected by NBFC partners (low CIBIL, no co-applicant, low banking, short credit history)
B15: 7 | C15: Sales / Service Process Issue | D15: =COUNTIF('Categorised Reasons'!H:H,"Sales / Service Process Issue") -> 15 | E15: =IFERROR(D15/(COUNTA('Categorised Reasons'!H2:H305)-COUNTIF('Categorised Reasons'!H:H,"Not Recorded")),0) -> 0.053380783 | F15: =IFERROR(D15/COUNTA('Categorised Reasons'!A2:A305),0) -> 0.049342105 | G15: Drives refunds | H15: Delay in revert from PS/SP, wrong information at sales, alumni feedback negative, BDA inactive in system
B16: 8 | C16: Higher Studies / Govt Career | D16: =COUNTIF('Categorised Reasons'!H:H,"Higher Studies / Govt Career") -> 3 | E16: =IFERROR(D16/(COUNTA('Categorised Reasons'!H2:H305)-COUNTIF('Categorised Reasons'!H:H,"Not Recorded")),0) -> 0.010676157 | F16: =IFERROR(D16/COUNTA('Categorised Reasons'!A2:A305),0) -> 0.0098684211 | G16: Drives refunds | H16: Cleared UPSC, going for Masters abroad, joining army
B17: 9 | C17: Pricing / Value Concern | D17: =COUNTIF('Categorised Reasons'!H:H,"Pricing / Value Concern") -> 2 | E17: =IFERROR(D17/(COUNTA('Categorised Reasons'!H2:H305)-COUNTIF('Categorised Reasons'!H:H,"Not Recorded")),0) -> 0.0071174377 | F17: =IFERROR(D17/COUNTA('Categorised Reasons'!A2:A305),0) -> 0.0065789474 | G17: Drives refunds | H17: Felt course not worth the price, others got it cheaper, asking too much for what is offered
B18: 10 | C18: Other / Unclear | D18: =COUNTIF('Categorised Reasons'!H:H,"Other / Unclear") -> 28 | E18: =IFERROR(D18/(COUNTA('Categorised Reasons'!H2:H305)-COUNTIF('Categorised Reasons'!H:H,"Not Recorded")),0) -> 0.099644128 | F18: =IFERROR(D18/COUNTA('Categorised Reasons'!A2:A305),0) -> 0.092105263 | G18: Drives refunds | H18: Vague, mixed, or unclear notes that don't cluster into one driver
B19: 11 | C19: Not Recorded | D19: =COUNTIF('Categorised Reasons'!H:H,"Not Recorded") -> 23 | E19: =IFERROR(D19/(COUNTA('Categorised Reasons'!H2:H305)-COUNTIF('Categorised Reasons'!H:H,"Not Recorded")),0) -> 0.081850534 | F19: =IFERROR(D19/COUNTA('Categorised Reasons'!A2:A305),0) -> 0.075657895 | G19: Drives refunds | H19: Refund row exists but no detailed reason field was filled in by the team
C20: TOTAL | D20: =SUM(D9:D19) -> 304
C21: Total with reason text: | D21: =COUNTA('Categorised Reasons'!F2:F305) -> 281
C22: Total refund requests: | D22: =COUNTA('Categorised Reasons'!A2:A305) -> 304
A25: 1.2 Headline insight
B27: Roughly two thirds of refund requests cluster into three buckets: Personal/Family/Medical (~26% of cases with a recorded reason), Career-related events like a new job or relocation (~14%), and Financial Difficulty including loan rejections (~21% combined when you add Loan/NBFC + Affordability). What is striking is that the remaining third splits into reasons Scaler can actually act on: course expectation mismatch (~11%), time/work pressure (~11%), and sales process issues (~5%). These three are the operational levers worth pulling, because a learner whose father is in hospital is hard to retain, but a learner who thought the course was 3 hours a week and discovered it is 9 is a fixable problem.
A30: 1.3 Sub-themes within the major buckets (qualitative)
B32: Bucket | C32: Recurring sub-themes I saw in the notes
B33: Personal / Family / Medical | C33: Family member hospitalised (father, grandmother, parent), own surgery or medical condition, pregnancy, newly married, family pressure or parents not supportive of upskilling. Often paired with a "will rejoin in 3-6 months" intent.
B34: New Job / Career Change / Relocation | C34: Got placed mid-program, onsite project to US/UK/Germany/Sweden/Mexico/Vietnam, L1 visa, Canada PR approved, or moving for spouse. A subset is "switching domain" where the learner decides development is not their long-term path after a few classes.
B35: Financial / Loan | C35: Loan rejected by NBFC partners (low CIBIL, no co-applicant, salary too low, AQBB norms), or learner is sole earner / lost job / already has 2-3 loans. Several mention they paid down-payment expecting loan approval and got blindsided.
B36: Course Expectation Mismatch | C36: "I thought it was 3-4 hrs/week, it is 9", "I thought class size was 100, it is 220", wanted morning batch, came from QA / testing / digital marketing / project management and felt the dev focus was wrong, expected DSML but got DSA, expected job guarantee.
B37: Time / Work Pressure | C37: 12-13 hour work days, multiple parallel projects assigned, overlapping IST/EST/PST shifts, newly added team responsibilities, internal courses pushed by employer competing for time.
B38: Sales / Service Process | C38: Delay in revert from PS or SP after refund request raised (multiple cases say "transferred due to breach in timelines, reason unknown"), wrong information at the sales stage, alumni gave bad feedback when the learner cross-checked, BDA inactive in system.

Sheet Q2 - Reduce Refund %
B2: Q2: Can we reduce refund % in future intakes? What strategies?
B4: Approach: I joined every learner's engagement signal (comms opens, Week 0 attendance, Dashboard Walkthrough completion, overall attendance, mentor sessions) onto the master roster of 1,649 learners and split refund rate by each signal. The full merged data lives in "Master Learner Profile" tab. All counts below are formulas pointing at that tab so they update if the underlying data changes.
A6: 2.1 The headline numbers
B8: Metric | C8: Value | D8: Formula source
B9: Total learners in batch | C9: =COUNTA('Master Learner Profile'!B2:B1650) -> 1649 | D9: COUNTA of Learner ID column
B10: Total refunds | C10: =COUNTIF('Master Learner Profile'!C2:C1650,"Yes") -> 281 | D10: COUNTIF Refunded? = Yes
B11: Overall refund rate | C11: =COUNTIF('Master Learner Profile'!C2:C1650,"Yes")/COUNTA('Master Learner Profile'!B2:B1650) -> 0.17040631 | D11: Refunds / Total
B12: Refunders avg overall attendance | C12: =AVERAGEIFS('Master Learner Profile'!K2:K1650,'Master Learner Profile'!C2:C1650,"Yes") -> 24.574964 | D12: AVERAGEIFS on Overall Attendance where Refunded=Yes
B13: Non-refunders avg overall attendance | C13: =AVERAGEIFS('Master Learner Profile'!K2:K1650,'Master Learner Profile'!C2:C1650,"No") -> 82.645804 | D13: AVERAGEIFS on Overall Attendance where Refunded=No
B14: Gap (non-refund minus refund) | C14: =AVERAGEIFS('Master Learner Profile'!K2:K1650,'Master Learner Profile'!C2:C1650,"No")-AVERAGEIFS('Master Learner Profile'!K2:K1650,'Master Learner Profile'!C2:C1650,"Yes") -> 58.07084 | D14: Difference of the two means
A17: 2.2 Refund rate by Overall Attendance bucket
B19: Attendance bucket | C19: Total learners | D19: Refunders | E19: Non-refunders | F19: Refund rate %
B20: 0% (no shows) | C20: =SUMPRODUCT(--('Master Learner Profile'!K2:K1650=0)) -> 91 | D20: =SUMPRODUCT(--('Master Learner Profile'!K2:K1650=0),--('Master Learner Profile'!C2:C1650="Yes")) -> 73 | E20: =SUMPRODUCT(--('Master Learner Profile'!K2:K1650=0),--('Master Learner Profile'!C2:C1650="No")) -> 18 | F20: =IFERROR(D20/C20,0) -> 0.8021978
B21: 1% to 25% | C21: =SUMPRODUCT(--('Master Learner Profile'!K2:K1650>0),--('Master Learner Profile'!K2:K1650<=25)) -> 175 | D21: =SUMPRODUCT(--('Master Learner Profile'!K2:K1650>0),--('Master Learner Profile'!K2:K1650<=25),--('Master Learner Profile'!C2:C1650="Yes")) -> 94 | E21: =SUMPRODUCT(--('Master Learner Profile'!K2:K1650>0),--('Master Learner Profile'!K2:K1650<=25),--('Master Learner Profile'!C2:C1650="No")) -> 81 | F21: =IFERROR(D21/C21,0) -> 0.53714286
B22: 25% to 50% | C22: =SUMPRODUCT(--('Master Learner Profile'!K2:K1650>25),--('Master Learner Profile'!K2:K1650<=50)) -> 155 | D22: =SUMPRODUCT(--('Master Learner Profile'!K2:K1650>25),--('Master Learner Profile'!K2:K1650<=50),--('Master Learner Profile'!C2:C1650="Yes")) -> 68 | E22: =SUMPRODUCT(--('Master Learner Profile'!K2:K1650>25),--('Master Learner Profile'!K2:K1650<=50),--('Master Learner Profile'!C2:C1650="No")) -> 87 | F22: =IFERROR(D22/C22,0) -> 0.43870968
B23: 50% to 75% | C23: =SUMPRODUCT(--('Master Learner Profile'!K2:K1650>50),--('Master Learner Profile'!K2:K1650<=75)) -> 163 | D23: =SUMPRODUCT(--('Master Learner Profile'!K2:K1650>50),--('Master Learner Profile'!K2:K1650<=75),--('Master Learner Profile'!C2:C1650="Yes")) -> 30 | E23: =SUMPRODUCT(--('Master Learner Profile'!K2:K1650>50),--('Master Learner Profile'!K2:K1650<=75),--('Master Learner Profile'!C2:C1650="No")) -> 133 | F23: =IFERROR(D23/C23,0) -> 0.18404908
B24: 75% to 90% | C24: =SUMPRODUCT(--('Master Learner Profile'!K2:K1650>75),--('Master Learner Profile'!K2:K1650<=90)) -> 247 | D24: =SUMPRODUCT(--('Master Learner Profile'!K2:K1650>75),--('Master Learner Profile'!K2:K1650<=90),--('Master Learner Profile'!C2:C1650="Yes")) -> 9 | E24: =SUMPRODUCT(--('Master Learner Profile'!K2:K1650>75),--('Master Learner Profile'!K2:K1650<=90),--('Master Learner Profile'!C2:C1650="No")) -> 238 | F24: =IFERROR(D24/C24,0) -> 0.036437247
B25: 90% to 100% | C25: =SUMPRODUCT(--('Master Learner Profile'!K2:K1650>=90),--('Master Learner Profile'!K2:K1650<=100)) -> 818 | D25: =SUMPRODUCT(--('Master Learner Profile'!K2:K1650>=90),--('Master Learner Profile'!K2:K1650<=100),--('Master Learner Profile'!C2:C1650="Yes")) -> 7 | E25: =SUMPRODUCT(--('Master Learner Profile'!K2:K1650>=90),--('Master Learner Profile'!K2:K1650<=100),--('Master Learner Profile'!C2:C1650="No")) -> 811 | F25: =IFERROR(D25/C25,0) -> 0.0085574572
B26: TOTAL | C26: =SUM(C20:C25) -> 1649 | D26: =SUM(D20:D25) -> 281 | E26: =SUM(E20:E25) -> 1368 | F26: =IFERROR(D26/C26,0) -> 0.17040631
B28: Insight: Attendance and refund are almost perfectly inversely correlated. Above 90% attendance the refund rate collapses to under 1%. Below 25% attendance more than half of learners ask for a refund. This is not just because refunders stop attending after deciding to leave, the timing data shows most refund requests are raised within the first 14 days, before attendance has had time to decay much. So low Week 0 to Week 2 attendance is a real leading indicator, not a lagging one.
A31: 2.3 Refund rate by Dashboard Walkthrough (DBWT) completion
B33: DBWT status | C33: Total learners | D33: Refunders | E33: Non-refunders | F33: Refund rate % | G33: Read note
B34: Yes (DBWT done) | C34: =COUNTIF('Master Learner Profile'!L2:L1650,"Yes") -> 1275 | D34: =COUNTIFS('Master Learner Profile'!L2:L1650,"Yes",'Master Learner Profile'!C2:C1650,"Yes") -> 154 | E34: =COUNTIFS('Master Learner Profile'!L2:L1650,"Yes",'Master Learner Profile'!C2:C1650,"No") -> 1121 | F34: =IFERROR(D34/C34,0) -> 0.12078431 | G34: Did the dashboard walkthrough
B35: No (DBWT not done) | C35: =COUNTIF('Master Learner Profile'!L2:L1650,"No") -> 295 | D35: =COUNTIFS('Master Learner Profile'!L2:L1650,"No",'Master Learner Profile'!C2:C1650,"Yes") -> 127 | E35: =COUNTIFS('Master Learner Profile'!L2:L1650,"No",'Master Learner Profile'!C2:C1650,"No") -> 168 | F35: =IFERROR(D35/C35,0) -> 0.43050847 | G35: Walkthrough scheduled but did not show / declined
B36: Not Tracked (no DBWT row) | C36: =COUNTIF('Master Learner Profile'!L2:L1650,"Not Tracked") -> 79 | D36: =COUNTIFS('Master Learner Profile'!L2:L1650,"Not Tracked",'Master Learner Profile'!C2:C1650,"Yes") -> 0 | E36: =COUNTIFS('Master Learner Profile'!L2:L1650,"Not Tracked",'Master Learner Profile'!C2:C1650,"No") -> 79 | F36: =IFERROR(D36/C36,0) -> 0 | G36: Did not appear in DBWT sheet at all
B38: Insight: Skipping the Dashboard Walkthrough is the single strongest pre-class signal we have. Learners who skipped it refunded at roughly 3 to 4 times the rate of those who attended. Note also that the small group "Not Tracked" has effectively no refunds, which suggests these are likely late enrollees or learners onboarded outside the standard flow. Worth confirming with the ops team.
A40: 2.4 Refund rate by combined Risk Segment
B41: Risk segment combines two signals: (a) did the learner do the Dashboard Walkthrough, and (b) did they attend any Week 0 session. The segment is computed in column O of Master Learner Profile.
B43: Risk Segment | C43: Total learners | D43: Refunders | E43: Non-refunders | F43: Refund rate % | G43: % of all refunders
B44: 1: Critical (No DBWT + No Wk0) | C44: =COUNTIF('Master Learner Profile'!O2:O1650,"1: Critical (No DBWT + No Wk0)") -> 76 | D44: =COUNTIFS('Master Learner Profile'!O2:O1650,"1: Critical (No DBWT + No Wk0)",'Master Learner Profile'!C2:C1650,"Yes") -> 56 | E44: =COUNTIFS('Master Learner Profile'!O2:O1650,"1: Critical (No DBWT + No Wk0)",'Master Learner Profile'!C2:C1650,"No") -> 20 | F44: =IFERROR(D44/C44,0) -> 0.73684211 | G44: =IFERROR(D44/COUNTIF('Master Learner Profile'!C2:C1650,"Yes"),0) -> 0.19928826
B45: 2: High (No DBWT) | C45: =COUNTIF('Master Learner Profile'!O2:O1650,"2: High (No DBWT)") -> 219 | D45: =COUNTIFS('Master Learner Profile'!O2:O1650,"2: High (No DBWT)",'Master Learner Profile'!C2:C1650,"Yes") -> 71 | E45: =COUNTIFS('Master Learner Profile'!O2:O1650,"2: High (No DBWT)",'Master Learner Profile'!C2:C1650,"No") -> 148 | F45: =IFERROR(D45/C45,0) -> 0.32420091 | G45: =IFERROR(D45/COUNTIF('Master Learner Profile'!C2:C1650,"Yes"),0) -> 0.25266904
B46: 3: Elevated (No Wk0) | C46: =COUNTIF('Master Learner Profile'!O2:O1650,"3: Elevated (No Wk0)") -> 88 | D46: =COUNTIFS('Master Learner Profile'!O2:O1650,"3: Elevated (No Wk0)",'Master Learner Profile'!C2:C1650,"Yes") -> 37 | E46: =COUNTIFS('Master Learner Profile'!O2:O1650,"3: Elevated (No Wk0)",'Master Learner Profile'!C2:C1650,"No") -> 51 | F46: =IFERROR(D46/C46,0) -> 0.42045455 | G46: =IFERROR(D46/COUNTIF('Master Learner Profile'!C2:C1650,"Yes"),0) -> 0.1316726
B47: 4: Engaged Early | C47: =COUNTIF('Master Learner Profile'!O2:O1650,"4: Engaged Early") -> 1266 | D47: =COUNTIFS('Master Learner Profile'!O2:O1650,"4: Engaged Early",'Master Learner Profile'!C2:C1650,"Yes") -> 117 | E47: =COUNTIFS('Master Learner Profile'!O2:O1650,"4: Engaged Early",'Master Learner Profile'!C2:C1650,"No") -> 1149 | F47: =IFERROR(D47/C47,0) -> 0.092417062 | G47: =IFERROR(D47/COUNTIF('Master Learner Profile'!C2:C1650,"Yes"),0) -> 0.41637011
A50: 2.5 Data-driven strategies to reduce refund %
B52: # | C52: Strategy | D52: Why it works (data trail)
B53: 1 | C53: Make Dashboard Walkthrough effectively non-skippable | D53: Learners who did DBWT refunded at ~12% versus ~43% for those who skipped. That gap is too large to be coincidence. Make it required for class access (or delay first live class invite until DBWT is done), and have a sales-side call-back loop kicked off if DBWT remains undone within 48 hours of enrollment.
B54: 2 | C54: Build an early-warning trigger for "Critical" risk segment | D54: 76 learners fell into the No-DBWT-and-No-Week0 bucket. 56 of them (~74%) refunded. That is an extremely tight predictor. A simple rule that fires a personal outreach call within 72 hours of batch start for anyone in this segment would touch only ~5% of the cohort but cover ~20% of all refunders.
B55: 3 | C55: Tighten financial qualification at sales | D55: 21% of recorded refund reasons trace back to loan rejection or post-enrollment affordability shock. These are people we accepted into the program despite financial constraints we could have seen. A pre-enrollment soft credit pull, plus a "you must have a co-applicant on file" rule before DP is collected, would catch most of these before they become refund cases.
B56: 4 | C56: Fix expectation gaps at the sales pitch | D56: Course expectation mismatch covers ~11-15% of refund reasons, and the recurring complaints are very specific: "told it was 3-4 hrs, it is 9", "told class size 100, it is 220", "I am from QA / project management, this is too dev-heavy", "I wanted morning batch". A standardised pre-enrollment fact sheet plus a 5-minute role-fit screen at sales would prevent almost all of these.
B57: 5 | C57: Service-level commitment for refund-flag escalations | D57: The notes contain a distinct sub-pattern of "no revert from SP/PS, hence had to transfer due to delay in timelines, full refund approved by HP". These are refunds that were process failures, not learner failures. A 24-hour SLA on retention call-backs, with auto-escalation to a manager if missed, would recover the ~5% of refunds that fall in this bucket.
B58: 6 | C58: Course-pause defaulting | D58: Many notes show learners ask for a refund when life happens (medical, marriage, work crunch) and say "I will rejoin in 3-6 months". The pause feature exists but is being offered late or as a fallback. Default to "pause first, refund only if pause is declined" in the retention script. This converts some share of the 25% Personal/Family bucket from refunds to deferred enrollments.
B59: 7 | C59: Mentor-session nudge in Week 0 | D59: Mentor sessions are technically optional in the first two weeks, and only ~10% of learners book one. The booked group does not refund less than the unbooked group at the aggregate, so this is not a blanket lever, but a targeted nudge to learners showing low engagement in Week 0 (and where finances or expectations were unclear at enrollment) could create the human-touch moment that retention usually requires.

Sheet Q3 - Additional Hypotheses
B2: Q3: Additional hypotheses worth exploring
B4: These are hypotheses I could not fully resolve with the data shared, but the patterns were strong enough that they are worth investigating in a follow-up cut. Each one identifies the data that would be needed to confirm or kill it.
B6: # | C6: Hypothesis | D6: What I see in the data and why I think it matters | E6: How to test it | F6: Likely lever if true
B7: 1 | C7: PS or SP rep performance is a hidden driver | D7: A handful of PS / SP names recur across delayed-revert refund notes: cases where the refund reason ends up being "no response from SP, transferred due to breach in timelines". Some reps might also be over-promising at the sales stage. There is also a cluster of cases where the BDA who originally signed the learner is described as "not active in the system anymore". | E7: Tag every refund record with the SP/PS/BDA who owned it. Compute refund rate by rep. Look for reps with refund rates more than 1.5x the cohort average. Cross-check with average response time from the comms tracker. | F7: Targeted coaching, SLA enforcement, BDA handover process
B8: 2 | C8: Learners enrolled within 7 days of batch start are higher risk | D8: The Comms Tracker has a "Week" column going from T-4 (4 weeks before start) to T-1 (1 week before). Learners with comms only at T-1 had less time to do DBWT, attend Week 0, or even read the welcome sequence. Worth testing whether late enrollees refund at a higher rate. | E8: Use the comms T-week minimum per learner as a proxy for enrollment-to-start lead time. Bucket the cohort by lead time and compute refund rate per bucket. | F8: Cap late enrollments, or auto-defer to next batch
B9: 3 | C9: Learners from non-development backgrounds (QA, testing, project management, digital marketing, older non-IT professionals) refund at higher rates | D9: The free-text notes contain repeated mentions of QA, testing, project manager with 16 yrs exp, digital marketing background, sole proprietor of a petrol pump for 17 years, etc. A meaningful chunk of refunders had a fundamental fit problem that should have been caught at sales. | E9: Capture self-declared current role / years of experience at enrollment. Refund rate by background segment will tell us whether sales is qualifying these learners well enough. | F9: Better pre-sales fit screening, separate cohorts for non-dev backgrounds
B10: 4 | C10: Loan rejection causes both direct refunds AND a hidden retention drag | D10: Direct loan-rejection refunds are about 8% of cases. But the underlying issue (down payment paid, then loan rejected) probably causes anxiety even in learners who eventually do find a way to pay. Some financial-difficulty refunds may originate from a stressful loan saga. | E10: Tag every learner with whether their loan went through cleanly, was approved late, or was rejected and the gap was filled differently. Compare refund rate and engagement across the three groups. | F10: Pre-qualify loan eligibility before DP collection
B11: 5 | C11: Refund decision is largely made by Day 7-10, regardless of when it is filed | D11: Refund requests cluster heavily in days 7-14 after batch start. But the engagement collapse (no DBWT, no Week 0) happens before that. The decision is probably formed in the first week, and the request is filed once the learner is sure. | E11: Time-stamp the engagement signals and check the gap between "first signal of disengagement" (missed first class, missed DBWT) and "refund request filed". If average gap is more than 5 days we have a recoverable retention window we are not using. | F11: Day-3 and Day-7 personal outreach for at-risk learners
B12: 6 | C12: Comms open rate is not predictive but comms click rate might be | D12: Aggregate open rates are nearly identical for refunders (~68%) and non-refunders (~70%). Click rates are slightly lower for refunders (~14% vs ~16%). Opens are noisy (auto-pixel-loading inflates them), clicks are a much stronger intent signal. | E12: Look at click rate distribution by refund status. Test whether learners with zero clicks across the entire pre-batch comms cycle have elevated refund rates. | F12: Use zero-click learners as an additional risk flag
B13: 7 | C13: Pricing inconsistency erodes trust | D13: At least one note explicitly says "I got the course for 2.9L while my batchmates got it for 2.1L, so I lost interest". This is anecdotal here but could be a wider issue if discount structures are inconsistent. | E13: Look at fee paid distribution within the same batch. If standard deviation is high, that is a signal. Survey learners who heard about peers paying less. | F13: Standardised pricing or transparent discount tiers
B14: 8 | C14: Mentor sessions could be retention-positive if mandatory rather than optional | D14: Mentor sessions are described as recommended-but-optional for the first two weeks. Booking rate is low (~10%) and refund rate among bookers is barely different from non-bookers. But that may just be self-selection: the bookers were already engaged. A mandatory first mentor session in Week 1 might pull at-risk learners into a human conversation. | E14: Run an A/B in the next intake: half the cohort gets a scheduled-by-default mentor session in Week 1, half does not. Compare refund rates. | F14: Mandatory week-1 mentor session

Sheet Categorised Reasons
A1: Learner ID | B1: Refund Request Date | C1: Stage | D1: Within Refund Window | E1: Days from Batch Start | F1: Detailed Reason | G1: Refund Type | H1: Primary Reason
A2: AIX11549 | B2: 44768 | C2: Retained | D2: Within Refund window | E2: 14 | H2: Not Recorded
A3: AIX11402 | B3: 44767 | C3: Retained | D3: Within Refund window | E3: 13 | F3: The learner does not see the value in the program and believes he can achieve the outcomes on his own as he has people in the industry he knows being a developer for 4 yrs. He appreciated the quality of the program but says its not up to the monetary value. Informed by SP Mr. Varun Awasthi | G3: Full Refund | H3: Course Expectation / Curriculum Mismatch
A4: AIX10761 | B4: 44767 | C4: Retained | D4: Within Refund window | E4: 13 | H4: Not Recorded
A5: AIX10413 | B5: 44767 | C5: Retained | D5: Within Refund window | E5: 13 | H5: Not Recorded
A6: AIX11026 | B6: 44767 | C6: Retained | D6: Within Refund window | E6: 13 | H6: Not Recorded
A7: AIX10998 | B7: 44767 | C7: Retained | D7: Within Refund window | E7: 13 | H7: Not Recorded
A8: AIX11170 | B8: 44766 | C8: Retained | D8: Within Refund window | E8: 12 | H8: Not Recorded
A9: AIX11541 | B9: 44766 | C9: Retained | D9: Within Refund window | E9: 12 | H9: Not Recorded
A10: AIX10749 | B10: 44766 | C10: Retained | D10: Within Refund window | E10: 12 | H10: Not Recorded
A11: AIX10070 | B11: 44765 | C11: Retained | D11: Within Refund window | E11: 11 | H11: Not Recorded
A12: AIX11647 | B12: 44765 | C12: Retained | D12: Within Refund window | E12: 11 | H12: Not Recorded
A13: AIX10397 | B13: 44762 | C13: Retained | D13: Within Refund window | E13: 8 | H13: Not Recorded
A14: AIX11191 | B14: 44761 | C14: Retained | D14: Within Refund window | E14: 7 | H14: Not Recorded
A15: AIX11230 | B15: 44760 | C15: Retained | D15: Within Refund window | E15: 6 | H15: Not Recorded
... A21: AIX11044 | B21: 44757 | C21: Retained | D21: Within Refund window | E21: 3 | H21: Not Recorded
A22: AIX11619 | B22: 44754 | C22: Refund Closed | D22: Within Refund window | E22: 0 | F22: The learner has many interviews lined up and doesn't have time to attend classes. | G22: Full Refund | H22: New Job / Career Change / Relocation
A23: AIX10179 | B23: 44751 | C23: Retained | D23: Within Refund window | E23: -3 | H23: Not Recorded
A24: AIX11582 | B24: 44734 | C24: Retained | D24: Within Refund window | E24: -20 | H24: Not Recorded
A25: AIX11544 | B25: 44731 | C25: DB to be Deactived | D25: Within Refund window | E25: -23 | F25: The learner has some personal issues and hence wants to go ahead with the refund, this was initially retained from SPs but the cx was adamant for a refund | G25: Full Refund | H25: Personal / Family / Medical
A26: AIX11627 | B26: 44736 | C26: DB to be Deactived | D26: Within Refund window | E26: -18 | F26: His CC is not listed in no cost EMI and he doesn't want to go for the loan. Informed by Ms. Annu Kumari | G26: Full Refund | H26: Loan / NBFC / Financing Issue
A27: AIX10256 | B27: 44738 | C27: DB to be Deactived | D27: Within Refund window | E27: -16 | F27: This learner has some personal issues due to which he does not want to continue with us | G27: Full Refund | H27: Personal / Family / Medical
A28: AIX10097 | B28: 44739 | C28: DB to be Deactived | D28: Within Refund window | E28: -15 | F28: This learner has family issues due to which he cannot continue with us | G28: Full Refund | H28: Personal / Family / Medical
A29: AIX10010 | B29: 44739 | C29: DB to be Deactived | D29: Within Refund window | E29: -15 | F29: His loan is not getting sanctioned and he doesn't have any co applicant to give | G29: Full Refund | H29: Loan / NBFC / Financing Issue
A30: AIX10665 | B30: 44739 | C30: DB to be Deactived | D30: Within Refund window | E30: -15 | F30: No update from PS nor SP despite multiple reminder, this learner was initially retained by SP Mr. Kuppa Nagarjuna but later the cx followed up for a refund and hence had to be processed as request is wrp | G30: Full Refund | H30: Sales / Service Process Issue
A31: AIX10031 | B31: 44739 | C31: DB to be Deactived | D31: Within Refund window | E31: -15 | F31: This learner doesnt want to go ahead with loan process as his family members are not supporting. | G31: Full Refund | H31: Loan / NBFC / Financing Issue
A32: AIX10222 | B32: 44738 | C32: DB to be Deactived | D32: Within Refund window | E32: -16 | F32: This learner is going through some financial emergency at his end at the moment so he will not be able to go ahead currently. Informed by SP | G32: Full Refund | H32: Financial Difficulty / Affordability
A33: AIX10007 | B33: 44741 | C33: DB to be Deactived | D33: Within Refund window | E33: -13 | F33: This learner has some personal major issues due to which he could not proceed further. | G33: Full Refund | H33: Personal / Family / Medical
A34: AIX10012 | B34: 44741 | C34: DB to be Deactived | D34: Within Refund window | E34: -13 | F34: There was no proper update from the sales team regarding this cx. The learner kept following up and hence had to push further to finance team | G34: Full Refund | H34: Sales / Service Process Issue
A35: AIX10109 | B35: 44742 | C35: DB to be Deactived | D35: Within Refund window | E35: -12 | F35: The learner has some family issue currently, her mental state is not fine. She needs a break and might join after few months. | G35: Full Refund | H35: Personal / Family / Medical
A36: AIX11547 | B36: 44742 | C36: DB to be Deactived | D36: Within Refund window | E36: -12 | F36: The learner was never interested in the course. We changed his class timings and addressed whatever complains he had. We worked on that now he comes up with another reason saying instructor is less experienced than his experience. He doesn't want the course. Informed by PS Ms. Sonam Thakur | G36: Full Refund | H36: Course Expectation / Curriculum Mismatch
... A54: AIX10044 | B54: 44748 | C54: DB to be Deactived | D54: Within Refund window | E54: -6 | F54: This learner has some medical emergency as informed by SP Mr. Ujjwal Saini. | G54: Full Refund | H54: Personal / Family / Medical
A55: AIX10119 | B55: 44746 | C55: DB to be Deactived | D55: Within Refund window | F55: This learner feels the company policies are not that fair, the learner feels he was pressurized by the SPs to pay the amount. The learner felt extremely harassed for a whole day by constant calls from every direction to join and to pay right now. The learner just wants to get out of this course asap. Hence refund | G55: Full Refund | H55: Sales / Service Process Issue
A56: AIX11356 | B56: 44746 | C56: DB to be Deactived | D56: Within Refund window | F56: This learner does not want any third party loan | G56: Full Refund | H56: Other / Unclear
A57: AIX10261 | B57: 44746 | C57: DB to be Deactived | D57: Within Refund window | F57: This learner got an offer from a different organization, next day after her enrolment. Hence refund | G57: Full Refund | H57: New Job / Career Change / Relocation
A58: AIX10005 | B58: 44745 | C58: UTR Details to be shared to candidate | D58: Within Refund window | F58: Duplicate entry | H58: Sales / Service Process Issue
A59: AIX11468 | B59: 44745 | C59: DB to be Deactived | D59: Within Refund window | F59: personal reason | G59: Full Refund | H59: Personal / Family / Medical
A60: AIX10018 | B60: 44749 | C60: DB to be Deactived | D60: Within Refund window | E60: -5 | F60: The learner's father passed away and she is not in a state to move ahead. | G60: Full Refund | H60: Personal / Family / Medical
A61: AIX10112 | B61: 44749 | C61: DB to be Deactived | D61: Within Refund window | E61: -5 | F61: This learner has financial issues going on in his family, hence refund | G61: Full Refund | H61: Financial Difficulty / Affordability
A62: AIX10215 | B62: 44750 | C62: DB to be Deactived | D62: Within Refund window | E62: -4 | F62: cx is really adamant for a refund.informed by SP | G62: Full Refund | H62: Other / Unclear
A63: AIX10245 | B63: 44749 | C63: DB to be Deactived | D63: Within Refund window | E63: -5 | F63: The learner said he has financial issues right now plus other commitments where in he cannot adjust | G63: Full Refund | H63: Financial Difficulty / Affordability
A64: AIX10263 | B64: 44747 | C64: DB to be Deactived | D64: Within Refund window | E64: -7 | F64: PS Ms. Bandna Pathania informed that the cx is unwilling to make the rest of the payment citing personal issues, hence refund | G64: Full Refund | H64: Personal / Family / Medical
A65: AIX10110 | B65: 44750 | C65: DB to be Deactived | D65: Within Refund window | E65: -4 | F65: The learner will not be able to pay the loan as he already has an education loan going on. Also, he is the only person earning for the family whereas his family is even banking upon him for a house loan. He doesn't think it is the right time for him to start with another liability as he isn't ready for it. | G65: Full Refund | H65: Financial Difficulty / Affordability
A66: AIX10257 | B66: 44750 | C66: UTR Details to be shared to candidate | D66: Within Refund window | E66: -4 | G66: Full Refund | H66: Not Recorded
A67: AIX10196 | B67: 44751 | C67: DB to be Deactived | D67: Within Refund window | E67: -3 | G67: Full Refund | H67: Not Recorded
A68: AIX10067 | B68: 44751 | C68: DB to be Deactived | D68: Within Refund window | E68: -3 | F68: This learner is always complaining as per SP Mr. Lakshaya Sharma. This learner has a very casual attitude and is very unprofessional. | G68: Full Refund | H68: Course Expectation / Curriculum Mismatch
A69: AIX10198 | B69: 44751 | C69: DB to be Deactived | D69: Within Refund window | E69: -3 | F69: she is having a lot of additional work from the company and she won't be able to invest time into the same. | G69: Full Refund | H69: Time / Work Pressure
A70: AIX10214 | B70: 44746 | C70: DB to be Deactived | D70: Within Refund window | E70: -8 | F70: Cx occupied for this whole year and won't be able to continue with the course. | G70: Full Refund | H70: Time / Work Pressure
A71: AIX11306 | B71: 44751 | C71: DB to be Deactived | D71: Within Refund window | E71: -3 | F71: The learner got placed into jio at very good salary and wants to join after a year or two. He likes course but for now want to focus on new team and job. | G71: Full Refund | H71: New Job / Career Change / Relocation
A72: AIX11600 | B72: 44752 | C72: DB to be Deactived | D72: Within Refund window | E72: -2 | F72: 1) He has resigned his current employment - looking for a new job. Is on his notice period 2) What if he is not able to pay his EMI since he might take a few more months to get employed. 3) I work in cyber security, therefore I can't really relate to the themes. 4) 3 lakh is a lot of money, and I want to devote myself fully. 5) want to work on projects first - which we do it in the last so that he gets the Job | G72: Full Refund | H72: Financial Difficulty / Affordability
A73: AIX10006 | B73: 44753 | C73: DB to be Deactived | D73: Within Refund window | E73: -1 | F73: There is a mandatory training that he needs to take at his work place and he can't manage time to attend the classes. Tried convincing him for a pause but he feels even after 2-3 month he has to reconsider his decision of joining back.He wants to continue only when he can manage proper time. Also tried convincing for a ACS before taking up a final decision but he doesn't think that will help because he liked the classes he has attended.It's just that he doesn't want to do the course right now. Informed by PS Ms. Deepti Nair | G73: Full Refund | H73: Time / Work Pressure
A74: AIX10219 | B74: 44753 | C74: DB to be Deactived | D74: Within Refund window | E74: -1 | F74: This learner has some personal issues which he did not discuss with anyone, neither SP nor pS | G74: Full Refund | H74: Personal / Family / Medical
A75: AIX10169 | B75: 44753 | C75: DB to be Deactived | D75: Within Refund window | E75: -1 | F75: This learner has some serious medical issues as informed by Ms. Preethi Sasikumar, hence refund | G75: Full Refund | H75: Personal / Family / Medical
A76: AIX10037 | B76: 44753 | C76: DB to be Deactived | D76: Within Refund window | E76: -1 | F76: due to time restrictions and his 12- to 13-hour workdays | G76: Full Refund | H76: Time / Work Pressure
A77: AIX11361 | B77: 44753 | C77: DB to be Deactived | D77: Within Refund window | E77: -1 | F77: The learner has requested refund because due to Low Cibil Score & unavailability of Co-aaplicant we couldn't process the Loan Amount of INR 244000. | G77: Full Refund | H77: Loan / NBFC / Financing Issue
A78: AIX10237 | B78: 44754 | C78: DB to be Deactived | D78: Within Refund window | E78: 0 | F78: Learner has health issues and is not in a position to go ahead with the program due to the financial instability to handle medical bills, school fees for her kid and cannot be retained on the longer run to pay the remaining loan balance as well. | G78: Full Refund | H78: Personal / Family / Medical
A79: AIX10029 | B79: 44754 | C79: DB to be Deactived | D79: Within Refund window | E79: 0 | F79: This learner has an uncontrollable situation so understanding this we should refund this, informed by SP | G79: Full Refund | H79: Other / Unclear
... A150: AIX10218 | B150: 44760 | C150: DB to be Deactived | D150: Within Refund window | E150: 6 | F150: This cx can't be retained due to his time constraint, he is doing 4 jobs altogether and not getting time to pursue this course. And when PS Ms. Anjali Singh suggested ACs connect, he said he has good time management skills, That's why he is managing 4 jobs together. The learner doesn't need any alumni to suggest to him on time issues, and till 6 months he will be highly occupied, which made his mind drop out from the course. | G150: Full Refund | H150: Time / Work Pressure
A151: AIX10312 | B151: 44760 | D151: Within Refund window | E151: 6 | F151: The learnner is stubborn and stated that class is too fast since he is not comfortable in English so much and got a different onsite opportunity. | G151: Full Refund | H151: Course Expectation / Curriculum Mismatch
A152: AIX10004 | B152: 44760 | C152: DB to be Deactived | D152: Within Refund window | E152: 6 | F152: The learner is having heavy work schedule, hence refund | G152: Full Refund | H152: Time / Work Pressure
A153: AIX10267 | B153: 44760 | C153: DB to be Deactived | D153: Within Refund window | E153: 6 | F153: This learner is facing some medical issues and it is difficult for him to take the steps further to kindly initiate his refund as soon as possible. | G153: Full Refund | H153: Personal / Family / Medical
A154: AIX10176 | B154: 44760 | C154: DB to be Deactived | D154: Within Refund window | E154: 6 | F154: the learner is not able to make time for the classes | G154: Full Refund | H154: Other / Unclear
A155: AIX10246 | B155: 44760 | C155: Forwarded to finance | D155: Within Refund window | E155: 6 | F155: learner not able to join scaler academy due to some personal reasons. | G155: Full Refund | H155: Personal / Family / Medical
A156: AIX10317 | B156: 44760 | C156: Forwarded to finance | D156: Within Refund window | E156: 6 | F156: No response from SP or PS. Hence the reason for the refund is unknown | G156: Full Refund | H156: Sales / Service Process Issue
A157: AIX10172 | B157: 44760 | C157: Forwarded to finance | D157: Within Refund window | E157: 6 | F157: this learner has some issues regarding the loan and will not be able to apply for it. He said he would like to enroll for the next batch. Informed by Ms. Vaishnavi Kamat (sales poc) | G157: Full Refund | H157: Loan / NBFC / Financing Issue
A158: AIX10600 | B158: 44761 | C158: DB to be Deactived | D158: Within Refund window | E158: 7 | F158: No proper response from SP or PS, had to transfer due to delay in timelines | G158: Full Refund | H158: Sales / Service Process Issue
A159: AIX11096 | B159: 44761 | C159: DB to be Deactived | D159: Within Refund window | E159: 7 | F159: Learner is stringent on his decision of self preparation and is wanting a refund at any cost | G159: Full Refund | H159: Course Expectation / Curriculum Mismatch
A160: AIX10046 | B160: 44761 | C160: DB to be Deactived | D160: Within Refund window | E160: 7 | F160: Learner was onboarded for July batch but did not complete the finance process as he wanted to start classes from sept/oct & wanted EMI to start from oct itself. learner has 20k downpayment & wants EMI to start from oct month. So i have suggested him to go for refund & enroll again in sept, then we can ensure his EMI will also start from oct. Learner is interested but has genuine reason to start from sept as he is already taking teamcenter customization course. Please proceed with refund & will enrol the learner again when EMI can start from oct month. | G160: Full Refund | H160: Loan / NBFC / Financing Issue
A161: AIX11591 | B161: 44761 | C161: DB to be Deactived | D161: Within Refund window | E161: 7 | F161: 1) She has a personal loan of 10 Lacs and will not be able to take up any other loan for now. 2) She comes from a QA background, and she feels that the course is primarily for people in development roles. As she has no future plans of switching to a development role, she does not find herself suitable for the program. She enrolled with us on a trial basis. 3) She also added that the classes which are taking place during the trial period are not enough for her to make an informed decision as very basic concepts are being taught initially. Therefore, she is adamant about opting out of the program. | G161: Full Refund | H161: New Job / Career Change / Relocation
A162: AIX10336 | B162: 44761 | C162: DB to be Deactived | D162: Within Refund window | E162: 7 | F162: The lead is serving a notice period and says he cannot afford the EMI at this point in time | G162: Full Refund | H162: Financial Difficulty / Affordability
A163: AIX10033 | B163: 44761 | C163: Forwarded to finance | D163: Within Refund window | E163: 7 | F163: This learner is facing major issues to cope with the course as he is from Digital Marketing bg and after the classes, he is sure that he would not be able to continue in this IT field. | G163: Full Refund | H163: Personal / Family / Medical
... A286: AIX10577 | B286: 44767 | C286: Forwarded to finance | D286: Within Refund window | E286: 13 | F286: Cx is currently not able to adjust with the program, said will not be able to continue, | G286: Full Refund | H286: Other / Unclear
A287: AIX11628 | B287: 44767 | C287: Forwarded to finance | D287: Within Refund window | E287: 13 | F287: The Learner doesn't want to continue anymore since he got an offer recently | H287: New Job / Career Change / Relocation
A288: AIX11639 | B288: 44767 | C288: Final closure mail to be shared | D288: Within Refund window | E288: 13 | F288: This learner is purchasing property and hence cannot continue further with us | G288: Full Refund | H288: Other / Unclear
A289: AIX11031 | B289: 44767 | C289: Forwarded to finance | D289: Within Refund window | E289: 13 | F289: There is no other option as the learner says he has been placed as a Product Manager @ 30LPA and says he doesn't need the course for that | G289: Full Refund | H289: New Job / Career Change / Relocation
A290: AIX11018 | B290: 44768 | C290: Forwarded to finance | D290: Within Refund window | E290: 14 | F290: learmer unable to cope up with lectures plus got a new job where WFH is not an option. | G290: Full Refund | H290: New Job / Career Change / Relocation
A291: AIX11431 | B291: 44768 | C291: Forwarded to finance | D291: Within Refund window | E291: 14 | F291: Due to some personal reason cx not continue the course same bd team try to retain her but she is not answering the calls | G291: Full Refund | H291: Personal / Family / Medical
A292: AIX11481 | B292: 44768 | C292: Forwarded to finance | D292: Within Refund window | E292: 14 | F292: Due to some personal reason cx not continue the course and need refund back | G292: Full Refund | H292: Personal / Family / Medical
A293: AIX10142 | B293: 44768 | C293: Final closure mail to be shared | D293: Within Refund window | E293: 14 | F293: Unfortunately this learner cannot be retained. His father in law has got some ascending paralysis and couple of other points as well. SP Dewesh Begwani already tried his best to provide a solution but at the moment he is not in the correct mindset to continue with Scaler. | G293: Full Refund | H293: Personal / Family / Medical
A294: AIX10841 | B294: 44768 | C294: Forwarded to finance | D294: Within Refund window | E294: 14 | F294: She do not have enough bandwidth to dedicate ~12hrs a week she wants refund | G294: Full Refund | H294: Other / Unclear
A295: AIX10896 | B295: 44768 | C295: Final closure mail to be shared | D295: Within Refund window | E295: 14 | F295: Learner grandfather has diagnosed with stage 4 cancer and I can't be able to give time to work, family medical issues and scaler simultaneously. | G295: Full Refund | H295: Personal / Family / Medical
A296: AIX10942 | B296: 44768 | C296: Forwarded to finance | D296: Within Refund window | E296: 14 | F296: Cx don't not want to continue with the course. he attended the classes but after careful consideration found that it's not for him. | G296: Full Refund | H296: Course Expectation / Curriculum Mismatch
A297: AIX11466 | B297: 44768 | C297: Forwarded to finance | D297: Within Refund window | E297: 14 | F297: The loan was not approved by our NBFC | G297: Full Refund | H297: Loan / NBFC / Financing Issue
A298: AIX10291 | B298: 44768 | C298: Forwarded to finance | D298: Within Refund window | E298: 14 | F298: The learner was not sure before joining scaler , when she joined she realised that it didn't matched up to her expectations she said she got less time to understand what scaler has planned up for her, i tried probing her for alum connect so that we can help her a vision but she said it was earlier promised by her BDA and never done and now she has taken the final decision to take up the new job opportunity as Analyst and not continue in the development role and not continue with course as of now , she said she will comeback if she gets saturated at her new job | G298: Full Refund | H298: Course Expectation / Curriculum Mismatch
A299: AIX11648 | B299: 44769 | C299: Forwarded to finance | D299: Outside refund window | E299: 15 | F299: Cx attempted a couple of classes and hereby do not wish to continue with the course could not find the classes helpful enough to continue and thus he looking at other avenues for upskilling | G299: Full Refund | H299: New Job / Career Change / Relocation
... A305: AIX11376 | B305: 44771 | C305: Forwarded to finance | D305: Outside refund window | E305: 17 | F305: This learner is planning for doing his masters program. This learner raised the refund request to support on 23rd july (wrp) but support assigned it to refund team on 29th July. This was approved for a full refund by HP | G305: Full Refund | H305: Higher Studies / Govt Career

Sheet Master Learner Profile
A1: Batch | B1: Learner ID | C1: Refunded? | D1: Comms Delivered | E1: Comms Opened | F1: Comms Clicked | G1: Open Rate | H1: Click Rate | I1: Week 0 Sessions Attended | J1: Week 0 Avg Attendance | K1: Overall Attendance % | L1: Dashboard Walkthrough Done | M1: Mentor Sessions Booked | N1: Engagement Score | O1: Risk Segment
A2: Academy Intake X | B2: AIX10001 | C2: Yes | D2: 22 | E2: 6 | F2: 3 | G2: =IFERROR(E2/D2,0) -> 0.27272727 | H2: =IFERROR(F2/D2,0) -> 0.13636364 | I2: 1 | J2: 75.83 | K2: 18.96 | L2: Yes | M2: 0 | N2: =ROUND(IFERROR(K2/100,0)*0.6 + IF(L2="Yes",1,IF(L2="No",0,0.3))*0.25 + IFERROR(J2/100,0)*0.15,3) -> 0.478 | O2: =IF(AND(L2="No",I2=0),"1: Critical (No DBWT + No Wk0)",IF(L2="No","2: High (No DBWT)",IF(I2=0,"3: Elevated (No Wk0)","4: Engaged Early"))) -> 4: Engaged Early
A3: Academy Intake X | B3: AIX10002 | C3: Yes | D3: 2 | E3: 2 | F3: 1 | G3: =IFERROR(E3/D3,0) -> 1 | H3: =IFERROR(F3/D3,0) -> 0.5 | I3: 1 | J3: 85.42 | K3: 12.5 | L3: No | M3: 0 | N3: =ROUND(IFERROR(K3/100,0)*0.6 + IF(L3="Yes",1,IF(L3="No",0,0.3))*0.25 + IFERROR(J3/100,0)*0.15,3) -> 0.203 | O3: =IF(AND(L3="No",I3=0),"1: Critical (No DBWT + No Wk0)",IF(L3="No","2: High (No DBWT)",IF(I3=0,"3: Elevated (No Wk0)","4: Engaged Early"))) -> 2: High (No DBWT)
A4: Academy Intake X | B4: AIX10003 | C4: No | D4: 4 | E4: 2 | F4: 1 | G4: =IFERROR(E4/D4,0) -> 0.5 | H4: =IFERROR(F4/D4,0) -> 0.25 | I4: 0 | K4: 0 | L4: No | M4: 0 | N4: =ROUND(IFERROR(K4/100,0)*0.6 + IF(L4="Yes",1,IF(L4="No",0,0.3))*0.25 + IFERROR(J4/100,0)*0.15,3) -> 0 | O4: =IF(AND(L4="No",I4=0),"1: Critical (No DBWT + No Wk0)",IF(L4="No","2: High (No DBWT)",IF(I4=0,"3: Elevated (No Wk0)","4: Engaged Early"))) -> 1: Critical (No DBWT + No Wk0)
A5: Academy Intake X | B5: AIX10004 | C5: Yes | D5: 13 | E5: 11 | F5: 1 | G5: =IFERROR(E5/D5,0) -> 0.84615385 | H5: =IFERROR(F5/D5,0) -> 0.076923077 | I5: 1 | J5: 98.5153 | K5: 16.02 | L5: No | M5: 0 | N5: =ROUND(IFERROR(K5/100,0)*0.6 + IF(L5="Yes",1,IF(L5="No",0,0.3))*0.25 + IFERROR(J5/100,0)*0.15,3) -> 0.244 | O5: =IF(AND(L5="No",I5=0),"1: Critical (No DBWT + No Wk0)",IF(L5="No","2: High (No DBWT)",IF(I5=0,"3: Elevated (No Wk0)","4: Engaged Early"))) -> 2: High (No DBWT)
A6: Academy Intake X | B6: AIX10005 | C6: Yes | D6: 5 | E6: 5 | F6: 0 | G6: =IFERROR(E6/D6,0) -> 1 | H6: =IFERROR(F6/D6,0) -> 0 | I6: 0 | K6: 0.69 | L6: No | M6: 0 | N6: =ROUND(IFERROR(K6/100,0)*0.6 + IF(L6="Yes",1,IF(L6="No",0,0.3))*0.25 + IFERROR(J6/100,0)*0.15,3) -> 0.004 | O6: =IF(AND(L6="No",I6=0),"1: Critical (No DBWT + No Wk0)",IF(L6="No","2: High (No DBWT)",IF(I6=0,"3: Elevated (No Wk0)","4: Engaged Early"))) -> 1: Critical (No DBWT + No Wk0)
A7: Academy Intake X | B7: AIX10006 | C7: Yes | D7: 22 | E7: 8 | F7: 0 | G7: =IFERROR(E7/D7,0) -> 0.36363636 | H7: =IFERROR(F7/D7,0) -> 0 | I7: 2 | J7: 33.31315 | K7: 17.8 | L7: Yes | M7: 0 | N7: =ROUND(IFERROR(K7/100,0)*0.6 + IF(L7="Yes",1,IF(L7="No",0,0.3))*0.25 + IFERROR(J7/100,0)*0.15,3) -> 0.407 | O7: =IF(AND(L7="No",I7=0),"1: Critical (No DBWT + No Wk0)",IF(L7="No","2: High (No DBWT)",IF(I7=0,"3: Elevated (No Wk0)","4: Engaged Early"))) -> 4: Engaged Early
A8: Academy Intake X | B8: AIX10007 | C8: Yes | D8: 22 | E8: 20 | F8: 0 | G8: =IFERROR(E8/D8,0) -> 0.90909091 | H8: =IFERROR(F8/D8,0) -> 0 | I8: 0 | K8: 0 | L8: No | M8: 0 | N8: =ROUND(IFERROR(K8/100,0)*0.6 + IF(L8="Yes",1,IF(L8="No",0,0.3))*0.25 + IFERROR(J8/100,0)*0.15,3) -> 0 | O8: =IF(AND(L8="No",I8=0),"1: Critical (No DBWT + No Wk0)",IF(L8="No","2: High (No DBWT)",IF(I8=0,"3: Elevated (No Wk0)","4: Engaged Early"))) -> 1: Critical (No DBWT + No Wk0)
A9: Academy Intake X | B9: AIX10008 | C9: Yes | D9: 10 | E9: 9 | F9: 2 | G9: =IFERROR(E9/D9,0) -> 0.9 | H9: =IFERROR(F9/D9,0) -> 0.2 | I9: 2 | J9: 80.5078 | K9: 82.86 | L9: Yes | M9: 0 | N9: =ROUND(IFERROR(K9/100,0)*0.6 + IF(L9="Yes",1,IF(L9="No",0,0.3))*0.25 + IFERROR(J9/100,0)*0.15,3) -> 0.868 | O9: =IF(AND(L9="No",I9=0),"1: Critical (No DBWT + No Wk0)",IF(L9="No","2: High (No DBWT)",IF(I9=0,"3: Elevated (No Wk0)","4: Engaged Early"))) -> 4: Engaged Early
A10: Academy Intake X | B10: AIX10009 | C10: No | D10: 7 | E10: 7 | F10: 4 | G10: =IFERROR(E10/D10,0) -> 1 | H10: =IFERROR(F10/D10,0) -> 0.57142857 | I10: 0 | K10: 0 | L10: No | M10: 0 | N10: =ROUND(IFERROR(K10/100,0)*0.6 + IF(L10="Yes",1,IF(L10="No",0,0.3))*0.25 + IFERROR(J10/100,0)*0.15,3) -> 0 | O10: =IF(AND(L10="No",I10=0),"1: Critical (No DBWT + No Wk0)",IF(L10="No","2: High (No DBWT)",IF(I10=0,"3: Elevated (No Wk0)","4: Engaged Early"))) -> 1: Critical (No DBWT + No Wk0)
A11: Academy Intake X | B11: AIX10010 | C11: Yes | D11: 26 | E11: 22 | F11: 1 | G11: =IFERROR(E11/D11,0) -> 0.84615385 | H11: =IFERROR(F11/D11,0) -> 0.038461538 | I11: 0 | K11: 0 | L11: No | M11: 0 | N11: =ROUND(IFERROR(K11/100,0)*0.6 + IF(L11="Yes",1,IF(L11="No",0,0.3))*0.25 + IFERROR(J11/100,0)*0.15,3) -> 0 | O11: =IF(AND(L11="No",I11=0),"1: Critical (No DBWT + No Wk0)",IF(L11="No","2: High (No DBWT)",IF(I11=0,"3: Elevated (No Wk0)","4: Engaged Early"))) -> 1: Critical (No DBWT + No Wk0)
A12: Academy Intake X | B12: AIX10011 | C12: No | D12: 7 | E12: 5 | F12: 1 | G12: =IFERROR(E12/D12,0) -> 0.71428571 | H12: =IFERROR(F12/D12,0) -> 0.14285714 | I12: 1 | J12: 0.85 | K12: 0.12 | L12: No | M12: 0 | N12: =ROUND(IFERROR(K12/100,0)*0.6 + IF(L12="Yes",1,IF(L12="No",0,0.3))*0.25 + IFERROR(J12/100,0)*0.15,3) -> 0.002 | O12: =IF(AND(L12="No",I12=0),"1: Critical (No DBWT + No Wk0)",IF(L12="No","2: High (No DBWT)",IF(I12=0,"3: Elevated (No Wk0)","4: Engaged Early"))) -> 2: High (No DBWT)
A13: Academy Intake X | B13: AIX10012 | C13: Yes | D13: 21 | E13: 21 | F13: 2 | G13: =IFERROR(E13/D13,0) -> 1 | H13: =IFERROR(F13/D13,0) -> 0.095238095 | I13: 0 | K13: 0 | L13: No | M13: 0 | N13: =ROUND(IFERROR(K13/100,0)*0.6 + IF(L13="Yes",1,IF(L13="No",0,0.3))*0.25 + IFERROR(J13/100,0)*0.15,3) -> 0 | O13: =IF(AND(L13="No",I13=0),"1: Critical (No DBWT + No Wk0)",IF(L13="No","2: High (No DBWT)",IF(I13=0,"3: Elevated (No Wk0)","4: Engaged Early"))) -> 1: Critical (No DBWT + No Wk0)
A14: Academy Intake X | B14: AIX10013 | C14: No | D14: 23 | E14: 12 | F14: 2 | G14: =IFERROR(E14/D14,0) -> 0.52173913 | H14: =IFERROR(F14/D14,0) -> 0.086956522 | I14: 2 | J14: 93.05765 | K14: 98.38 | L14: Yes | M14: 0 | N14: =ROUND(IFERROR(K14/100,0)*0.6 + IF(L14="Yes",1,IF(L14="No",0,0.3))*0.25 + IFERROR(J14/100,0)*0.15,3) -> 0.98 | O14: =IF(AND(L14="No",I14=0),"1: Critical (No DBWT + No Wk0)",IF(L14="No","2: High (No DBWT)",IF(I14=0,"3: Elevated (No Wk0)","4: Engaged Early"))) -> 4: Engaged Early
A15: Academy Intake X | B15: AIX10014 | C15: Yes | D15: 24 | E15: 17 | F15: 0 | G15: =IFERROR(E15/D15,0) -> 0.70833333 | H15: =IFERROR(F15/D15,0) -> 0 | I15: 0 | K15: 0 | L15: No | M15: 0 | N15: =ROUND(IFERROR(K15/100,0)*0.6 + IF(L15="Yes",1,IF(L15="No",0,0.3))*0.25 + IFERROR(J15/100,0)*0.15,3) -> 0 | O15: =IF(AND(L15="No",I15=0),"1: Critical (No DBWT + No Wk0)",IF(L15="No","2: High (No DBWT)",IF(I15=0,"3: Elevated (No Wk0)","4: Engaged Early"))) -> 1: Critical (No DBWT + No Wk0)
A16: Academy Intake X | B16: AIX10015 | C16: No | D16: 13 | E16: 11 | F16: 3 | G16: =IFERROR(E16/D16,0) -> 0.84615385 | H16: =IFERROR(F16/D16,0) -> 0.23076923 | I16: 2 | J16: 87.17515 | K16: 97.37 | L16: Yes | M16: 0 | N16: =ROUND(IFERROR(K16/100,0)*0.6 + IF(L16="Yes",1,IF(L16="No",0,0.3))*0.25 + IFERROR(J16/100,0)*0.15,3) -> 0.965 | O16: =IF(AND(L16="No",I16=0),"1: Critical (No DBWT + No Wk0)",IF(L16="No","2: High (No DBWT)",IF(I16=0,"3: Elevated (No Wk0)","4: Engaged Early"))) -> 4: Engaged Early
A17: Academy Intake X | B17: AIX10016 | C17: No | D17: 20 | E17: 17 | F17: 1 | G17: =IFERROR(E17/D17,0) -> 0.85 | H17: =IFERROR(F17/D17,0) -> 0.05 | I17: 2 | J17: 64.68235 | K17: 42.89 | L17: Yes | M17: 0 | N17: =ROUND(IFERROR(K17/100,0)*0.6 + IF(L17="Yes",1,IF(L17="No",0,0.3))*0.25 + IFERROR(J17/100,0)*0.15,3) -> 0.604 | O17: =IF(AND(L17="No",I17=0),"1: Critical (No DBWT + No Wk0)",IF(L17="No","2: High (No DBWT)",IF(I17=0,"3: Elevated (No Wk0)","4: Engaged Early"))) -> 4: Engaged Early
A18: Academy Intake X | B18: AIX10017 | C18: No | D18: 13 | E18: 7 | F18: 1 | G18: =IFERROR(E18/D18,0) -> 0.53846154 | H18: =IFERROR(F18/D18,0) -> 0.076923077 | I18: 2 | J18: 94.81025 | K18: 57.26 | L18: Yes | M18: 0 | N18: =ROUND(IFERROR(K18/100,0)*0.6 + IF(L18="Yes",1,IF(L18="No",0,0.3))*0.25 + IFERROR(J18/100,0)*0.15,3) -> 0.736 | O18: =IF(AND(L18="No",I18=0),"1: Critical (No DBWT + No Wk0)",IF(L18="No","2: High (No DBWT)",IF(I18=0,"3: Elevated (No Wk0)","4: Engaged Early"))) -> 4: Engaged Early
A19: Academy Intake X | B19: AIX10018 | C19: Yes | D19: 23 | E19: 18 | F19: 0 | G19: =IFERROR(E19/D19,0) -> 0.7826087 | H19: =IFERROR(F19/D19,0) -> 0 | I19: 0 | K19: 0 | L19: No | M19: 0 | N19: =ROUND(IFERROR(K19/100,0)*0.6 + IF(L19="Yes",1,IF(L19="No",0,0.3))*0.25 + IFERROR(J19/100,0)*0.15,3) -> 0 | O19: =IF(AND(L19="No",I19=0),"1: Critical (No DBWT + No Wk0)",IF(L19="No","2: High (No DBWT)",IF(I19=0,"3: Elevated (No Wk0)","4: Engaged Early"))) -> 1: Critical (No DBWT + No Wk0)
A20: Academy Intake X | B20: AIX10019 | C20: Yes | D20: 6 | E20: 3 | F20: 0 | G20: =IFERROR(E20/D20,0) -> 0.5 | H20: =IFERROR(F20/D20,0) -> 0 | I20: 0 | K20: 0.05 | L20: Yes | M20: 0 | N20: =ROUND(IFERROR(K20/100,0)*0.6 + IF(L20="Yes",1,IF(L20="No",0,0.3))*0.25 + IFERROR(J20/100,0)*0.15,3) -> 0.25 | O20: =IF(AND(L20="No",I20=0),"1: Critical (No DBWT + No Wk0)",IF(L20="No","2: High (No DBWT)",IF(I20=0,"3: Elevated (No Wk0)","4: Engaged Early"))) -> 3: Elevated (No Wk0)
A21: Academy Intake X | B21: AIX10020 | C21: No | D21: 0 | E21: 0 | F21: 0 | G21: =IFERROR(E21/D21,0) -> 0 | H21: =IFERROR(F21/D21,0) -> 0 | I21: 0 | K21: 1.09 | L21: No | M21: 0 | N21: =ROUND(IFERROR(K21/100,0)*0.6 + IF(L21="Yes",1,IF(L21="No",0,0.3))*0.25 + IFERROR(J21/100,0)*0.15,3) -> 0.007 | O21: =IF(AND(L21="No",I21=0),"1: Critical (No DBWT + No Wk0)",IF(L21="No","2: High (No DBWT)",IF(I21=0,"3: Elevated (No Wk0)","4: Engaged Early"))) -> 1: Critical (No DBWT + No Wk0)
A22: Academy Intake X | B22: AIX10021 | C22: No | D22: 7 | E22: 2 | F22: 0 | G22: =IFERROR(E22/D22,0) -> 0.28571429 | H22: =IFERROR(F22/D22,0) -> 0 | I22: 2 | J22: 79.33595 | K22: 95.21 | L22: Yes | M22: 0 | N22: =ROUND(IFERROR(K22/100,0)*0.6 + IF(L22="Yes",1,IF(L22="No",0,0.3))*0.25 + IFERROR(J22/100,0)*0.15,3) -> 0.94 | O22: =IF(AND(L22="No",I22=0),"1: Critical (No DBWT + No Wk0)",IF(L22="No","2: High (No DBWT)",IF(I22=0,"3: Elevated (No Wk0)","4: Engaged Early"))) -> 4: Engaged Early
A23: Academy Intake X | B23: AIX10022 | C23: No | D23: 3 | E23: 2 | F23: 0 | G23: =IFERROR(E23/D23,0) -> 0.66666667 | H23: =IFERROR(F23/D23,0) -> 0 | I23: 1 | J23: 34.46 | K23: 10.37 | L23: Yes | M23: 0 | N23: =ROUND(IFERROR(K23/100,0)*0.6 + IF(L23="Yes",1,IF(L23="No",0,0.3))*0.25 + IFERROR(J23/100,0)*0.15,3) -> 0.364 | O23: =IF(AND(L23="No",I23=0),"1: Critical (No DBWT + No Wk0)",IF(L23="No","2: High (No DBWT)",IF(I23=0,"3: Elevated (No Wk0)","4: Engaged Early"))) -> 4: Engaged Early
A24: Academy Intake X | B24: AIX10023 | C24: No | D24: 21 | E24: 18 | F24: 6 | G24: =IFERROR(E24/D24,0) -> 0.85714286 | H24: =IFERROR(F24/D24,0) -> 0.28571429 | I24: 2 | J24: 97.27395 | K24: 88.89 | L24: Yes | M24: 0 | N24: =ROUND(IFERROR(K24/100,0)*0.6 + IF(L24="Yes",1,IF(L24="No",0,0.3))*0.25 + IFERROR(J24/100,0)*0.15,3) -> 0.929 | O24: =IF(AND(L24="No",I24=0),"1: Critical (No DBWT + No Wk0)",IF(L24="No","2: High (No DBWT)",IF(I24=0,"3: Elevated (No Wk0)","4: Engaged Early"))) -> 4: Engaged Early
A25: Academy Intake X | B25: AIX10024 | C25: No | D25: 5 | E25: 5 | F25: 0 | G25: =IFERROR(E25/D25,0) -> 1 | H25: =IFERROR(F25/D25,0) -> 0 | I25: 0 | K25: 0 | L25: No | M25: 0 | N25: =ROUND(IFERROR(K25/100,0)*0.6 + IF(L25="Yes",1,IF(L25="No",0,0.3))*0.25 + IFERROR(J25/100,0)*0.15,3) -> 0 | O25: =IF(AND(L25="No",I25=0),"1: Critical (No DBWT + No Wk0)",IF(L25="No","2: High (No DBWT)",IF(I25=0,"3: Elevated (No Wk0)","4: Engaged Early"))) -> 1: Critical (No DBWT + No Wk0)
A26: Academy Intake X | B26: AIX10025 | C26: No | D26: 0 | E26: 0 | F26: 0 | G26: =IFERROR(E26/D26,0) -> 0 | H26: =IFERROR(F26/D26,0) -> 0 | I26: 0 | K26: 49.93 | L26: Not Tracked | M26: 0 | N26: =ROUND(IFERROR(K26/100,0)*0.6 + IF(L26="Yes",1,IF(L26="No",0,0.3))*0.25 + IFERROR(J26/100,0)*0.15,3) -> 0.375 | O26: =IF(AND(L26="No",I26=0),"1: Critical (No DBWT + No Wk0)",IF(L26="No","2: High (No DBWT)",IF(I26=0,"3: Elevated (No Wk0)","4: Engaged Early"))) -> 3: Elevated (No Wk0)
A27: Academy Intake X | B27: AIX10026 | C27: No | D27: 23 | E27: 22 | F27: 3 | G27: =IFERROR(E27/D27,0) -> 0.95652174 | H27: =IFERROR(F27/D27,0) -> 0.13043478 | I27: 2 | J27: 48.30066 | K27: 82.13 | L27: Yes | M27: 0 | N27: =ROUND(IFERROR(K27/100,0)*0.6 + IF(L27="Yes",1,IF(L27="No",0,0.3))*0.25 + IFERROR(J27/100,0)*0.15,3) -> 0.815 | O27: =IF(AND(L27="No",I27=0),"1: Critical (No DBWT + No Wk0)",IF(L27="No","2: High (No DBWT)",IF(I27=0,"3: Elevated (No Wk0)","4: Engaged Early"))) -> 4: Engaged Early
A28: Academy Intake X | B28: AIX10027 | C28: No | D28: 10 | E28: 6 | F28: 0 | G28: =IFERROR(E28/D28,0) -> 0.6 | H28: =IFERROR(F28/D28,0) -> 0 | I28: 1 | J28: 9.8751 | K28: 12.58 | L28: Yes | M28: 0 | N28: =ROUND(IFERROR(K28/100,0)*0.6 + IF(L28="Yes",1,IF(L28="No",0,0.3))*0.25 + IFERROR(J28/100,0)*0.15,3) -> 0.34 | O28: =IF(AND(L28="No",I28=0),"1: Critical (No DBWT + No Wk0)",IF(L28="No","2: High (No DBWT)",IF(I28=0,"3: Elevated (No Wk0)","4: Engaged Early"))) -> 4: Engaged Early
A29: Academy Intake X | B29: AIX10028 | C29: No | D29: 13 | E29: 8 | F29: 2 | G29: =IFERROR(E29/D29,0) -> 0.61538462 | H29: =IFERROR(F29/D29,0) -> 0.15384615 | I29: 2 | J29: 94.445 | K29: 100 | L29: Yes | M29: 0 | N29: =ROUND(IFERROR(K29/100,0)*0.6 + IF(L29="Yes",1,IF(L29="No",0,0.3))*0.25 + IFERROR(J29/100,0)*0.15,3) -> 0.992 | O29: =IF(AND(L29="No",I29=0),"1: Critical (No DBWT + No Wk0)",IF(L29="No","2: High (No DBWT)",IF(I29=0,"3: Elevated (No Wk0)","4: Engaged Early"))) -> 4: Engaged Early
A30: Academy Intake X | B30: AIX10029 | C30: Yes | D30: 10 | E30: 10 | F30: 3 | G30: =IFERROR(E30/D30,0) -> 1 | H30: =IFERROR(F30/D30,0) -> 0.3 | I30: 1 | J30: 7.02 | K30: 9.39 | L30: No | M30: 0 | N30: =ROUND(IFERROR(K30/100,0)*0.6 + IF(L30="Yes",1,IF(L30="No",0,0.3))*0.25 + IFERROR(J30/100,0)*0.15,3) -> 0.067 | O30: =IF(AND(L30="No",I30=0),"1: Critical (No DBWT + No Wk0)",IF(L30="No","2: High (No DBWT)",IF(I30=0,"3: Elevated (No Wk0)","4: Engaged Early"))) -> 2: High (No DBWT)
A31: Academy Intake X | B31: AIX10030 | C31: No | D31: 10 | E31: 8 | F31: 2 | G31: =IFERROR(E31/D31,0) -> 0.8 | H31: =IFERROR(F31/D31,0) -> 0.2 | I31: 2 | J31: 99.84665 | K31: 94.24 | L31: Yes | M31: 0 | N31: =ROUND(IFERROR(K31/100,0)*0.6 + IF(L31="Yes",1,IF(L31="No",0,0.3))*0.25 + IFERROR(J31/100,0)*0.15,3) -> 0.965 | O31: =IF(AND(L31="No",I31=0),"1: Critical (No DBWT + No Wk0)",IF(L31="No","2: High (No DBWT)",IF(I31=0,"3: Elevated (No Wk0)","4: Engaged Early"))) -> 4: Engaged Early
A32: Academy Intake X | B32: AIX10031 | C32: Yes | D32: 3 | E32: 3 | F32: 0 | G32: =IFERROR(E32/D32,0) -> 1 | H32: =IFERROR(F32/D32,0) -> 0 | I32: 0 | K32: 0 | L32: No | M32: 0 | N32: =ROUND(IFERROR(K32/100,0)*0.6 + IF(L32="Yes",1,IF(L32="No",0,0.3))*0.25 + IFERROR(J32/100,0)*0.15,3) -> 0 | O32: =IF(AND(L32="No",I32=0),"1: Critical (No DBWT + No Wk0)",IF(L32="No","2: High (No DBWT)",IF(I32=0,"3: Elevated (No Wk0)","4: Engaged Early"))) -> 1: Critical (No DBWT + No Wk0)
A33: Academy Intake X | B33: AIX10032 | C33: No | D33: 13 | E33: 1 | F33: 0 | G33: =IFERROR(E33/D33,0) -> 0.076923077 | H33: =IFERROR(F33/D33,0) -> 0 | I33: 2 | J33: 99.75255 | K33: 100 | L33: Yes | M33: 0 | N33: =ROUND(IFERROR(K33/100,0)*0.6 + IF(L33="Yes",1,IF(L33="No",0,0.3))*0.25 + IFERROR(J33/100,0)*0.15,3) -> 1 | O33: =IF(AND(L33="No",I33=0),"1: Critical (No DBWT + No Wk0)",IF(L33="No","2: High (No DBWT)",IF(I33=0,"3: Elevated (No Wk0)","4: Engaged Early"))) -> 4: Engaged Early
A34: Academy Intake X | B34: AIX10033 | C34: Yes | D34: 13 | E34: 0 | F34: 0 | G34: =IFERROR(E34/D34,0) -> 0 | H34: =IFERROR(F34/D34,0) -> 0 | I34: 2 | J34: 68.11475 | K34: 16.84 | L34: Yes | M34: 0 | N34: =ROUND(IFERROR(K34/100,0)*0.6 + IF(L34="Yes",1,IF(L34="No",0,0.3))*0.25 + IFERROR(J34/100,0)*0.15,3) -> 0.453 | O34: =IF(AND(L34="No",I34=0),"1: Critical (No DBWT + No Wk0)",IF(L34="No","2: High (No DBWT)",IF(I34=0,"3: Elevated (No Wk0)","4: Engaged Early"))) -> 4: Engaged Early
A35: Academy Intake X | B35: AIX10034 | C35: No | D35: 15 | E35: 9 | F35: 1 | G35: =IFERROR(E35/D35,0) -> 0.6 | H35: =IFERROR(F35/D35,0) -> 0.066666667 | I35: 2 | J35: 88.03625 | K35: 100 | L35: Yes | M35: 0 | N35: =ROUND(IFERROR(K35/100,0)*0.6 + IF(L35="Yes",1,IF(L35="No",0,0.3))*0.25 + IFERROR(J35/100,0)*0.15,3) -> 0.982 | O35: =IF(AND(L35="No",I35=0),"1: Critical (No DBWT + No Wk0)",IF(L35="No","2: High (No DBWT)",IF(I35=0,"3: Elevated (No Wk0)","4: Engaged Early"))) -> 4: Engaged Early
A36: Academy Intake X | B36: AIX10035 | C36: No | D36: 22 | E36: 12 | F36: 1 | G36: =IFERROR(E36/D36,0) -> 0.54545455 | H36: =IFERROR(F36/D36,0) -> 0.045454545 | I36: 2 | J36: 85.01325 | K36: 34.52 | L36: Yes | M36: 0 | N36: =ROUND(IFERROR(K36/100,0)*0.6 + IF(L36="Yes",1,IF(L36="No",0,0.3))*0.25 + IFERROR(J36/100,0)*0.15,3) -> 0.585 | O36: =IF(AND(L36="No",I36=0),"1: Critical (No DBWT + No Wk0)",IF(L36="No","2: High (No DBWT)",IF(I36=0,"3: Elevated (No Wk0)","4: Engaged Early"))) -> 4: Engaged Early
A37: Academy Intake X | B37: AIX10036 | C37: No | D37: 17 | E37: 5 | F37: 0 | G37: =IFERROR(E37/D37,0) -> 0.29411765 | H37: =IFERROR(F37/D37,0) -> 0 | I37: 2 | J37: 94.79165 | K37: 100 | L37: Yes | M37: 0 | N37: =ROUND(IFERROR(K37/100,0)*0.6 + IF(L37="Yes",1,IF(L37="No",0,0.3))*0.25 + IFERROR(J37/100,0)*0.15,3) -> 0.992 | O37: =IF(AND(L37="No",I37=0),"1: Critical (No DBWT + No Wk0)",IF(L37="No","2: High (No DBWT)",IF(I37=0,"3: Elevated (No Wk0)","4: Engaged Early"))) -> 4: Engaged Early
A38: Academy Intake X | B38: AIX10037 | C38: Yes | D38: 4 | E38: 4 | F38: 2 | G38: =IFERROR(E38/D38,0) -> 1 | H38: =IFERROR(F38/D38,0) -> 0.5 | I38: 1 | J38: 38.61 | K38: 9.65 | L38: Yes | M38: 0 | N38: =ROUND(IFERROR(K38/100,0)*0.6 + IF(L38="Yes",1,IF(L38="No",0,0.3))*0.25 + IFERROR(J38/100,0)*0.15,3) -> 0.366 | O38: =IF(AND(L38="No",I38=0),"1: Critical (No DBWT + No Wk0)",IF(L38="No","2: High (No DBWT)",IF(I38=0,"3: Elevated (No Wk0)","4: Engaged Early"))) -> 4: Engaged Early
A39: Academy Intake X | B39: AIX10038 | C39: Yes | D39: 15 | E39: 10 | F39: 0 | G39: =IFERROR(E39/D39,0) -> 0.66666667 | H39: =IFERROR(F39/D39,0) -> 0 | I39: 0 | K39: 0 | L39: Yes | M39: 0 | N39: =ROUND(IFERROR(K39/100,0)*0.6 + IF(L39="Yes",1,IF(L39="No",0,0.3))*0.25 + IFERROR(J39/100,0)*0.15,3) -> 0.25 | O39: =IF(AND(L39="No",I39=0),"1: Critical (No DBWT + No Wk0)",IF(L39="No","2: High (No DBWT)",IF(I39=0,"3: Elevated (No Wk0)","4: Engaged Early"))) -> 3: Elevated (No Wk0)
A40: Academy Intake X | B40: AIX10039 | C40: No | D40: 13 | E40: 7 | F40: 1 | G40: =IFERROR(E40/D40,0) -> 0.53846154 | H40: =IFERROR(F40/D40,0) -> 0.076923077 | I40: 1 | J40: 63.56 | K40: 53.3 | L40: Yes | M40: 0 | N40: =ROUND(IFERROR(K40/100,0)*0.6 + IF(L40="Yes",1,IF(L40="No",0,0.3))*0.25 + IFERROR(J40/100,0)*0.15,3) -> 0.665 | O40: =IF(AND(L40="No",I40=0),"1: Critical (No DBWT + No Wk0)",IF(L40="No","2: High (No DBWT)",IF(I40=0,"3: Elevated (No Wk0)","4: Engaged Early"))) -> 4: Engaged Early
A41: Academy Intake X | B41: AIX10040 | C41: No | D41: 23 | E41: 22 | F41: 0 | G41: =IFERROR(E41/D41,0) -> 0.95652174 | H41: =IFERROR(F41/D41,0) -> 0 | I41: 1 | J41: 78.11 | K41: 69.87 | L41: Yes | M41: 0 | N41: =ROUND(IFERROR(K41/100,0)*0.6 + IF(L41="Yes",1,IF(L41="No",0,0.3))*0.25 + IFERROR(J41/100,0)*0.15,3) -> 0.786 | O41: =IF(AND(L41="No",I41=0),"1: Critical (No DBWT + No Wk0)",IF(L41="No","2: High (No DBWT)",IF(I41=0,"3: Elevated (No Wk0)","4: Engaged Early"))) -> 4: Engaged Early
A42: Academy Intake X | B42: AIX10041 | C42: Yes | D42: 4 | E42: 0 | F42: 0 | G42: =IFERROR(E42/D42,0) -> 0 | H42: =IFERROR(F42/D42,0) -> 0 | I42: 0 | K42: 0 | L42: No | M42: 0 | N42: =ROUND(IFERROR(K42/100,0)*0.6 + IF(L42="Yes",1,IF(L42="No",0,0.3))*0.25 + IFERROR(J42/100,0)*0.15,3) -> 0 | O42: =IF(AND(L42="No",I42=0),"1: Critical (No DBWT + No Wk0)",IF(L42="No","2: High (No DBWT)",IF(I42=0,"3: Elevated (No Wk0)","4: Engaged Early"))) -> 1: Critical (No DBWT + No Wk0)
A43: Academy Intake X | B43: AIX10042 | C43: No | D43: 26 | E43: 9 | F43: 0 | G43: =IFERROR(E43/D43,0) -> 0.34615385 | H43: =IFERROR(F43/D43,0) -> 0 | I43: 0 | K43: 0 | L43: No | M43: 0 | N43: =ROUND(IFERROR(K43/100,0)*0.6 + IF(L43="Yes",1,IF(L43="No",0,0.3))*0.25 + IFERROR(J43/100,0)*0.15,3) -> 0 | O43: =IF(AND(L43="No",I43=0),"1: Critical (No DBWT + No Wk0)",IF(L43="No","2: High (No DBWT)",IF(I43=0,"3: Elevated (No Wk0)","4: Engaged Early"))) -> 1: Critical (No DBWT + No Wk0)
A44: Academy Intake X | B44: AIX10043 | C44: Yes | D44: 23 | E44: 12 | F44: 0 | G44: =IFERROR(E44/D44,0) -> 0.52173913 | H44: =IFERROR(F44/D44,0) -> 0 | I44: 0 | K44: 0 | L44: No | M44: 0 | N44: =ROUND(IFERROR(K44/100,0)*0.6 + IF(L44="Yes",1,IF(L44="No",0,0.3))*0.25 + IFERROR(J44/100,0)*0.15,3) -> 0 | O44: =IF(AND(L44="No",I44=0),"1: Critical (No DBWT + No Wk0)",IF(L44="No","2: High (No DBWT)",IF(I44=0,"3: Elevated (No Wk0)","4: Engaged Early"))) -> 1: Critical (No DBWT + No Wk0)
A45: Academy Intake X | B45: AIX10044 | C45: Yes | D45: 25 | E45: 15 | F45: 3 | G45: =IFERROR(E45/D45,0) -> 0.6 | H45: =IFERROR(F45/D45,0) -> 0.12 | I45: 0 | K45: 0 | L45: Yes | M45: 0 | N45: =ROUND(IFERROR(K45/100,0)*0.6 + IF(L45="Yes",1,IF(L45="No",0,0.3))*0.25 + IFERROR(J45/100,0)*0.15,3) -> 0.25 | O45: =IF(AND(L45="No",I45=0),"1: Critical (No DBWT + No Wk0)",IF(L45="No","2: High (No DBWT)",IF(I45=0,"3: Elevated (No Wk0)","4: Engaged Early"))) -> 3: Elevated (No Wk0)
A46: Academy Intake X | B46: AIX10045 | C46: Yes | D46: 10 | E46: 7 | F46: 0 | G46: =IFERROR(E46/D46,0) -> 0.7 | H46: =IFERROR(F46/D46,0) -> 0 | I46: 0 | K46: 0 | L46: No | M46: 0 | N46: =ROUND(IFERROR(K46/100,0)*0.6 + IF(L46="Yes",1,IF(L46="No",0,0.3))*0.25 + IFERROR(J46/100,0)*0.15,3) -> 0 | O46: =IF(AND(L46="No",I46=0),"1: Critical (No DBWT + No Wk0)",IF(L46="No","2: High (No DBWT)",IF(I46=0,"3: Elevated (No Wk0)","4: Engaged Early"))) -> 1: Critical (No DBWT + No Wk0)
A47: Academy Intake X | B47: AIX10046 | C47: Yes | D47: 15 | E47: 2 | F47: 0 | G47: =IFERROR(E47/D47,0) -> 0.13333333 | H47: =IFERROR(F47/D47,0) -> 0 | I47: 0 | K47: 0 | L47: Yes | M47: 0 | N47: =ROUND(IFERROR(K47/100,0)*0.6 + IF(L47="Yes",1,IF(L47="No",0,0.3))*0.25 + IFERROR(J47/100,0)*0.15,3) -> 0.25 | O47: =IF(AND(L47="No",I47=0),"1: Critical (No DBWT + No Wk0)",IF(L47="No","2: High (No DBWT)",IF(I47=0,"3: Elevated (No Wk0)","4: Engaged Early"))) -> 3: Elevated (No Wk0)
A48: Academy Intake X | B48: AIX10047 | C48: No | D48: 0 | E48: 0 | F48: 0 | G48: =IFERROR(E48/D48,0) -> 0 | H48: =IFERROR(F48/D48,0) -> 0 | I48: 0 | K48: 0 | L48: Not Tracked | M48: 0 | N48: =ROUND(IFERROR(K48/100,0)*0.6 + IF(L48="Yes",1,IF(L48="No",0,0.3))*0.25 + IFERROR(J48/100,0)*0.15,3) -> 0.075 | O48: =IF(AND(L48="No",I48=0),"1: Critical (No DBWT + No Wk0)",IF(L48="No","2: High (No DBWT)",IF(I48=0,"3: Elevated (No Wk0)","4: Engaged Early"))) -> 3: Elevated (No Wk0)
A49: Academy Intake X | B49: AIX10048 | C49: Yes | D49: 3 | E49: 2 | F49: 1 | G49: =IFERROR(E49/D49,0) -> 0.66666667 | H49: =IFERROR(F49/D49,0) -> 0.33333333 | I49: 1 | J49: 82.35 | K49: 16.67 | L49: No | M49: 0 | N49: =ROUND(IFERROR(K49/100,0)*0.6 + IF(L49="Yes",1,IF(L49="No",0,0.3))*0.25 + IFERROR(J49/100,0)*0.15,3) -> 0.224 | O49: =IF(AND(L49="No",I49=0),"1: Critical (No DBWT + No Wk0)",IF(L49="No","2: High (No DBWT)",IF(I49=0,"3: Elevated (No Wk0)","4: Engaged Early"))) -> 2: High (No DBWT)
A50: Academy Intake X | B50: AIX10049 | C50: No | D50: 22 | E50: 20 | F50: 6 | G50: =IFERROR(E50/D50,0) -> 0.90909091 | H50: =IFERROR(F50/D50,0) -> 0.27272727 | I50: 2 | J50: 83.79805 | K50: 100 | L50: Yes | M50: 1 | N50: =ROUND(IFERROR(K50/100,0)*0.6 + IF(L50="Yes",1,IF(L50="No",0,0.3))*0.25 + IFERROR(J50/100,0)*0.15,3) -> 0.976 | O50: =IF(AND(L50="No",I50=0),"1: Critical (No DBWT + No Wk0)",IF(L50="No","2: High (No DBWT)",IF(I50=0,"3: Elevated (No Wk0)","4: Engaged Early"))) -> 4: Engaged Early
A51: Academy Intake X | B51: AIX10050 | C51: Yes | D51: 10 | E51: 9 | F51: 2 | G51: =IFERROR(E51/D51,0) -> 0.9 | H51: =IFERROR(F51/D51,0) -> 0.2 | I51: 1 | J51: 81.58 | K51: 16.67 | L51: Yes | M51: 0 | N51: =ROUND(IFERROR(K51/100,0)*0.6 + IF(L51="Yes",1,IF(L51="No",0,0.3))*0.25 + IFERROR(J51/100,0)*0.15,3) -> 0.472 | O51: =IF(AND(L51="No",I51=0),"1: Critical (No DBWT + No Wk0)",IF(L51="No","2: High (No DBWT)",IF(I51=0,"3: Elevated (No Wk0)","4: Engaged Early"))) -> 4: Engaged Early
A52: Academy Intake X | B52: AIX10051 | C52: No | D52: 18 | E52: 18 | F52: 1 | G52: =IFERROR(E52/D52,0) -> 1 | H52: =IFERROR(F52/D52,0) -> 0.055555556 | I52: 1 | J52: 44.8876 | K52: 74.41 | L52: Yes | M52: 1 | N52: =ROUND(IFERROR(K52/100,0)*0.6 + IF(L52="Yes",1,IF(L52="No",0,0.3))*0.25 + IFERROR(J52/100,0)*0.15,3) -> 0.764 | O52: =IF(AND(L52="No",I52=0),"1: Critical (No DBWT + No Wk0)",IF(L52="No","2: High (No DBWT)",IF(I52=0,"3: Elevated (No Wk0)","4: Engaged Early"))) -> 4: Engaged Early
A53: Academy Intake X | B53: AIX10052 | C53: No | D53: 17 | E53: 12 | F53: 0 | G53: =IFERROR(E53/D53,0) -> 0.70588235 | H53: =IFERROR(F53/D53,0) -> 0 | I53: 1 | J53: 90.63 | K53: 85.01 | L53: Yes | M53: 0 | N53: =ROUND(IFERROR(K53/100,0)*0.6 + IF(L53="Yes",1,IF(L53="No",0,0.3))*0.25 + IFERROR(J53/100,0)*0.15,3) -> 0.896 | O53: =IF(AND(L53="No",I53=0),"1: Critical (No DBWT + No Wk0)",IF(L53="No","2: High (No DBWT)",IF(I53=0,"3: Elevated (No Wk0)","4: Engaged Early"))) -> 4: Engaged Early
A54: Academy Intake X | B54: AIX10053 | C54: No | D54: 14 | E54: 10 | F54: 2 | G54: =IFERROR(E54/D54,0) -> 0.71428571 | H54: =IFERROR(F54/D54,0) -> 0.14285714 | I54: 2 | J54: 96.39115 | K54: 100 | L54: Yes | M54: 0 | N54: =ROUND(IFERROR(K54/100,0)*0.6 + IF(L54="Yes",1,IF(L54="No",0,0.3))*0.25 + IFERROR(J54/100,0)*0.15,3) -> 0.995 | O54: =IF(AND(L54="No",I54=0),"1: Critical (No DBWT + No Wk0)",IF(L54="No","2: High (No DBWT)",IF(I54=0,"3: Elevated (No Wk0)","4: Engaged Early"))) -> 4: Engaged Early
A55: Academy Intake X | B55: AIX10054 | C55: No | D55: 13 | E55: 10 | F55: 0 | G55: =IFERROR(E55/D55,0) -> 0.76923077 | H55: =IFERROR(F55/D55,0) -> 0 | I55: 2 | J55: 96.55115 | K55: 86.51 | L55: Yes | M55: 0 | N55: =ROUND(IFERROR(K55/100,0)*0.6 + IF(L55="Yes",1,IF(L55="No",0,0.3))*0.25 + IFERROR(J55/100,0)*0.15,3) -> 0.914 | O55: =IF(AND(L55="No",I55=0),"1: Critical (No DBWT + No Wk0)",IF(L55="No","2: High (No DBWT)",IF(I55=0,"3: Elevated (No Wk0)","4: Engaged Early"))) -> 4: Engaged Early
A56: Academy Intake X | B56: AIX10055 | C56: No | D56: 9 | E56: 7 | F56: 2 | G56: =IFERROR(E56/D56,0) -> 0.77777778 | H56: =IFERROR(F56/D56,0) -> 0.22222222 | I56: 2 | J56: 81.04045 | K56: 90.04 | L56: Yes | M56: 0 | N56: =ROUND(IFERROR(K56/100,0)*0.6 + IF(L56="Yes",1,IF(L56="No",0,0.3))*0.25 + IFERROR(J56/100,0)*0.15,3) -> 0.912 | O56: =IF(AND(L56="No",I56=0),"1: Critical (No DBWT + No Wk0)",IF(L56="No","2: High (No DBWT)",IF(I56=0,"3: Elevated (No Wk0)","4: Engaged Early"))) -> 4: Engaged Early
A57: Academy Intake X | B57: AIX10056 | C57: No | D57: 17 | E57: 13 | F57: 2 | G57: =IFERROR(E57/D57,0) -> 0.76470588 | H57: =IFERROR(F57/D57,0) -> 0.11764706 | I57: 2 | J57: 50.03935 | K57: 80.12 | L57: Yes | M57: 1 | N57: =ROUND(IFERROR(K57/100,0)*0.6 + IF(L57="Yes",1,IF(L57="No",0,0.3))*0.25 + IFERROR(J57/100,0)*0.15,3) -> 0.806 | O57: =IF(AND(L57="No",I57=0),"1: Critical (No DBWT + No Wk0)",IF(L57="No","2: High (No DBWT)",IF(I57=0,"3: Elevated (No Wk0)","4: Engaged Early"))) -> 4: Engaged Early
A58: Academy Intake X | B58: AIX10057 | C58: No | D58: 17 | E58: 5 | F58: 5 | G58: =IFERROR(E58/D58,0) -> 0.29411765 | H58: =IFERROR(F58/D58,0) -> 0.29411765 | I58: 2 | J58: 99.45365 | K58: 100 | L58: Yes | M58: 0 | N58: =ROUND(IFERROR(K58/100,0)*0.6 + IF(L58="Yes",1,IF(L58="No",0,0.3))*0.25 + IFERROR(J58/100,0)*0.15,3) -> 0.999 | O58: =IF(AND(L58="No",I58=0),"1: Critical (No DBWT + No Wk0)",IF(L58="No","2: High (No DBWT)",IF(I58=0,"3: Elevated (No Wk0)","4: Engaged Early"))) -> 4: Engaged Early
A59: Academy Intake X | B59: AIX10058 | C59: No | D59: 6 | E59: 4 | F59: 2 | G59: =IFERROR(E59/D59,0) -> 0.66666667 | H59: =IFERROR(F59/D59,0) -> 0.33333333 | I59: 2 | J59: 89.3045 | K59: 100 | L59: Yes | M59: 1 | N59: =ROUND(IFERROR(K59/100,0)*0.6 + IF(L59="Yes",1,IF(L59="No",0,0.3))*0.25 + IFERROR(J59/100,0)*0.15,3) -> 0.984 | O59: =IF(AND(L59="No",I59=0),"1: Critical (No DBWT + No Wk0)",IF(L59="No","2: High (No DBWT)",IF(I59=0,"3: Elevated (No Wk0)","4: Engaged Early"))) -> 4: Engaged Early
A60: Academy Intake X | B60: AIX10059 | C60: No | D60: 22 | E60: 21 | F60: 2 | G60: =IFERROR(E60/D60,0) -> 0.95454545 | H60: =IFERROR(F60/D60,0) -> 0.090909091 | I60: 2 | J60: 70.75255 | K60: 93.35 | L60: Yes | M60: 0 | N60: =ROUND(IFERROR(K60/100,0)*0.6 + IF(L60="Yes",1,IF(L60="No",0,0.3))*0.25 + IFERROR(J60/100,0)*0.15,3) -> 0.916 | O60: =IF(AND(L60="No",I60=0),"1: Critical (No DBWT + No Wk0)",IF(L60="No","2: High (No DBWT)",IF(I60=0,"3: Elevated (No Wk0)","4: Engaged Early"))) -> 4: Engaged Early
... A69: Academy Intake X | B69: AIX10068 | C69: No | D69: 5 | E69: 4 | F69: 0 | G69: =IFERROR(E69/D69,0) -> 0.8 | H69: =IFERROR(F69/D69,0) -> 0 | I69: 2 | J69: 57.8501 | K69: 82.43 | L69: Yes | M69: 0 | N69: =ROUND(IFERROR(K69/100,0)*0.6 + IF(L69="Yes",1,IF(L69="No",0,0.3))*0.25 + IFERROR(J69/100,0)*0.15,3) -> 0.831 | O69: =IF(AND(L69="No",I69=0),"1: Critical (No DBWT + No Wk0)",IF(L69="No","2: High (No DBWT)",IF(I69=0,"3: Elevated (No Wk0)","4: Engaged Early"))) -> 4: Engaged Early
A70: Academy Intake X | B70: AIX10069 | C70: Yes | D70: 13 | E70: 4 | F70: 1 | G70: =IFERROR(E70/D70,0) -> 0.30769231 | H70: =IFERROR(F70/D70,0) -> 0.076923077 | I70: 0 | K70: 0 | L70: No | M70: 0 | N70: =ROUND(IFERROR(K70/100,0)*0.6 + IF(L70="Yes",1,IF(L70="No",0,0.3))*0.25 + IFERROR(J70/100,0)*0.15,3) -> 0 | O70: =IF(AND(L70="No",I70=0),"1: Critical (No DBWT + No Wk0)",IF(L70="No","2: High (No DBWT)",IF(I70=0,"3: Elevated (No Wk0)","4: Engaged Early"))) -> 1: Critical (No DBWT + No Wk0)
A71: Academy Intake X | B71: AIX10070 | C71: No | D71: 10 | E71: 7 | F71: 3 | G71: =IFERROR(E71/D71,0) -> 0.7 | H71: =IFERROR(F71/D71,0) -> 0.3 | I71: 2 | J71: 99.9479 | K71: 100 | L71: Yes | M71: 0 | N71: =ROUND(IFERROR(K71/100,0)*0.6 + IF(L71="Yes",1,IF(L71="No",0,0.3))*0.25 + IFERROR(J71/100,0)*0.15,3) -> 1 | O71: =IF(AND(L71="No",I71=0),"1: Critical (No DBWT + No Wk0)",IF(L71="No","2: High (No DBWT)",IF(I71=0,"3: Elevated (No Wk0)","4: Engaged Early"))) -> 4: Engaged Early
A72: Academy Intake X | B72: AIX10071 | C72: Yes | D72: 13 | E72: 9 | F72: 2 | G72: =IFERROR(E72/D72,0) -> 0.69230769 | H72: =IFERROR(F72/D72,0) -> 0.15384615 | I72: 0 | K72: 0.21 | L72: No | M72: 0 | N72: =ROUND(IFERROR(K72/100,0)*0.6 + IF(L72="Yes",1,IF(L72="No",0,0.3))*0.25 + IFERROR(J72/100,0)*0.15,3) -> 0.001 | O72: =IF(AND(L72="No",I72=0),"1: Critical (No DBWT + No Wk0)",IF(L72="No","2: High (No DBWT)",IF(I72=0,"3: Elevated (No Wk0)","4: Engaged Early"))) -> 1: Critical (No DBWT + No Wk0)
A73: Academy Intake X | B73: AIX10072 | C73: No | D73: 22 | E73: 12 | F73: 3 | G73: =IFERROR(E73/D73,0) -> 0.54545455 | H73: =IFERROR(F73/D73,0) -> 0.13636364 | I73: 1 | J73: 73.73 | K73: 41.47 | L73: Yes | M73: 0 | N73: =ROUND(IFERROR(K73/100,0)*0.6 + IF(L73="Yes",1,IF(L73="No",0,0.3))*0.25 + IFERROR(J73/100,0)*0.15,3) -> 0.609 | O73: =IF(AND(L73="No",I73=0),"1: Critical (No DBWT + No Wk0)",IF(L73="No","2: High (No DBWT)",IF(I73=0,"3: Elevated (No Wk0)","4: Engaged Early"))) -> 4: Engaged Early
A74: Academy Intake X | B74: AIX10073 | C74: No | D74: 15 | E74: 7 | F74: 5 | G74: =IFERROR(E74/D74,0) -> 0.46666667 | H74: =IFERROR(F74/D74,0) -> 0.33333333 | I74: 2 | J74: 69.7372 | K74: 80.06 | L74: Yes | M74: 0 | N74: =ROUND(IFERROR(K74/100,0)*0.6 + IF(L74="Yes",1,IF(L74="No",0,0.3))*0.25 + IFERROR(J74/100,0)*0.15,3) -> 0.835 | O74: =IF(AND(L74="No",I74=0),"1: Critical (No DBWT + No Wk0)",IF(L74="No","2: High (No DBWT)",IF(I74=0,"3: Elevated (No Wk0)","4: Engaged Early"))) -> 4: Engaged Early
A75: Academy Intake X | B75: AIX10074 | C75: No | D75: 21 | E75: 17 | F75: 1 | G75: =IFERROR(E75/D75,0) -> 0.80952381 | H75: =IFERROR(F75/D75,0) -> 0.047619048 | I75: 2 | J75: 98.61 | K75: 100 | L75: Yes | M75: 0 | N75: =ROUND(IFERROR(K75/100,0)*0.6 + IF(L75="Yes",1,IF(L75="No",0,0.3))*0.25 + IFERROR(J75/100,0)*0.15,3) -> 0.998 | O75: =IF(AND(L75="No",I75=0),"1: Critical (No DBWT + No Wk0)",IF(L75="No","2: High (No DBWT)",IF(I75=0,"3: Elevated (No Wk0)","4: Engaged Early"))) -> 4: Engaged Early
A76: Academy Intake X | B76: AIX10075 | C76: Yes | D76: 26 | E76: 3 | F76: 0 | G76: =IFERROR(E76/D76,0) -> 0.11538462 | H76: =IFERROR(F76/D76,0) -> 0 | I76: 1 | J76: 80.75 | K76: 16.67 | L76: Yes | M76: 0 | N76: =ROUND(IFERROR(K76/100,0)*0.6 + IF(L76="Yes",1,IF(L76="No",0,0.3))*0.25 + IFERROR(J76/100,0)*0.15,3) -> 0.471 | O76: =IF(AND(L76="No",I76=0),"1: Critical (No DBWT + No Wk0)",IF(L76="No","2: High (No DBWT)",IF(I76=0,"3: Elevated (No Wk0)","4: Engaged Early"))) -> 4: Engaged Early
A77: Academy Intake X | B77: AIX10076 | C77: No | D77: 25 | E77: 18 | F77: 4 | G77: =IFERROR(E77/D77,0) -> 0.72 | H77: =IFERROR(F77/D77,0) -> 0.16 | I77: 2 | J77: 85.0385 | K77: 100 | L77: Yes | M77: 1 | N77: =ROUND(IFERROR(K77/100,0)*0.6 + IF(L77="Yes",1,IF(L77="No",0,0.3))*0.25 + IFERROR(J77/100,0)*0.15,3) -> 0.978 | O77: =IF(AND(L77="No",I77=0),"1: Critical (No DBWT + No Wk0)",IF(L77="No","2: High (No DBWT)",IF(I77=0,"3: Elevated (No Wk0)","4: Engaged Early"))) -> 4: Engaged Early
A78: Academy Intake X | B78: AIX10077 | C78: Yes | D78: 10 | E78: 9 | F78: 6 | G78: =IFERROR(E78/D78,0) -> 0.9 | H78: =IFERROR(F78/D78,0) -> 0.6 | I78: 2 | J78: 61.4417 | K78: 24.32 | L78: No | M78: 0 | N78: =ROUND(IFERROR(K78/100,0)*0.6 + IF(L78="Yes",1,IF(L78="No",0,0.3))*0.25 + IFERROR(J78/100,0)*0.15,3) -> 0.238 | O78: =IF(AND(L78="No",I78=0),"1: Critical (No DBWT + No Wk0)",IF(L78="No","2: High (No DBWT)",IF(I78=0,"3: Elevated (No Wk0)","4: Engaged Early"))) -> 2: High (No DBWT)
A79: Academy Intake X | B79: AIX10078 | C79: No | D79: 12 | E79: 11 | F79: 8 | G79: =IFERROR(E79/D79,0) -> 0.91666667 | H79: =IFERROR(F79/D79,0) -> 0.66666667 | I79: 2 | J79: 82.036 | K79: 100 | L79: Yes | M79: 0 | N79: =ROUND(IFERROR(K79/100,0)*0.6 + IF(L79="Yes",1,IF(L79="No",0,0.3))*0.25 + IFERROR(J79/100,0)*0.15,3) -> 0.973 | O79: =IF(AND(L79="No",I79=0),"1: Critical (No DBWT + No Wk0)",IF(L79="No","2: High (No DBWT)",IF(I79=0,"3: Elevated (No Wk0)","4: Engaged Early"))) -> 4: Engaged Early
A80: Academy Intake X | B80: AIX10079 | C80: No | D80: 13 | E80: 3 | F80: 1 | G80: =IFERROR(E80/D80,0) -> 0.23076923 | H80: =IFERROR(F80/D80,0) -> 0.076923077 | I80: 0 | K80: 0 | L80: No | M80: 0 | N80: =ROUND(IFERROR(K80/100,0)*0.6 + IF(L80="Yes",1,IF(L80="No",0,0.3))*0.25 + IFERROR(J80/100,0)*0.15,3) -> 0 | O80: =IF(AND(L80="No",I80=0),"1: Critical (No DBWT + No Wk0)",IF(L80="No","2: High (No DBWT)",IF(I80=0,"3: Elevated (No Wk0)","4: Engaged Early"))) -> 1: Critical (No DBWT + No Wk0)
A81: Academy Intake X | B81: AIX10080 | C81: Yes | D81: 10 | E81: 6 | F81: 2 | G81: =IFERROR(E81/D81,0) -> 0.6 | H81: =IFERROR(F81/D81,0) -> 0.2 | I81: 2 | J81: 45.78125 | K81: 14.81 | L81: No | M81: 0 | N81: =ROUND(IFERROR(K81/100,0)*0.6 + IF(L81="Yes",1,IF(L81="No",0,0.3))*0.25 + IFERROR(J81/100,0)*0.15,3) -> 0.158 | O81: =IF(AND(L81="No",I81=0),"1: Critical (No DBWT + No Wk0)",IF(L81="No","2: High (No DBWT)",IF(I81=0,"3: Elevated (No Wk0)","4: Engaged Early"))) -> 2: High (No DBWT)
A82: Academy Intake X | B82: AIX10081 | C82: Yes | D82: 18 | E82: 13 | F82: 1 | G82: =IFERROR(E82/D82,0) -> 0.72222222 | H82: =IFERROR(F82/D82,0) -> 0.055555556 | I82: 0 | K82: 0 | L82: Yes | M82: 0 | N82: =ROUND(IFERROR(K82/100,0)*0.6 + IF(L82="Yes",1,IF(L82="No",0,0.3))*0.25 + IFERROR(J82/100,0)*0.15,3) -> 0.25 | O82: =IF(AND(L82="No",I82=0),"1: Critical (No DBWT + No Wk0)",IF(L82="No","2: High (No DBWT)",IF(I82=0,"3: Elevated (No Wk0)","4: Engaged Early"))) -> 3: Elevated (No Wk0)
A83: Academy Intake X | B83: AIX10082 | C83: Yes | D83: 22 | E83: 13 | F83: 1 | G83: =IFERROR(E83/D83,0) -> 0.59090909 | H83: =IFERROR(F83/D83,0) -> 0.045454545 | I83: 1 | J83: 96.63 | K83: 16.67 | L83: Yes | M83: 0 | N83: =ROUND(IFERROR(K83/100,0)*0.6 + IF(L83="Yes",1,IF(L83="No",0,0.3))*0.25 + IFERROR(J83/100,0)*0.15,3) -> 0.495 | O83: =IF(AND(L83="No",I83=0),"1: Critical (No DBWT + No Wk0)",IF(L83="No","2: High (No DBWT)",IF(I83=0,"3: Elevated (No Wk0)","4: Engaged Early"))) -> 4: Engaged Early
A84: Academy Intake X | B84: AIX10083 | C84: Yes | D84: 15 | E84: 4 | F84: 0 | G84: =IFERROR(E84/D84,0) -> 0.26666667 | H84: =IFERROR(F84/D84,0) -> 0 | I84: 0 | K84: 0 | L84: No | M84: 0 | N84: =ROUND(IFERROR(K84/100,0)*0.6 + IF(L84="Yes",1,IF(L84="No",0,0.3))*0.25 + IFERROR(J84/100,0)*0.15,3) -> 0 | O84: =IF(AND(L84="No",I84=0),"1: Critical (No DBWT + No Wk0)",IF(L84="No","2: High (No DBWT)",IF(I84=0,"3: Elevated (No Wk0)","4: Engaged Early"))) -> 1: Critical (No DBWT + No Wk0)
A85: Academy Intake X | B85: AIX10084 | C85: No | D85: 17 | E85: 7 | F85: 0 | G85: =IFERROR(E85/D85,0) -> 0.41176471 | H85: =IFERROR(F85/D85,0) -> 0 | I85: 0 | K85: 3.66 | L85: Yes | M85: 0 | N85: =ROUND(IFERROR(K85/100,0)*0.6 + IF(L85="Yes",1,IF(L85="No",0,0.3))*0.25 + IFERROR(J85/100,0)*0.15,3) -> 0.272 | O85: =IF(AND(L85="No",I85=0),"1: Critical (No DBWT + No Wk0)",IF(L85="No","2: High (No DBWT)",IF(I85=0,"3: Elevated (No Wk0)","4: Engaged Early"))) -> 3: Elevated (No Wk0)
A86: Academy Intake X | B86: AIX10085 | C86: No | D86: 26 | E86: 16 | F86: 3 | G86: =IFERROR(E86/D86,0) -> 0.61538462 | H86: =IFERROR(F86/D86,0) -> 0.11538462 | I86: 2 | J86: 64.1757 | K86: 92.04 | L86: Yes | M86: 0 | N86: =ROUND(IFERROR(K86/100,0)*0.6 + IF(L86="Yes",1,IF(L86="No",0,0.3))*0.25 + IFERROR(J86/100,0)*0.15,3) -> 0.899 | O86: =IF(AND(L86="No",I86=0),"1: Critical (No DBWT + No Wk0)",IF(L86="No","2: High (No DBWT)",IF(I86=0,"3: Elevated (No Wk0)","4: Engaged Early"))) -> 4: Engaged Early
A87: Academy Intake X | B87: AIX10086 | C87: Yes | D87: 25 | E87: 15 | F87: 1 | G87: =IFERROR(E87/D87,0) -> 0.6 | H87: =IFERROR(F87/D87,0) -> 0.04 | I87: 0 | K87: 0 | L87: Yes | M87: 0 | N87: =ROUND(IFERROR(K87/100,0)*0.6 + IF(L87="Yes",1,IF(L87="No",0,0.3))*0.25 + IFERROR(J87/100,0)*0.15,3) -> 0.25 | O87: =IF(AND(L87="No",I87=0),"1: Critical (No DBWT + No Wk0)",IF(L87="No","2: High (No DBWT)",IF(I87=0,"3: Elevated (No Wk0)","4: Engaged Early"))) -> 3: Elevated (No Wk0)
A88: Academy Intake X | B88: AIX10087 | C88: No | D88: 4 | E88: 4 | F88: 2 | G88: =IFERROR(E88/D88,0) -> 1 | H88: =IFERROR(F88/D88,0) -> 0.5 | I88: 2 | J88: 84.37405 | K88: 98.51 | L88: Yes | M88: 0 | N88: =ROUND(IFERROR(K88/100,0)*0.6 + IF(L88="Yes",1,IF(L88="No",0,0.3))*0.25 + IFERROR(J88/100,0)*0.15,3) -> 0.968 | O88: =IF(AND(L88="No",I88=0),"1: Critical (No DBWT + No Wk0)",IF(L88="No","2: High (No DBWT)",IF(I88=0,"3: Elevated (No Wk0)","4: Engaged Early"))) -> 4: Engaged Early
A89: Academy Intake X | B89: AIX10088 | C89: Yes | D89: 13 | E89: 4 | F89: 1 | G89: =IFERROR(E89/D89,0) -> 0.30769231 | H89: =IFERROR(F89/D89,0) -> 0.076923077 | I89: 0 | K89: 0 | L89: No | M89: 0 | N89: =ROUND(IFERROR(K89/100,0)*0.6 + IF(L89="Yes",1,IF(L89="No",0,0.3))*0.25 + IFERROR(J89/100,0)*0.15,3) -> 0 | O89: =IF(AND(L89="No",I89=0),"1: Critical (No DBWT + No Wk0)",IF(L89="No","2: High (No DBWT)",IF(I89=0,"3: Elevated (No Wk0)","4: Engaged Early"))) -> 1: Critical (No DBWT + No Wk0)
A90: Academy Intake X | B90: AIX10089 | C90: No | D90: 4 | E90: 4 | F90: 3 | G90: =IFERROR(E90/D90,0) -> 1 | H90: =IFERROR(F90/D90,0) -> 0.75 | I90: 2 | J90: 83.56525 | K90: 100 | L90: Yes | M90: 0 | N90: =ROUND(IFERROR(K90/100,0)*0.6 + IF(L90="Yes",1,IF(L90="No",0,0.3))*0.25 + IFERROR(J90/100,0)*0.15,3) -> 0.975 | O90: =IF(AND(L90="No",I90=0),"1: Critical (No DBWT + No Wk0)",IF(L90="No","2: High (No DBWT)",IF(I90=0,"3: Elevated (No Wk0)","4: Engaged Early"))) -> 4: Engaged Early
A91: Academy Intake X | B91: AIX10090 | C91: Yes | D91: 23 | E91: 15 | F91: 0 | G91: =IFERROR(E91/D91,0) -> 0.65217391 | H91: =IFERROR(F91/D91,0) -> 0 | I91: 0 | K91: 0 | L91: Yes | M91: 0 | N91: =ROUND(IFERROR(K91/100,0)*0.6 + IF(L91="Yes",1,IF(L91="No",0,0.3))*0.25 + IFERROR(J91/100,0)*0.15,3) -> 0.25 | O91: =IF(AND(L91="No",I91=0),"1: Critical (No DBWT + No Wk0)",IF(L91="No","2: High (No DBWT)",IF(I91=0,"3: Elevated (No Wk0)","4: Engaged Early"))) -> 3: Elevated (No Wk0)
A92: Academy Intake X | B92: AIX10091 | C92: Yes | D92: 2 | E92: 1 | F92: 0 | G92: =IFERROR(E92/D92,0) -> 0.5 | H92: =IFERROR(F92/D92,0) -> 0 | I92: 1 | J92: 7.23 | K92: 1.51 | L92: No | M92: 0 | N92: =ROUND(IFERROR(K92/100,0)*0.6 + IF(L92="Yes",1,IF(L92="No",0,0.3))*0.25 + IFERROR(J92/100,0)*0.15,3) -> 0.02 | O92: =IF(AND(L92="No",I92=0),"1: Critical (No DBWT + No Wk0)",IF(L92="No","2: High (No DBWT)",IF(I92=0,"3: Elevated (No Wk0)","4: Engaged Early"))) -> 2: High (No DBWT)
A93: Academy Intake X | B93: AIX10092 | C93: Yes | D93: 15 | E93: 12 | F93: 2 | G93: =IFERROR(E93/D93,0) -> 0.8 | H93: =IFERROR(F93/D93,0) -> 0.13333333 | I93: 1 | J93: 7.5 | K93: 1.87 | L93: No | M93: 0 | N93: =ROUND(IFERROR(K93/100,0)*0.6 + IF(L93="Yes",1,IF(L93="No",0,0.3))*0.25 + IFERROR(J93/100,0)*0.15,3) -> 0.022 | O93: =IF(AND(L93="No",I93=0),"1: Critical (No DBWT + No Wk0)",IF(L93="No","2: High (No DBWT)",IF(I93=0,"3: Elevated (No Wk0)","4: Engaged Early"))) -> 2: High (No DBWT)
A94: Academy Intake X | B94: AIX10093 | C94: Yes | D94: 12 | E94: 11 | F94: 3 | G94: =IFERROR(E94/D94,0) -> 0.91666667 | H94: =IFERROR(F94/D94,0) -> 0.25 | I94: 2 | J94: 72.28185 | K94: 36.97 | L94: Yes | M94: 0 | N94: =ROUND(IFERROR(K94/100,0)*0.6 + IF(L94="Yes",1,IF(L94="No",0,0.3))*0.25 + IFERROR(J94/100,0)*0.15,3) -> 0.58 | O94: =IF(AND(L94="No",I94=0),"1: Critical (No DBWT + No Wk0)",IF(L94="No","2: High (No DBWT)",IF(I94=0,"3: Elevated (No Wk0)","4: Engaged Early"))) -> 4: Engaged Early
A95: Academy Intake X | B95: AIX10094 | C95: Yes | D95: 1 | E95: 1 | F95: 1 | G95: =IFERROR(E95/D95,0) -> 1 | H95: =IFERROR(F95/D95,0) -> 1 | I95: 1 | J95: 87.05 | K95: 12.5 | L95: Yes | M95: 0 | N95: =ROUND(IFERROR(K95/100,0)*0.6 + IF(L95="Yes",1,IF(L95="No",0,0.3))*0.25 + IFERROR(J95/100,0)*0.15,3) -> 0.456 | O95: =IF(AND(L95="No",I95=0),"1: Critical (No DBWT + No Wk0)",IF(L95="No","2: High (No DBWT)",IF(I95=0,"3: Elevated (No Wk0)","4: Engaged Early"))) -> 4: Engaged Early
A96: Academy Intake X | B96: AIX10095 | C96: No | D96: 13 | E96: 12 | F96: 5 | G96: =IFERROR(E96/D96,0) -> 0.92307692 | H96: =IFERROR(F96/D96,0) -> 0.38461538 | I96: 1 | J96: 95.19 | K96: 11.47 | L96: Yes | M96: 0 | N96: =ROUND(IFERROR(K96/100,0)*0.6 + IF(L96="Yes",1,IF(L96="No",0,0.3))*0.25 + IFERROR(J96/100,0)*0.15,3) -> 0.462 | O96: =IF(AND(L96="No",I96=0),"1: Critical (No DBWT + No Wk0)",IF(L96="No","2: High (No DBWT)",IF(I96=0,"3: Elevated (No Wk0)","4: Engaged Early"))) -> 4: Engaged Early
A97: Academy Intake X | B97: AIX10096 | C97: Yes | D97: 13 | E97: 0 | F97: 0 | G97: =IFERROR(E97/D97,0) -> 0 | H97: =IFERROR(F97/D97,0) -> 0 | I97: 0 | K97: 0 | L97: Yes | M97: 0 | N97: =ROUND(IFERROR(K97/100,0)*0.6 + IF(L97="Yes",1,IF(L97="No",0,0.3))*0.25 + IFERROR(J97/100,0)*0.15,3) -> 0.25 | O97: =IF(AND(L97="No",I97=0),"1: Critical (No DBWT + No Wk0)",IF(L97="No","2: High (No DBWT)",IF(I97=0,"3: Elevated (No Wk0)","4: Engaged Early"))) -> 3: Elevated (No Wk0)
A98: Academy Intake X | B98: AIX10097 | C98: Yes | D98: 23 | E98: 17 | F98: 2 | G98: =IFERROR(E98/D98,0) -> 0.73913043 | H98: =IFERROR(F98/D98,0) -> 0.086956522 | I98: 0 | K98: 0 | L98: No | M98: 0 | N98: =ROUND(IFERROR(K98/100,0)*0.6 + IF(L98="Yes",1,IF(L98="No",0,0.3))*0.25 + IFERROR(J98/100,0)*0.15,3) -> 0 | O98: =IF(AND(L98="No",I98=0),"1: Critical (No DBWT + No Wk0)",IF(L98="No","2: High (No DBWT)",IF(I98=0,"3: Elevated (No Wk0)","4: Engaged Early"))) -> 1: Critical (No DBWT + No Wk0)
A99: Academy Intake X | B99: AIX10098 | C99: No | D99: 23 | E99: 10 | F99: 2 | G99: =IFERROR(E99/D99,0) -> 0.43478261 | H99: =IFERROR(F99/D99,0) -> 0.086956522 | I99: 2 | J99: 45.57005 | K99: 31.51 | L99: Yes | M99: 0 | N99: =ROUND(IFERROR(K99/100,0)*0.6 + IF(L99="Yes",1,IF(L99="No",0,0.3))*0.25 + IFERROR(J99/100,0)*0.15,3) -> 0.507 | O99: =IF(AND(L99="No",I99=0),"1: Critical (No DBWT + No Wk0)",IF(L99="No","2: High (No DBWT)",IF(I99=0,"3: Elevated (No Wk0)","4: Engaged Early"))) -> 4: Engaged Early
A100: Academy Intake X | B100: AIX10099 | C100: No | D100: 10 | E100: 6 | F100: 0 | G100: =IFERROR(E100/D100,0) -> 0.6 | H100: =IFERROR(F100/D100,0) -> 0 | I100: 2 | J100: 61.75305 | K100: 38.6 | L100: No | M100: 0 | N100: =ROUND(IFERROR(K100/100,0)*0.6 + IF(L100="Yes",1,IF(L100="No",0,0.3))*0.25 + IFERROR(J100/100,0)*0.15,3) -> 0.324 | O100: =IF(AND(L100="No",I100=0),"1: Critical (No DBWT + No Wk0)",IF(L100="No","2: High (No DBWT)",IF(I100=0,"3: Elevated (No Wk0)","4: Engaged Early"))) -> 2: High (No DBWT)
A101: Academy Intake X | B101: AIX10100 | C101: No | D101: 12 | E101: 7 | F101: 1 | G101: =IFERROR(E101/D101,0) -> 0.58333333 | H101: =IFERROR(F101/D101,0) -> 0.083333333 | I101: 2 | J101: 59.2437 | K101: 87.51 | L101: Yes | M101: 1 | N101: =ROUND(IFERROR(K101/100,0)*0.6 + IF(L101="Yes",1,IF(L101="No",0,0.3))*0.25 + IFERROR(J101/100,0)*0.15,3) -> 0.864 | O101: =IF(AND(L101="No",I101=0),"1: Critical (No DBWT + No Wk0)",IF(L101="No","2: High (No DBWT)",IF(I101=0,"3: Elevated (No Wk0)","4: Engaged Early"))) -> 4: Engaged Early
A102: Academy Intake X | B102: AIX10101 | C102: Yes | D102: 4 | E102: 4 | F102: 0 | G102: =IFERROR(E102/D102,0) -> 1 | H102: =IFERROR(F102/D102,0) -> 0 | I102: 0 | K102: 0 | L102: No | M102: 0 | N102: =ROUND(IFERROR(K102/100,0)*0.6 + IF(L102="Yes",1,IF(L102="No",0,0.3))*0.25 + IFERROR(J102/100,0)*0.15,3) -> 0 | O102: =IF(AND(L102="No",I102=0),"1: Critical (No DBWT + No Wk0)",IF(L102="No","2: High (No DBWT)",IF(I102=0,"3: Elevated (No Wk0)","4: Engaged Early"))) -> 1: Critical (No DBWT + No Wk0)
A103: Academy Intake X | B103: AIX10102 | C103: No | D103: 20 | E103: 15 | F103: 1 | G103: =IFERROR(E103/D103,0) -> 0.75 | H103: =IFERROR(F103/D103,0) -> 0.05 | I103: 2 | J103: 77.9136 | K103: 88.02 | L103: Yes | M103: 0 | N103: =ROUND(IFERROR(K103/100,0)*0.6 + IF(L103="Yes",1,IF(L103="No",0,0.3))*0.25 + IFERROR(J103/100,0)*0.15,3) -> 0.895 | O103: =IF(AND(L103="No",I103=0),"1: Critical (No DBWT + No Wk0)",IF(L103="No","2: High (No DBWT)",IF(I103=0,"3: Elevated (No Wk0)","4: Engaged Early"))) -> 4: Engaged Early
A104: Academy Intake X | B104: AIX10103 | C104: Yes | D104: 20 | E104: 3 | F104: 5 | G104: =IFERROR(E104/D104,0) -> 0.15 | H104: =IFERROR(F104/D104,0) -> 0.25 | I104: 1 | J104: 60.39 | K104: 9.44 | L104: Yes | M104: 0 | N104: =ROUND(IFERROR(K104/100,0)*0.6 + IF(L104="Yes",1,IF(L104="No",0,0.3))*0.25 + IFERROR(J104/100,0)*0.15,3) -> 0.397 | O104: =IF(AND(L104="No",I104=0),"1: Critical (No DBWT + No Wk0)",IF(L104="No","2: High (No DBWT)",IF(I104=0,"3: Elevated (No Wk0)","4: Engaged Early"))) -> 4: Engaged Early
A105: Academy Intake X | B105: AIX10104 | C105: No | D105: 3 | E105: 0 | F105: 0 | G105: =IFERROR(E105/D105,0) -> 0 | H105: =IFERROR(F105/D105,0) -> 0 | I105: 2 | J105: 83.8705 | K105: 100 | L105: Yes | M105: 1 | N105: =ROUND(IFERROR(K105/100,0)*0.6 + IF(L105="Yes",1,IF(L105="No",0,0.3))*0.25 + IFERROR(J105/100,0)*0.15,3) -> 0.976 | O105: =IF(AND(L105="No",I105=0),"1: Critical (No DBWT + No Wk0)",IF(L105="No","2: High (No DBWT)",IF(I105=0,"3: Elevated (No Wk0)","4: Engaged Early"))) -> 4: Engaged Early
A106: Academy Intake X | B106: AIX10105 | C106: Yes | D106: 22 | E106: 19 | F106: 2 | G106: =IFERROR(E106/D106,0) -> 0.86363636 | H106: =IFERROR(F106/D106,0) -> 0.090909091 | I106: 0 | K106: 0 | L106: No | M106: 0 | N106: =ROUND(IFERROR(K106/100,0)*0.6 + IF(L106="Yes",1,IF(L106="No",0,0.3))*0.25 + IFERROR(J106/100,0)*0.15,3) -> 0 | O106: =IF(AND(L106="No",I106=0),"1: Critical (No DBWT + No Wk0)",IF(L106="No","2: High (No DBWT)",IF(I106=0,"3: Elevated (No Wk0)","4: Engaged Early"))) -> 1: Critical (No DBWT + No Wk0)
A107: Academy Intake X | B107: AIX10106 | C107: No | D107: 0 | E107: 0 | F107: 0 | G107: =IFERROR(E107/D107,0) -> 0 | H107: =IFERROR(F107/D107,0) -> 0 | I107: 1 | J107: 80.0333 | K107: 97.03 | L107: Not Tracked | M107: 0 | N107: =ROUND(IFERROR(K107/100,0)*0.6 + IF(L107="Yes",1,IF(L107="No",0,0.3))*0.25 + IFERROR(J107/100,0)*0.15,3) -> 0.777 | O107: =IF(AND(L107="No",I107=0),"1: Critical (No DBWT + No Wk0)",IF(L107="No","2: High (No DBWT)",IF(I107=0,"3: Elevated (No Wk0)","4: Engaged Early"))) -> 4: Engaged Early
A108: Academy Intake X | B108: AIX10107 | C108: No | D108: 5 | E108: 0 | F108: 0 | G108: =IFERROR(E108/D108,0) -> 0 | H108: =IFERROR(F108/D108,0) -> 0 | I108: 1 | J108: 36.6112 | K108: 38.96 | L108: No | M108: 0 | N108: =ROUND(IFERROR(K108/100,0)*0.6 + IF(L108="Yes",1,IF(L108="No",0,0.3))*0.25 + IFERROR(J108/100,0)*0.15,3) -> 0.289 | O108: =IF(AND(L108="No",I108=0),"1: Critical (No DBWT + No Wk0)",IF(L108="No","2: High (No DBWT)",IF(I108=0,"3: Elevated (No Wk0)","4: Engaged Early"))) -> 2: High (No DBWT)
...

Sheet Learner IDs
A1: Batch | B1: Learner ID | C1: Refunded?
A2: Academy Intake X | B2: AIX10001 | C2: Yes
A3: Academy Intake X | B3: AIX10002 | C3: Yes
A4: Academy Intake X | B4: AIX10003 | C4: No
A5: Academy Intake X | B5: AIX10004 | C5: Yes
A6: Academy Intake X | B6: AIX10005 | C6: Yes
A7: Academy Intake X | B7: AIX10006 | C7: Yes
A8: Academy Intake X | B8: AIX10007 | C8: Yes
A9: Academy Intake X | B9: AIX10008 | C9: Yes
A10: Academy Intake X | B10: AIX10009 | C10: No
A11: Academy Intake X | B11: AIX10010 | C11: Yes
A12: Academy Intake X | B12: AIX10011 | C12: No
... A1650: Academy Intake X | B1650: AIX11649 | C1650: No

Sheet Comms Tracker
A1: Learner ID | B1: Delivered | C1: Opened / Read | D1: Clicked | E1: Week
A2: AIX10383 | B2: 5 | C2: 1 | D2: 0 | E2: T-1
A3: AIX10698 | B3: 5 | C3: 4 | D3: 1 | E3: T-1
A4: AIX11027 | B4: 5 | C4: 5 | D4: 0 | E4: T-1
A5: AIX10428 | B5: 6 | C5: 6 | D5: 0 | E5: T-2
A6: AIX11388 | B6: 3 | C6: 1 | D6: 0 | E6: T-3
A7: AIX10642 | B7: 5 | C7: 2 | D7: 0 | E7: T-1
A8: AIX10255 | B8: 8 | C8: 5 | D8: 2 | E8: T-1
A9: AIX10132 | B9: 2 | C9: 1 | D9: 0 | E9: T-1
A10: AIX10002 | B10: 2 | C10: 2 | D10: 1 | E10: T-1
A11: AIX10061 | B11: 8 | C11: 7 | D11: 3 | E11: T-1
A12: AIX10374 | B12: 8 | C12: 7 | D12: 2 | E12: T-1
A13: AIX10439 | B13: 8 | C13: 7 | D13: 3 | E13: T-1
... A1541: AIX11318 | B1541: 24 | C1541: 20 | D1541: 0 | E1541: T-4

Sheet Week 0 Attendance
A1: Learner ID | B1: meeting slug | C1: attendance | D1: live_attendance | E1: passive_attendance
A2: AIX10066 | B2: build-the-problem-solving-mindset | C2: 100 | D2: 99.8168 | E2: 13.8077
A3: AIX10574 | B3: build-the-problem-solving-mindset | C3: 100 | D3: 16.9692 | E3: 99.7177
A4: AIX10362 | B4: build-the-problem-solving-mindset | C4: 100 | D4: 100
A5: AIX10386 | B5: build-the-problem-solving-mindset | C5: 100 | D5: 39.9417 | E5: 59.9718
A6: AIX10280 | B6: build-the-problem-solving-mindset | C6: 100 | D6: 100
A7: AIX11090 | B7: build-the-problem-solving-mindset | C7: 100 | D7: 84.9042 | E7: 97.0027
A8: AIX10028 | B8: build-the-problem-solving-mindset | C8: 100 | D8: 47.4938 | E8: 99.7758
A9: AIX10581 | B9: build-the-problem-solving-mindset | C9: 100 | D9: 99.7002 | E9: 14.4221
A10: AIX10175 | B10: build-the-problem-solving-mindset | C10: 100 | E10: 100.058
A11: AIX10392 | B11: build-the-problem-solving-mindset | C11: 100 | D11: 99.6753 | E11: 100.058
A12: AIX11084 | B12: build-the-problem-solving-mindset | C12: 100 | D12: 60.7744 | E12: 76.7187
A13: AIX10309 | B13: build-the-problem-solving-mindset | C13: 100 | E13: 100.058
A14: AIX10030 | B14: build-the-problem-solving-mindset | C14: 99.9833 | D14: 99.9833
A15: AIX11262 | B15: build-the-problem-solving-mindset | C15: 99.95 | D15: 97.7186 | E15: 20.7904
A16: AIX10356 | B16: build-the-problem-solving-mindset | C16: 99.95 | D16: 95.2623 | E16: 76.5028
A17: AIX10981 | B17: build-the-problem-solving-mindset | C17: 99.9334 | D17: 99.5004 | E17: 50.5563
A18: AIX10422 | B18: build-the-problem-solving-mindset | C18: 99.9251 | D18: 99.9251
A19: AIX11574 | B19: build-the-problem-solving-mindset | C19: 99.9251 | D19: 99.9251
A20: AIX11113 | B20: build-the-problem-solving-mindset | C20: 99.8668 | D20: 99.8668
A21: AIX11093 | B21: build-the-problem-solving-mindset | C21: 99.8168 | D21: 30.8576 | E21: 99.535
A22: AIX10569 | B22: build-the-problem-solving-mindset | C22: 99.7918 | E22: 99.5101
A23: AIX10481 | B23: build-the-problem-solving-mindset | C23: 99.7669 | D23: 99.7669
A24: AIX10549 | B24: build-the-problem-solving-mindset | C24: 99.7336 | D24: 99.7336
A25: AIX10445 | B25: build-the-problem-solving-mindset | C25: 99.7002 | D25: 94.9625 | E25: 37.7449
A26: AIX10153 | B26: build-the-problem-solving-mindset | C26: 99.6919 | D26: 99.6919
A27: AIX10501 | B27: build-the-problem-solving-mindset | C27: 99.6919 | D27: 99.5837 | E27: 8.49386
A28: AIX10108 | B28: build-the-problem-solving-mindset | C28: 99.6336 | D28: 99.6336
A29: AIX10418 | B29: build-the-problem-solving-mindset | C29: 99.6087 | D29: 69.2007 | E29: 36.6988
A30: AIX10116 | B30: build-the-problem-solving-mindset | C30: 99.6003 | D30: 99.6003 | E30: 6.0279
A31: AIX10398 | B31: build-the-problem-solving-mindset | C31: 99.592 | D31: 99.592
A32: AIX11181 | B32: build-the-problem-solving-mindset | C32: 99.592 | D32: 99.592
A33: AIX10416 | B33: build-the-problem-solving-mindset | C33: 99.5754 | D33: 99.5754
A34: AIX10401 | B34: build-the-problem-solving-mindset | C34: 99.567 | D34: 44.438 | E34: 69.2046
A35: AIX10547 | B35: build-the-problem-solving-mindset | C35: 99.5587 | D35: 86.9026 | E35: 89.8705
A36: AIX10405 | B36: build-the-problem-solving-mindset | C36: 99.5254 | D36: 91.4571 | E36: 9.32414
A37: AIX10546 | B37: build-the-problem-solving-mindset | C37: 99.5171 | D37: 95.1957 | E37: 13.733
A38: AIX10528 | B38: build-the-problem-solving-mindset | C38: 99.5004 | D38: 94.03 | E38: 38.8409
A39: AIX10467 | B39: build-the-problem-solving-mindset | C39: 99.4921 | D39: 65.97 | E39: 97.4593
A40: AIX10384 | B40: build-the-problem-solving-mindset | C40: 99.4921 | D40: 71.5404 | E40: 27.8728
A41: AIX10449 | B41: build-the-problem-solving-mindset | C41: 99.3256 | D41: 99.3256
A42: AIX10149 | B42: build-the-problem-solving-mindset | C42: 99.3089 | E42: 99.0286
A43: AIX10062 | B43: build-the-problem-solving-mindset | C43: 99.3006 | D43: 99.3006
A44: AIX10244 | B44: build-the-problem-solving-mindset | C44: 99.2756 | D44: 99.2756
A45: AIX11274 | B45: build-the-problem-solving-mindset | C45: 99.2756 | D45: 99.2256 | E45: 17.6935
A46: AIX11204 | B46: build-the-problem-solving-mindset | C46: 99.2756 | E46: 98.9954
A47: AIX10372 | B47: build-the-problem-solving-mindset | C47: 99.2589 | D47: 98.9092 | E47: 50.9714
A48: AIX11587 | B48: build-the-problem-solving-mindset | C48: 99.2506 | D48: 99.2506
A49: AIX10057 | B49: build-the-problem-solving-mindset | C49: 99.2173 | D49: 99.2173
A50: AIX11003 | B50: build-the-problem-solving-mindset | C50: 99.184 | D50: 72.1232 | E50: 26.9844
A51: AIX10575 | B51: build-the-problem-solving-mindset | C51: 99.1341 | D51: 99.1341
A52: AIX10151 | B52: build-the-problem-solving-mindset | C52: 99.1257 | E52: 98.8459
A53: AIX10289 | B53: build-the-problem-solving-mindset | C53: 98.9842 | D53: 98.8343 | E53: 4.0269
A54: AIX11196 | B54: build-the-problem-solving-mindset | C54: 98.9092 | E54: 98.63
A55: AIX11510 | B55: build-the-problem-solving-mindset | C55: 98.851 | D55: 98.851
A56: AIX10567 | B56: build-the-problem-solving-mindset | C56: 98.8426 | D56: 42.6311 | E56: 95.7738
A57: AIX10522 | B57: build-the-problem-solving-mindset | C57: 98.8343 | D57: 98.8343
A58: AIX10304 | B58: build-the-problem-solving-mindset | C58: 98.7094 | D58: 98.7094
A59: AIX10479 | B59: build-the-problem-solving-mindset | C59: 98.6844 | D59: 98.6844
A60: AIX11032 | B60: build-the-problem-solving-mindset | C60: 98.6012 | E60: 98.3228
A61: AIX11189 | B61: build-the-problem-solving-mindset | C61: 98.5762 | D61: 18.776 | E61: 97.9741
A62: AIX10572 | B62: build-the-problem-solving-mindset | C62: 98.443 | D62: 98.1182 | E62: 79.4753
A63: AIX11012 | B63: build-the-problem-solving-mindset | C63: 98.4346 | D63: 85.8784 | E63: 12.8363
A64: AIX11182 | B64: build-the-problem-solving-mindset | C64: 98.368 | D64: 98.368
A65: AIX10347 | B65: build-the-problem-solving-mindset | C65: 98.2931 | D65: 3.55537 | E65: 98.0156
A66: AIX10503 | B66: build-the-problem-solving-mindset | C66: 98.1765 | D66: 98.1765
A67: AIX10897 | B67: build-the-problem-solving-mindset | C67: 98.1599 | D67: 94.0799 | E67: 8.80106
A68: AIX11216 | B68: build-the-problem-solving-mindset | C68: 97.8684 | D68: 59.6753 | E68: 38.0854
A69: AIX10552 | B69: build-the-problem-solving-mindset | C69: 97.8518 | E69: 97.5756
A70: AIX10435 | B70: build-the-problem-solving-mindset | C70: 97.7519 | D70: 97.602 | E70: 0.381933
A71: AIX10415 | B71: build-the-problem-solving-mindset | C71: 97.6353 | D71: 97.6353
A72: AIX10273 | B72: build-the-problem-solving-mindset | C72: 97.3439 | D72: 97.3439
A73: AIX11257 | B73: build-the-problem-solving-mindset | C73: 96.7943 | D73: 96.7943
A74: AIX10276 | B74: build-the-problem-solving-mindset | C74: 96.7444 | D74: 96.7444
A75: AIX11141 | B75: build-the-problem-solving-mindset | C75: 96.6028 | D75: 43.2057 | E75: 53.2464
A76: AIX10358 | B76: build-the-problem-solving-mindset | C76: 96.5779 | D76: 96.5779
A77: AIX10023 | B77: build-the-problem-solving-mindset | C77: 96.5279 | D77: 96.5279
A78: AIX10395 | B78: build-the-problem-solving-mindset | C78: 96.5196 | D78: 95.0375 | E78: 6.63401
A79: AIX10934 | B79: build-the-problem-solving-mindset | C79: 96.5196 | D79: 96.2948 | E79: 64.09
A80: AIX10321 | B80: build-the-problem-solving-mindset | C80: 96.4696 | D80: 7.84346 | E80: 96.1973
A81: AIX10396 | B81: build-the-problem-solving-mindset | C81: 96.428 | D81: 96.428
A82: AIX10852 | B82: build-the-problem-solving-mindset | C82: 96.3697 | E82: 96.0976
A83: AIX11550 | B83: build-the-problem-solving-mindset | C83: 96.3031 | D83: 6.90258 | E83: 89.1481
A84: AIX11172 | B84: build-the-problem-solving-mindset | C84: 95.97 | D84: 95.97
A85: AIX10589 | B85: build-the-problem-solving-mindset | C85: 95.9284 | D85: 64.8626 | E85: 90.3354
A86: AIX10864 | B86: build-the-problem-solving-mindset | C86: 95.5121 | D86: 87.4771 | E86: 8.01229
A87: AIX10345 | B87: build-the-problem-solving-mindset | C87: 95.4621 | D87: 95.4621
A88: AIX11529 | B88: build-the-problem-solving-mindset | C88: 95.4038 | D88: 69.95 | E88: 94.4288
A89: AIX10421 | B89: build-the-problem-solving-mindset | C89: 95.3455 | E89: 95.0764
A90: AIX11228 | B90: build-the-problem-solving-mindset | C90: 94.6628 | D90: 94.6628
A91: AIX11050 | B91: build-the-problem-solving-mindset | C91: 94.5379 | D91: 94.5379
A92: AIX10410 | B92: build-the-problem-solving-mindset | C92: 94.413 | D92: 94.413
A93: AIX10456 | B93: build-the-problem-solving-mindset | C93: 94.3963 | D93: 0.50791 | E93: 94.1299
A94: AIX10303 | B94: build-the-problem-solving-mindset | C94: 94.2548 | D94: 94.2548
A95: AIX10565 | B95: build-the-problem-solving-mindset | C95: 94.1632 | D95: 72.3231 | E95: 22.7499
A96: AIX10373 | B96: build-the-problem-solving-mindset | C96: 94.005 | D96: 86.0783 | E96: 7.90435
A97: AIX11185 | B97: build-the-problem-solving-mindset | C97: 93.9051 | D97: 93.9051
A98: AIX10590 | B98: build-the-problem-solving-mindset | C98: 93.5221 | D98: 93.5221
A99: AIX10470 | B99: build-the-problem-solving-mindset | C99: 93.4221 | D99: 84.3297 | E99: 73.0737
A100: AIX10017 | B100: build-the-problem-solving-mindset | C100: 93.3805 | D100: 93.3805
...

Sheet Overall Attendance
A1: Learner ID | B1: overall_attendance
A2: AIX11619 | B2: 20
A3: AIX11623 | B3: 93.73
A4: AIX11624 | B4: 100
A5: AIX11607 | B5: 26.02
A6: AIX11640 | B6: 99.61
A7: AIX11635 | B7: 15.57
A8: AIX11621 | B8: 100
A9: AIX11616 | B9: 100
A10: AIX11606 | B10: 22.22
A11: AIX11628 | B11: 22.41
A12: AIX11631 | B12: 95.77
A13: AIX11615 | B13: 16.97
... A1649: AIX10255 | B1649: 20

Sheet Dashboard Walkthrough
A1: Learner ID | B1: Lead Punched | C1: DBWT completed
A2: AIX10698 | B2: 44902.599 | C2: 44761.644
A3: AIX11260 | B3: 44780.685 | C3: No
A4: AIX10455 | B4: 44749.969 | C4: 44763.625
A5: AIX11388 | B5: 26/06/22 16:46 | C5: 44741.468
A6: AIX10383 | B6: 44902.738 | C6: No
A7: AIX11027 | B7: 44902.553 | C7: 44758.583
A8: AIX10255 | B8: 44872.912 | C8: No
A9: AIX10132 | B9: 44872.865 | C9: No
A10: AIX10002 | B10: 44872.851 | C10: No
A11: AIX10061 | B11: 44872.825 | C11: 44758.773
A12: AIX10374 | B12: 44872.803 | C12: 44758.783
A13: AIX10439 | B13: 44872.797 | C13: No
A14: AIX10091 | B14: 44872.795 | C14: No
A15: AIX11416 | B15: 44872.794 | C15: 44762.832
A16: AIX10598 | B16: 44872.794 | C16: 44759.545
A17: AIX10282 | B17: 44872.786 | C17: 44763.869
A18: AIX10680 | B18: 44872.776 | C18: 44766.715
A19: AIX11426 | B19: 44872.774 | C19: 44756.835
A20: AIX10495 | B20: 44872.749 | C20: 44758.547
A21: AIX10360 | B21: 44872.748 | C21: 44761.77
A22: AIX10834 | B22: 44872.742 | C22: 44762.564
A23: AIX10125 | B23: 44872.732 | C23: 44769.794
A24: AIX10243 | B24: 44872.728 | C24: 44764.671
A25: AIX10139 | B25: 44872.722 | C25: No
A26: AIX11268 | B26: 44872.72 | C26: No
A27: AIX11608 | B27: 44872.719 | C27: No
A28: AIX11240 | B28: 44872.715 | C28: 44756.708
A29: AIX11451 | B29: 44872.713 | C29: 44762.526
A30: AIX11215 | B30: 44872.71 | C30: No
A31: AIX11590 | B31: 44872.707 | C31: 44765.583
A32: AIX10068 | B32: 44872.705 | C32: 44759.666
A33: AIX11272 | B33: 44872.704 | C33: 44757.926
A34: AIX10711 | B34: 44872.701 | C34: No
A35: AIX11527 | B35: 44872.697 | C35: No
A36: AIX10192 | B36: 44872.697 | C36: 44765.688
A37: AIX10338 | B37: 44872.697 | C37: 44760.699
A38: AIX10670 | B38: 44872.697 | C38: 44757.749
A39: AIX10500 | B39: 44872.692 | C39: 44761.817
A40: AIX10520 | B40: 44872.692 | C40: 44760.511
A41: AIX10561 | B41: 44872.686 | C41: 44762.872
A42: AIX10510 | B42: 44872.685 | C42: No
A43: AIX10317 | B43: 44872.682 | C43: 44758.561
A44: AIX10629 | B44: 44872.681 | C44: 44759.775
A45: AIX10760 | B45: 44872.677 | C45: 44761.791
A46: AIX11339 | B46: 44872.676 | C46: No
A47: AIX10412 | B47: 44872.676 | C47: 44757.783
A48: AIX11180 | B48: 44872.674 | C48: 44757.464
A49: AIX10266 | B49: 44872.674 | C49: No
A50: AIX10341 | B50: 44872.668 | C50: No
A51: AIX10418 | B51: 44872.664 | C51: 44765.666
A52: AIX10533 | B52: 44872.656 | C52: 44756.606
A53: AIX11016 | B53: 44872.655 | C53: 44760.891
A54: AIX10870 | B54: 44872.652 | C54: 44764.87
A55: AIX11278 | B55: 44872.651 | C55: 44763.751
A56: AIX11598 | B56: 44872.651 | C56: No
A57: AIX10811 | B57: 44872.651 | C57: 44762.672
A58: AIX10274 | B58: 44872.645 | C58: 44761.735
A59: AIX10891 | B59: 44872.645 | C59: 44762.521
A60: AIX10460 | B60: 44872.644 | C60: 44762.874
A61: AIX10206 | B61: 44872.644 | C61: No
A62: AIX11565 | B62: 44872.641 | C62: 44759.906
A63: AIX10913 | B63: 44872.64 | C63: 44764.906
A64: AIX10541 | B64: 44872.631 | C64: 44764.751
A65: AIX10772 | B65: 44872.625 | C65: 44764.908
A66: AIX10211 | B66: 44872.619 | C66: No
A67: AIX11093 | B67: 44872.617 | C67: 44754.867
A68: AIX10454 | B68: 44872.615 | C68: 44762.738
A69: AIX10978 | B69: 44872.607 | C69: 44758.645
A70: AIX11365 | B70: 44872.603 | C70: 44762.609
A71: AIX10112 | B71: 44872.601 | C71: No
A72: AIX10527 | B72: 44872.596 | C72: 44758.833
A73: AIX10954 | B73: 44872.593 | C73: No
A74: AIX10137 | B74: 44872.588 | C74: No
A75: AIX10402 | B75: 44872.585 | C75: No
A76: AIX10552 | B76: 44872.584 | C76: 44759.832
A77: AIX11634 | B77: 44872.581 | C77: 44758.721
A78: AIX10672 | B78: 44872.581 | C78: No
A79: AIX11218 | B79: 44872.578 | C79: 44762.831
A80: AIX10736 | B80: 44872.576 | C80: 44766.798
A81: AIX10945 | B81: 44872.575 | C81: No
A82: AIX10878 | B82: 44872.573 | C82: No
A83: AIX10705 | B83: 44872.562 | C83: No
A84: AIX10107 | B84: 44872.553 | C84: No
A85: AIX10461 | B85: 44872.551 | C85: 44759.585
A86: AIX10199 | B86: 44872.551 | C86: 44759.811
A87: AIX10992 | B87: 44872.55 | C87: 44757.783
A88: AIX10707 | B88: 44872.545 | C88: 44772.874
A89: AIX10708 | B89: 44872.541 | C89: 44759.96
A90: AIX11530 | B90: 44872.53 | C90: 44757.739
A91: AIX10654 | B91: 44872.525 | C91: 44758.744
A92: AIX11022 | B92: 44872.522 | C92: No
A93: AIX10626 | B93: 44872.519 | C93: 44757.774
A94: AIX10094 | B94: 44872.517 | C94: 44757.434
A95: AIX10449 | B95: 44872.499 | C95: No
A96: AIX10024 | B96: 44872.499 | C96: No
A97: AIX10740 | B97: 44872.49 | C97: No
A98: AIX10259 | B98: 44872.489 | C98: No
A99: AIX10227 | B99: 44872.485 | C99: No
A100: AIX10824 | B100: 44872.484 | C100: 44756.774
...

Sheet Refund Team Tracker
A1: Date on which the refund request was submitted by the candidate | B1: Learner ID | C1: Stage | D1: Ownership to Follow Up | E1: Within / Outside Refund period | F1: Was Refund intimated within the refund period to BDA/BDM previously | G1: Date of earliest intimation (if applicable) | H1: Batch | I1: Whether Loan from NBFC obtained/approved | J1: Closed Sales as per BD | K1: Batch Start Date | L1: No. of days after/before batch start date the request was raised by the learner | M1: Date on which finance team is informed to make the payment | N1: Remark | O1: Detailed reason for the refund as communicated by the candidate | P1: Partial / Full Refund | Q1: Probable to rejoin | R1: Unique Student ID
A2: 44768 | B2: AIX11549 | C2: Retained | D2: Completed | E2: Within Refund window | F2: NA | G2: NA | H2: Academy Intake X | J2: yes | K2: 44754 | L2: 14 | M2: Retained
A3: 44767 | B3: AIX11402 | C3: Retained | D3: Completed | E3: Within Refund window | F3: NA | G3: NA | H3: Academy Intake X | J3: yes | K3: 44754 | L3: 13 | M3: Retained | O3: The learner does not see the value in the program and believes he can achieve the outcomes on his own as he has people in the industry he knows being a developer for 4 yrs. He appreciated the quality of the program but says its not up to the monetary value. Informed by SP Mr. Varun Awasthi | P3: Full Refund | Q3: yes
A4: 44767 | B4: AIX10761 | C4: Retained | D4: Completed | E4: Within Refund window | F4: NA | G4: NA | H4: Academy Intake X | J4: yes | K4: 44754 | L4: 13 | M4: Retained
A5: 44767 | B5: AIX10413 | C5: Retained | D5: Completed | E5: Within Refund window | F5: NA | G5: NA | H5: Academy Intake X | J5: yes | K5: 44754 | L5: 13 | M5: Retained
A6: 44767 | B6: AIX11026 | C6: Retained | D6: Completed | E6: Within Refund window | F6: NA | G6: NA | H6: Academy Intake X | J6: yes | K6: 44754 | L6: 13 | M6: Retained
A7: 44767 | B7: AIX10998 | C7: Retained | D7: Completed | E7: Within Refund window | F7: NA | G7: NA | H7: Academy Intake X | J7: yes | K7: 44754 | L7: 13 | M7: Retained
A8: 44766 | B8: AIX11170 | C8: Retained | D8: Completed | E8: Within Refund window | F8: NA | G8: NA | H8: Academy Intake X | J8: yes | K8: 44754 | L8: 12 | M8: Retained
A9: 44766 | B9: AIX11541 | C9: Retained | D9: Completed | E9: Within Refund window | F9: NA | G9: NA | H9: Academy Intake X | J9: yes | K9: 44754 | L9: 12 | M9: Retained
A10: 44766 | B10: AIX10749 | C10: Retained | D10: Completed | E10: Within Refund window | F10: NA | G10: NA | H10: Academy Intake X | J10: yes | K10: 44754 | L10: 12 | M10: Retained
A11: 44765 | B11: AIX10070 | C11: Retained | D11: Completed | E11: Within Refund window | F11: NA | G11: NA | H11: Academy Intake X | J11: yes | K11: 44754 | L11: 11 | M11: Retained
A12: 44765 | B12: AIX11647 | C12: Retained | D12: Completed | E12: Within Refund window | F12: NA | G12: NA | H12: Academy Intake X | J12: yes | K12: 44754 | L12: 11 | M12: Retained
A13: 44762 | B13: AIX10397 | C13: Retained | D13: Completed | E13: Within Refund window | F13: NA | G13: NA | H13: Academy Intake X | J13: yes | K13: 44754 | L13: 8 | M13: Retained
A14: 44761 | B14: AIX11191 | C14: Retained | D14: Completed | E14: Within Refund window | F14: NA | G14: NA | H14: Academy Intake X | J14: yes | K14: 44754 | L14: 7 | M14: Retained
A15: 44760 | B15: AIX11230 | C15: Retained | D15: Completed | E15: Within Refund window | F15: NA | G15: NA | H15: Academy Intake X | J15: yes | K15: 44754 | L15: 6 | M15: Retained
... A21: 44757 | B21: AIX11044 | C21: Retained | D21: Completed | E21: Within Refund window | F21: NA | G21: NA | H21: Academy Intake X | J21: yes | K21: 44754 | L21: 3 | M21: Retained
A22: 44754 | B22: AIX11619 | C22: Refund Closed | D22: Completed | E22: Within Refund window | F22: NA | G22: NA | H22: Academy Intake X | J22: yes | K22: 44754 | L22: 0 | M22: 44755 | O22: The learner has many interviews lined up and doesn't have time to attend classes. | P22: Full Refund | Q22: yes
A23: 44751 | B23: AIX10179 | C23: Retained | D23: Completed | E23: Within Refund window | F23: NA | G23: NA | H23: Academy Intake X | J23: yes | K23: 44754 | L23: -3 | M23: Retained
A24: 44734 | B24: AIX11582 | C24: Retained | D24: Completed | E24: Within Refund window | F24: NA | G24: NA | H24: Academy Intake X | J24: yes | K24: 44754 | L24: -20 | M24: Retained
A25: 44731 | B25: AIX11544 | C25: DB to be Deactived | D25: Ayush | E25: Within Refund window | F25: NA | G25: NA | H25: Academy Intake X | K25: 44754 | L25: -23 | M25: 44762 | O25: The learner has some personal issues and hence wants to go ahead with the refund, this was initially retained from SPs but the cx was adamant for a refund | P25: Full Refund | Q25: yes
A26: 44736 | B26: AIX11627 | C26: DB to be Deactived | D26: Ayush | E26: Within Refund window | F26: NA | G26: NA | H26: Academy Intake X | J26: yes | K26: 44754 | L26: -18 | M26: 44739 | O26: His CC is not listed in no cost EMI and he doesn't want to go for the loan. Informed by Ms. Annu Kumari | P26: Full Refund | Q26: yes
A27: 44738 | B27: AIX10256 | C27: DB to be Deactived | D27: Ayush | E27: Within Refund window | F27: NA | G27: NA | H27: Academy Intake X | J27: yes | K27: 44754 | L27: -16 | M27: 44740 | O27: This learner has some personal issues due to which he does not want to continue with us | P27: Full Refund | Q27: yes
A28: 44739 | B28: AIX10097 | C28: DB to be Deactived | D28: Ayush | E28: Within Refund window | F28: NA | G28: NA | H28: Academy Intake X | J28: yes | K28: 44754 | L28: -15 | M28: 44740 | O28: This learner has family issues due to which he cannot continue with us | P28: Full Refund | Q28: yes
A29: 44739 | B29: AIX10010 | C29: DB to be Deactived | D29: Ayush | E29: Within Refund window | F29: NA | G29: NA | H29: Academy Intake X | J29: yes | K29: 44754 | L29: -15 | M29: 44740 | O29: His loan is not getting sanctioned and he doesn't have any co applicant to give | P29: Full Refund | Q29: yes
A30: 44739 | B30: AIX10665 | C30: DB to be Deactived | D30: Ayush | E30: Within Refund window | F30: NA | G30: NA | H30: Academy Intake X | J30: yes | K30: 44754 | L30: -15 | M30: 44768 | O30: No update from PS nor SP despite multiple reminder, this learner was initially retained by SP Mr. Kuppa Nagarjuna but later the cx followed up for a refund and hence had to be processed as request is wrp | P30: Full Refund | Q30: yes
A31: 44739 | B31: AIX10031 | C31: DB to be Deactived | D31: Ayush | E31: Within Refund window | F31: NA | G31: NA | H31: Academy Intake X | J31: yes | K31: 44754 | L31: -15 | M31: 44741 | O31: This learner doesnt want to go ahead with loan process as his family members are not supporting. | P31: Full Refund | Q31: yes
A32: 44738 | B32: AIX10222 | C32: DB to be Deactived | D32: Ayush | E32: Within Refund window | F32: NA | G32: NA | H32: Academy Intake X | J32: yes | K32: 44754 | L32: -16 | M32: 44741 | O32: This learner is going through some financial emergency at his end at the moment so he will not be able to go ahead currently. Informed by SP | P32: Full Refund | Q32: yes
A33: 44741 | B33: AIX10007 | C33: DB to be Deactived | D33: Ayush | E33: Within Refund window | F33: NA | G33: NA | H33: Academy Intake X | J33: yes | K33: 44754 | L33: -13 | M33: 44753 | O33: This learner has some personal major issues due to which he could not proceed further. | P33: Full Refund | Q33: yes
A34: 44741 | B34: AIX10012 | C34: DB to be Deactived | D34: Ayush | E34: Within Refund window | F34: NA | G34: NA | H34: Academy Intake X | J34: yes | K34: 44754 | L34: -13 | M34: 44760 | O34: There was no proper update from the sales team regarding this cx. The learner kept following up and hence had to push further to finance team | P34: Full Refund | Q34: yes
A35: 44742 | B35: AIX10109 | C35: DB to be Deactived | D35: Ayush | E35: Within Refund window | F35: NA | G35: NA | H35: Academy Intake X | J35: yes | K35: 44754 | L35: -12 | M35: 44743 | O35: The learner has some family issue currently, her mental state is not fine. She needs a break and might join after few months. | P35: Full Refund | Q35: yes
A36: 44742 | B36: AIX11547 | C36: DB to be Deactived | D36: Ayush | E36: Within Refund window | F36: NA | G36: NA | H36: Academy Intake X | J36: yes | K36: 44754 | L36: -12 | M36: 44769 | O36: The learner was never interested in the course. We changed his class timings and addressed whatever complains he had. We worked on that now he comes up with another reason saying instructor is less experienced than his experience. He doesn't want the course. Informed by PS Ms. Sonam Thakur | P36: Full Refund | Q36: yes
A37: 44742 | B37: AIX10675 | C37: DB to be Deactived | D37: Ayush | E37: Within Refund window | F37: NA | G37: NA | H37: Academy Intake X | J37: yes | K37: 44754 | L37: -12 | M37: 44754 | N37: Full refund approved by Harshvardhan | O37: The learner's workload got increased due to some project, hence refund | P37: Full Refund | Q37: yes
A38: 44743 | B38: AIX10019 | C38: DB to be Deactived | D38: Ayush | E38: Within Refund window | F38: NA | G38: NA | H38: Academy Intake X | J38: yes | K38: 44754 | L38: -11 | M38: 44744 | O38: Learner has is MVP reday to launch his start up, since his business mentor told him to invest more time in launching prod, he wants to get transist off. | P38: Full Refund | Q38: yes
A39: 44743 | B39: AIX10170 | C39: DB to be Deactived | D39: Ayush | E39: Within Refund window | F39: NA | G39: NA | H39: Academy Intake X | J39: yes | K39: 44754 | L39: -11 | M39: 44764 | O39: The learner is working as a Project Manager having 16 years of work experience, the learner thought much about this course and finally decided this course is not suitable for me as it is totally technical course in depth. And as a project manager, he needs knowledge of DS but not in-depth as a developer.The learner decided to go for some management-related certifications to grow my career. | P39: Full Refund | Q39: yes
A40: 44743 | B40: AIX10879 | C40: Forwarded to finance | D40: Finance | E40: Within Refund window | F40: NA | G40: NA | H40: Academy Intake X | J40: yes | K40: 44754 | L40: -11 | M40: 44775 | O40: He's not happy with the course and he thinks he can learn this on his own. He didn't find the sessions useful. There was significant delay in approval from SP or PS team. Hence full refund approved by HP over email due to delay in timelines | P40: Full Refund | Q40: yes
A41: 44743 | B41: AIX10350 | C41: DB to be Deactived | D41: Ayush | E41: Within Refund window | F41: NA | G41: NA | H41: Academy Intake X | J41: yes | K41: 44754 | L41: -11 | M41: 44751 | O41: This learner recently got an offer letter from the govt. of Odhisa in the electrical engg dept. hence refund | P41: Full Refund | Q41: yes
A42: 44743 | B42: AIX11391 | C42: DB to be Deactived | D42: Ayush | E42: Within Refund window | F42: NA | G42: NA | H42: Academy Intake X | J42: yes | K42: 44754 | L42: -11 | M42: 44750 | O42: The learner needs validation on what better this program can offer to him as he is already sitting at a package of 40 LPA in 2 years. Therefore, he believes it is easy for him to crack the Tier - 1 PBC without the help of the platform. He is mainly inclined toward Google & Microsoft. The learner can be retained if he sees what we have to offer him in the trial period. But he does not want to go for a loan or want to pay the remaining amount until the trial ends. Hence, he initiated the refund. Informed by SP Suman Panda | P42: Full Refund | Q42: yes
A43: 44743 | B43: AIX10270 | C43: DB to be Deactived | D43: Ayush | E43: Within Refund window | F43: NA | G43: NA | H43: Academy Intake X | J43: yes | K43: 44754 | L43: -11 | M43: 44769 | O43: No update from SP nor PS. Hence reason unclear. Transferred due to delay in timelines. | P43: Full Refund | Q43: yes
A44: 44744 | B44: AIX10090 | C44: DB to be Deactived | D44: Ayush | E44: Within Refund window | F44: NA | G44: NA | H44: Academy Intake X | J44: yes | K44: 44754 | L44: -10 | M44: 44759 | O44: he has joined a new company and is not able to find time to give it to our course. | P44: Full Refund | Q44: yes
A45: 44744 | B45: AIX10122 | C45: DB to be Deactived | D45: Ayush | E45: Within Refund window | F45: NA | G45: NA | H45: Academy Intake X | J45: yes | K45: 44754 | L45: -10 | M45: 44763 | O45: The learner is unwilling to go ahead for the course as he is not interested in taking the loan . The financial situation is also unwell and is considering joining back for the course when the amount is available . | P45: Full Refund | Q45: yes
A46: 44744 | B46: AIX10121 | C46: DB to be Deactived | D46: Ayush | E46: Within Refund window | F46: NA | G46: NA | H46: Academy Intake X | J46: yes | K46: 44754 | L46: -10 | M46: 44750 | O46: Cx cannot continue because his grandmother is hospitalized | P46: Full Refund | Q46: yes
A47: 44745 | B47: AIX10005 | C47: DB to be Deactived | D47: Ayush | E47: Within Refund window | F47: NA | G47: NA | H47: Academy Intake X | J47: yes | K47: 44754 | L47: -9 | M47: 44745 | O47: Please initiate the refund as soon as possible as he is saying some really objectionable things to me which is unacceptable. | P47: Full Refund | Q47: yes
A48: 44747 | B48: AIX10081 | C48: DB to be Deactived | D48: Ayush | E48: Within Refund window | F48: NA | G48: NA | H48: Academy Intake X | J48: yes | K48: 44754 | L48: -7 | M48: 44752 | O48: Abhijeet has genuine problems crop up at his end, father being hospitalized, | P48: Full Refund | Q48: yes
A49: 44747 | B49: AIX10043 | C49: DB to be Deactived | D49: Ayush | E49: Within Refund window | F49: NA | G49: NA | H49: Academy Intake X | J49: yes | K49: 44754 | L49: -7 | M49: 44761 | O49: The cx is relocating to UK and hence cannot continue with us owing to time issues | P49: Full Refund | Q49: yes
... A54: 44748 | B54: AIX10044 | C54: DB to be Deactived | D54: Ayush | E54: Within Refund window | F54: NA | G54: NA | H54: Academy Intake X | J54: yes | K54: 44754 | L54: -6 | M54: 44750 | O54: This learner has some medical emergency as informed by SP Mr. Ujjwal Saini. | P54: Full Refund | Q54: yes
A55: 44746 | B55: AIX10119 | C55: DB to be Deactived | D55: Ayush | E55: Within Refund window | H55: Academy Intake X | J55: yes | M55: 44750 | O55: This learner feels the company policies are not that fair, the learner feels he was pressurized by the SPs to pay the amount. The learner felt extremely harassed for a whole day by constant calls from every direction to join and to pay right now. The learner just wants to get out of this course asap. Hence refund | P55: Full Refund | Q55: yes
A56: 44746 | B56: AIX11356 | C56: DB to be Deactived | D56: Ayush | E56: Within Refund window | H56: Academy Intake X | J56: yes | M56: 44750 | O56: This learner does not want any third party loan | P56: Full Refund | Q56: yes
A57: 44746 | B57: AIX10261 | C57: DB to be Deactived | D57: Ayush | E57: Within Refund window | H57: Academy Intake X | J57: yes | M57: 44755 | O57: This learner got an offer from a different organization, next day after her enrolment. Hence refund | P57: Full Refund | Q57: yes
A58: 44745 | B58: AIX10005 | C58: UTR Details to be shared to candidate | D58: Sudhish | E58: Within Refund window | H58: Academy Intake X | J58: yes | M58: NA | N58: Duplicate entry | O58: Duplicate entry
A59: 44745 | B59: AIX11468 | C59: DB to be Deactived | D59: Ayush | E59: Within Refund window | H59: Academy Intake X | J59: yes | M59: 44756 | O59: personal reason | P59: Full Refund | Q59: yes
A60: 44749 | B60: AIX10018 | C60: DB to be Deactived | D60: Ayush | E60: Within Refund window | F60: NA | G60: NA | H60: Academy Intake X | J60: yes | K60: 44754 | L60: -5 | M60: 44752 | O60: The learner's father passed away and she is not in a state to move ahead. | P60: Full Refund | Q60: yes
A61: 44749 | B61: AIX10112 | C61: DB to be Deactived | D61: Ayush | E61: Within Refund window | F61: NA | G61: NA | H61: Academy Intake X | K61: 44754 | L61: -5 | M61: 44750 | O61: This learner has financial issues going on in his family, hence refund | P61: Full Refund | Q61: yes
A62: 44750 | B62: AIX10215 | C62: DB to be Deactived | D62: Ayush | E62: Within Refund window | F62: NA | G62: NA | H62: Academy Intake X | J62: yes | K62: 44754 | L62: -4 | M62: 44754 | O62: cx is really adamant for a refund.informed by SP | P62: Full Refund | Q62: yes
A63: 44749 | B63: AIX10245 | C63: DB to be Deactived | D63: Ayush | E63: Within Refund window | F63: NA | G63: NA | H63: Academy Intake X | J63: yes | K63: 44754 | L63: -5 | M63: 44751 | O63: The learner said he has financial issues right now plus other commitments where in he cannot adjust | P63: Full Refund | Q63: yes
A64: 44747 | B64: AIX10263 | C64: DB to be Deactived | D64: Ayush | E64: Within Refund window | F64: NA | G64: NA | H64: Academy Intake X | J64: yes | K64: 44754 | L64: -7 | M64: 44750 | O64: PS Ms. Bandna Pathania informed that the cx is unwilling to make the rest of the payment citing personal issues, hence refund | P64: Full Refund | Q64: yes
A65: 44750 | B65: AIX10110 | C65: DB to be Deactived | D65: Ayush | E65: Within Refund window | F65: NA | G65: NA | H65: Academy Intake X | J65: yes | K65: 44754 | L65: -4 | M65: 44750 | O65: The learner will not be able to pay the loan as he already has an education loan going on. Also, he is the only person earning for the family whereas his family is even banking upon him for a house loan. He doesn't think it is the right time for him to start with another liability as he isn't ready for it. | P65: Full Refund | Q65: yes
A66: 44750 | B66: AIX10257 | C66: UTR Details to be shared to candidate | D66: Sudhish | E66: Within Refund window | F66: NA | G66: NA | H66: Academy Intake X | J66: yes | K66: 44754 | L66: -4 | M66: 44750 | P66: Full Refund | Q66: yes
A67: 44751 | B67: AIX10196 | C67: DB to be Deactived | D67: Ayush | E67: Within Refund window | F67: NA | G67: NA | H67: Academy Intake X | J67: yes | K67: 44754 | L67: -3 | M67: 44756 | P67: Full Refund | Q67: yes
A68: 44751 | B68: AIX10067 | C68: DB to be Deactived | D68: Ayush | E68: Within Refund window | F68: NA | G68: NA | H68: Academy Intake X | J68: yes | K68: 44754 | L68: -3 | M68: 44769 | O68: This learner is always complaining as per SP Mr. Lakshaya Sharma. This learner has a very casual attitude and is very unprofessional. | P68: Full Refund | Q68: yes
A69: 44751 | B69: AIX10198 | C69: DB to be Deactived | D69: Ayush | E69: Within Refund window | F69: NA | G69: NA | H69: Academy Intake X | J69: yes | K69: 44754 | L69: -3 | M69: 44752 | O69: she is having a lot of additional work from the company and she won't be able to invest time into the same. | P69: Full Refund | Q69: yes
A70: 44746 | B70: AIX10214 | C70: DB to be Deactived | D70: Ayush | E70: Within Refund window | F70: NA | G70: NA | H70: Academy Intake X | J70: yes | K70: 44754 | L70: -8 | M70: 44752 | O70: Cx occupied for this whole year and won't be able to continue with the course. | P70: Full Refund | Q70: yes
A71: 44751 | B71: AIX11306 | C71: DB to be Deactived | D71: Ayush | E71: Within Refund window | F71: NA | G71: NA | H71: Academy Intake X | J71: yes | K71: 44754 | L71: -3 | M71: 44753 | O71: The learner got placed into jio at very good salary and wants to join after a year or two. He likes course but for now want to focus on new team and job. | P71: Full Refund | Q71: yes
A72: 44752 | B72: AIX11600 | C72: DB to be Deactived | D72: Ayush | E72: Within Refund window | F72: NA | G72: NA | H72: Academy Intake X | J72: yes | K72: 44754 | L72: -2 | M72: 44756 | O72: 1) He has resigned his current employment - looking for a new job. Is on his notice period 2) What if he is not able to pay his EMI since he might take a few more months to get employed. 3) I work in cyber security, therefore I can't really relate to the themes. 4) 3 lakh is a lot of money, and I want to devote myself fully. 5) want to work on projects first - which we do it in the last so that he gets the Job | P72: Full Refund | Q72: yes
A73: 44753 | B73: AIX10006 | C73: DB to be Deactived | D73: Ayush | E73: Within Refund window | F73: NA | G73: NA | H73: Academy Intake X | J73: yes | K73: 44754 | L73: -1 | M73: 44763 | O73: There is a mandatory training that he needs to take at his work place and he can't manage time to attend the classes. Tried convincing him for a pause but he feels even after 2-3 month he has to reconsider his decision of joining back.He wants to continue only when he can manage proper time. Also tried convincing for a ACS before taking up a final decision but he doesn't think that will help because he liked the classes he has attended.It's just that he doesn't want to do the course right now. Informed by PS Ms. Deepti Nair | P73: Full Refund | Q73: yes
A74: 44753 | B74: AIX10219 | C74: DB to be Deactived | D74: Ayush | E74: Within Refund window | F74: NA | G74: NA | H74: Academy Intake X | J74: yes | K74: 44754 | L74: -1 | M74: 44761 | O74: This learner has some personal issues which he did not discuss with anyone, neither SP nor pS | P74: Full Refund | Q74: yes
A75: 44753 | B75: AIX10169 | C75: DB to be Deactived | D75: Ayush | E75: Within Refund window | F75: NA | G75: NA | H75: Academy Intake X | J75: yes | K75: 44754 | L75: -1 | M75: 44753 | O75: This learner has some serious medical issues as informed by Ms. Preethi Sasikumar, hence refund | P75: Full Refund | Q75: yes
A76: 44753 | B76: AIX10037 | C76: DB to be Deactived | D76: Ayush | E76: Within Refund window | F76: NA | G76: NA | H76: Academy Intake X | J76: yes | K76: 44754 | L76: -1 | M76: 44757 | O76: due to time restrictions and his 12- to 13-hour workdays | P76: Full Refund | Q76: yes
A77: 44753 | B77: AIX11361 | C77: DB to be Deactived | D77: Ayush | E77: Within Refund window | F77: NA | G77: NA | H77: Academy Intake X | J77: yes | K77: 44754 | L77: -1 | M77: 44755 | O77: The learner has requested refund because due to Low Cibil Score & unavailability of Co-aaplicant we couldn't process the Loan Amount of INR 244000. | P77: Full Refund | Q77: yes
A78: 44754 | B78: AIX10237 | C78: DB to be Deactived | D78: Ayush | E78: Within Refund window | F78: NA | G78: NA | H78: Academy Intake X | J78: yes | K78: 44754 | L78: 0 | M78: 44754 | O78: Learner has health issues and is not in a position to go ahead with the program due to the financial instability to handle medical bills, school fees for her kid and cannot be retained on the longer run to pay the remaining loan balance as well. | P78: Full Refund | Q78: yes
A79: 44754 | B79: AIX10029 | C79: DB to be Deactived | D79: Ayush | E79: Within Refund window | F79: NA | G79: NA | H79: Academy Intake X | J79: yes | K79: 44754 | L79: 0 | M79: 44755 | O79: This learner has an uncontrollable situation so understanding this we should refund this, informed by SP | P79: Full Refund | Q79: yes
... A150: 44760 | B150: AIX10218 | C150: DB to be Deactived | D150: Ayush | E150: Within Refund window | F150: NA | G150: NA | H150: Academy Intake X | J150: yes | K150: 44754 | L150: 6 | M150: 44764 | O150: This cx can't be retained due to his time constraint, he is doing 4 jobs altogether and not getting time to pursue this course. And when PS Ms. Anjali Singh suggested ACs connect, he said he has good time management skills, That's why he is managing 4 jobs together. The learner doesn't need any alumni to suggest to him on time issues, and till 6 months he will be highly occupied, which made his mind drop out from the course. | P150: Full Refund | Q150: yes
A151: 44760 | B151: AIX10312 | C151: Unknown | E151: Within Refund window | F151: NA | G151: NA | H151: Academy Intake X | J151: yes | K151: 44754 | L151: 6 | M151: 44762 | O151: The learnner is stubborn and stated that class is too fast since he is not comfortable in English so much and got a different onsite opportunity. | P151: Full Refund | Q151: yes
A152: 44760 | B152: AIX10004 | C152: DB to be Deactived | D152: Ayush | E152: Within Refund window | F152: NA | G152: NA | H152: Academy Intake X | J152: yes | K152: 44754 | L152: 6 | M152: 44767 | O152: The learner is having heavy work schedule, hence refund | P152: Full Refund | Q152: yes
A153: 44760 | B153: AIX10267 | C153: DB to be Deactived | D153: Ayush | E153: Within Refund window | F153: NA | G153: NA | H153: Academy Intake X | J153: yes | K153: 44754 | L153: 6 | M153: 44762 | O153: This learner is facing some medical issues and it is difficult for him to take the steps further to kindly initiate his refund as soon as possible. | P153: Full Refund | Q153: yes
A154: 44760 | B154: AIX10176 | C154: DB to be Deactived | D154: Ayush | E154: Within Refund window | F154: NA | G154: NA | H154: Academy Intake X | J154: yes | K154: 44754 | L154: 6 | M154: 44766 | O154: the learner is not able to make time for the classes | P154: Full Refund | Q154: yes
A155: 44760 | B155: AIX10246 | C155: Forwarded to finance | D155: Finance | E155: Within Refund window | F155: NA | G155: NA | H155: Academy Intake X | J155: yes | K155: 44754 | L155: 6 | M155: 44772 | O155: learner not able to join scaler academy due to some personal reasons. | P155: Full Refund | Q155: yes
A156: 44760 | B156: AIX10317 | C156: Forwarded to finance | D156: Finance | E156: Within Refund window | F156: NA | G156: NA | H156: Academy Intake X | J156: yes | K156: 44754 | L156: 6 | M156: 44774 | O156: No response from SP or PS. Hence the reason for the refund is unknown | P156: Full Refund | Q156: yes
A157: 44760 | B157: AIX10172 | C157: Forwarded to finance | D157: Finance | E157: Within Refund window | F157: NA | G157: NA | H157: Academy Intake X | J157: yes | K157: 44754 | L157: 6 | M157: 44769 | O157: this learner has some issues regarding the loan and will not be able to apply for it. He said he would like to enroll for the next batch. Informed by Ms. Vaishnavi Kamat (sales poc) | P157: Full Refund | Q157: yes
A158: 44761 | B158: AIX10600 | C158: DB to be Deactived | D158: Ayush | E158: Within Refund window | F158: NA | G158: NA | H158: Academy Intake X | J158: yes | K158: 44754 | L158: 7 | M158: 44767 | O158: No proper response from SP or PS, had to transfer due to delay in timelines | P158: Full Refund | Q158: yes
A159: 44761 | B159: AIX11096 | C159: DB to be Deactived | D159: Ayush | E159: Within Refund window | F159: NA | G159: NA | H159: Academy Intake X | J159: yes | K159: 44754 | L159: 7 | M159: 44761 | O159: Learner is stringent on his decision of self preparation and is wanting a refund at any cost | P159: Full Refund | Q159: yes
A160: 44761 | B160: AIX10046 | C160: DB to be Deactived | D160: Ayush | E160: Within Refund window | F160: NA | G160: NA | H160: Academy Intake X | J160: yes | K160: 44754 | L160: 7 | M160: 44761 | O160: Learner was onboarded for July batch but did not complete the finance process as he wanted to start classes from sept/oct & wanted EMI to start from oct itself. learner has 20k downpayment & wants EMI to start from oct month. So i have suggested him to go for refund & enroll again in sept, then we can ensure his EMI will also start from oct. Learner is interested but has genuine reason to start from sept as he is already taking teamcenter customization course. Please proceed with refund & will enrol the learner again when EMI can start from oct month. | P160: Full Refund | Q160: yes
A161: 44761 | B161: AIX11591 | C161: DB to be Deactived | D161: Ayush | E161: Within Refund window | F161: NA | G161: NA | H161: Academy Intake X | J161: yes | K161: 44754 | L161: 7 | M161: 44761 | O161: 1) She has a personal loan of 10 Lacs and will not be able to take up any other loan for now. 2) She comes from a QA background, and she feels that the course is primarily for people in development roles. As she has no future plans of switching to a development role, she does not find herself suitable for the program. She enrolled with us on a trial basis. 3) She also added that the classes which are taking place during the trial period are not enough for her to make an informed decision as very basic concepts are being taught initially. Therefore, she is adamant about opting out of the program. | P161: Full Refund | Q161: yes
A162: 44761 | B162: AIX10336 | C162: DB to be Deactived | D162: Ayush | E162: Within Refund window | F162: NA | G162: NA | H162: Academy Intake X | J162: yes | K162: 44754 | L162: 7 | M162: 44762 | O162: The lead is serving a notice period and says he cannot afford the EMI at this point in time | P162: Full Refund | Q162: yes
A163: 44761 | B163: AIX10033 | C163: Forwarded to finance | D163: Finance | E163: Within Refund window | F163: NA | G163: NA | H163: Academy Intake X | J163: yes | K163: 44754 | L163: 7 | M163: 44771 | O163: This learner is facing major issues to cope with the course as he is from Digital Marketing bg and after the classes, he is sure that he would not be able to continue in this IT field. | P163: Full Refund | Q163: yes
... A286: 44767 | B286: AIX10577 | C286: Forwarded to finance | D286: Finance | E286: Within Refund window | F286: NA | G286: NA | H286: Academy Intake X | J286: yes | K286: 44754 | L286: 13 | M286: 44770 | O286: Cx is currently not able to adjust with the program, said will not be able to continue, | P286: Full Refund | Q286: yes
A287: 44767 | B287: AIX11628 | C287: Forwarded to finance | D287: Finance | E287: Within Refund window | F287: NA | G287: NA | H287: Academy Intake X | J287: yes | K287: 44754 | L287: 13 | M287: 44771 | O287: The Learner doesn't want to continue anymore since he got an offer recently
A288: 44767 | B288: AIX11639 | C288: Final closure mail to be shared | D288: Sudhish | E288: Within Refund window | F288: NA | G288: NA | H288: Academy Intake X | J288: yes | K288: 44754 | L288: 13 | M288: 44771 | O288: This learner is purchasing property and hence cannot continue further with us | P288: Full Refund | Q288: yes
A289: 44767 | B289: AIX11031 | C289: Forwarded to finance | D289: Finance | E289: Within Refund window | F289: NA | G289: NA | H289: Academy Intake X | J289: yes | K289: 44754 | L289: 13 | M289: 44772 | O289: There is no other option as the learner says he has been placed as a Product Manager @ 30LPA and says he doesn't need the course for that | P289: Full Refund | Q289: yes
A290: 44768 | B290: AIX11018 | C290: Forwarded to finance | D290: Finance | E290: Within Refund window | F290: NA | G290: NA | H290: Academy Intake X | J290: yes | K290: 44754 | L290: 14 | M290: 44773 | O290: learmer unable to cope up with lectures plus got a new job where WFH is not an option. | P290: Full Refund | Q290: yes
A291: 44768 | B291: AIX11431 | C291: Forwarded to finance | D291: Finance | E291: Within Refund window | F291: NA | G291: NA | H291: Academy Intake X | J291: yes | K291: 44754 | L291: 14 | M291: 44772 | O291: Due to some personal reason cx not continue the course same bd team try to retain her but she is not answering the calls | P291: Full Refund | Q291: yes
A292: 44768 | B292: AIX11481 | C292: Forwarded to finance | D292: Finance | E292: Within Refund window | F292: NA | G292: NA | H292: Academy Intake X | J292: yes | K292: 44754 | L292: 14 | M292: 44773 | O292: Due to some personal reason cx not continue the course and need refund back | P292: Full Refund | Q292: yes
A293: 44768 | B293: AIX10142 | C293: Final closure mail to be shared | D293: Sudhish | E293: Within Refund window | F293: NA | G293: NA | H293: Academy Intake X | J293: yes | K293: 44754 | L293: 14 | M293: 44769 | O293: Unfortunately this learner cannot be retained. His father in law has got some ascending paralysis and couple of other points as well. SP Dewesh Begwani already tried his best to provide a solution but at the moment he is not in the correct mindset to continue with Scaler. | P293: Full Refund | Q293: yes
A294: 44768 | B294: AIX10841 | C294: Forwarded to finance | D294: Finance | E294: Within Refund window | F294: NA | G294: NA | H294: Academy Intake X | J294: yes | K294: 44754 | L294: 14 | M294: 44771 | O294: She do not have enough bandwidth to dedicate ~12hrs a week she wants refund | P294: Full Refund | Q294: yes
A295: 44768 | B295: AIX10896 | C295: Final closure mail to be shared | D295: Sudhish | E295: Within Refund window | F295: NA | G295: NA | H295: Academy Intake X | J295: yes | K295: 44754 | L295: 14 | M295: 44770 | O295: Learner grandfather has diagnosed with stage 4 cancer and I can't be able to give time to work, family medical issues and scaler simultaneously. | P295: Full Refund | Q295: yes
A296: 44768 | B296: AIX10942 | C296: Forwarded to finance | D296: Finance | E296: Within Refund window | F296: NA | G296: NA | H296: Academy Intake X | J296: yes | K296: 44754 | L296: 14 | M296: 44772 | O296: Cx don't not want to continue with the course. he attended the classes but after careful consideration found that it's not for him. | P296: Full Refund | Q296: yes
A297: 44768 | B297: AIX11466 | C297: Forwarded to finance | D297: Finance | E297: Within Refund window | F297: NA | G297: NA | H297: Academy Intake X | J297: yes | K297: 44754 | L297: 14 | M297: 44769 | O297: The loan was not approved by our NBFC | P297: Full Refund | Q297: yes
A298: 44768 | B298: AIX10291 | C298: Forwarded to finance | D298: Finance | E298: Within Refund window | F298: NA | G298: NA | H298: Academy Intake X | J298: yes | K298: 44754 | L298: 14 | M298: 44771 | O298: The learner was not sure before joining scaler , when she joined she realised that it didn't matched up to her expectations she said she got less time to understand what scaler has planned up for her, i tried probing her for alum connect so that we can help her a vision but she said it was earlier promised by her BDA and never done and now she has taken the final decision to take up the new job opportunity as Analyst and not continue in the development role and not continue with course as of now , she said she will comeback if she gets saturated at her new job | P298: Full Refund | Q298: yes
A299: 44769 | B299: AIX11648 | C299: Forwarded to finance | D299: Finance | E299: Outside refund window | H299: Academy Intake X | J299: yes | K299: 44754 | L299: 15 | M299: 44770 | N299: Approved by HP | O299: Cx attempted a couple of classes and hereby do not wish to continue with the course could not find the classes helpful enough to continue and thus he looking at other avenues for upskilling | P299: Full Refund | Q299: yes
A300: 44770 | B300: AIX10412 | C300: Forwarded to finance | D300: Finance | E300: Outside refund window | F300: yes | G300: 44768 | H300: Academy Intake X | J300: yes | K300: 44754 | L300: 16 | M300: 44774 | O300: This learner informed his SP wrp of his decision to withdraw from the program. This learner has time issues and feels he cannot devote 8-9 months for the program now. | P300: Full Refund | Q300: yes
A301: 44770 | B301: AIX11357 | C301: Forwarded to finance | D301: Finance | E301: Outside refund window | F301: yes | G301: 44768 | H301: Academy Intake X | J301: yes | K301: 44754 | L301: 16 | M301: 44774 | O301: This learner already informed her SP wrp on 26th July and also shared whatsapp screenshot of the same. This learner has time issues and hence has decided to back out from the program. There was also a delay in response from the PS team regarding this learner's retention call. This learner has time issues due to her office hours and some personal committments | P301: Full Refund | Q301: yes
...

Sheet Mentor Sessions
A1: Learner ID | B1: Session Title | C1: Session start time | D1: Session end time | E1: Session Status | F1: Call Duration (mins) | G1: session_rating_by_mentee | H1: grant_status
A2: AIX10731 | B2: Agenda: Career advice OR Career related doubt | C2: 44776.458 | D2: 44776.477 | E2: complete | F2: 26 | H2: Session Ended
A3: AIX10973 | B3: Agenda: Career advice OR Career related doubt | C3: 44775.896 | D3: 44775.935 | E3: complete | F3: 54 | G3: 5 | H3: Session Ended
A4: AIX10653 | B4: Agenda: Career advice OR Career related doubt | C4: 44774.917 | D4: 44774.954 | E4: complete | F4: 49 | G4: 5 | H4: Session Ended
A5: AIX10271 | B5: Agenda: Career advice OR Career related doubt | C5: 44774.896 | D5: 44774.922 | E5: complete | F5: 25 | G5: 4 | H5: Session Ended
A6: AIX10136 | B6: Agenda: Career advice OR Career related doubt | C6: 44774.604 | D6: 44774.628 | E6: complete | F6: 34 | G6: 5 | H6: Session Ended
A7: AIX10944 | B7: Agenda: Career advice OR Career related doubt | C7: 44773.875 | D7: 44773.919 | E7: complete | F7: 62 | G7: 5 | H7: Session Ended
A8: AIX10758 | B8: Agenda: Career advice OR Career related doubt | C8: 44773.792 | D8: 44773.804 | E8: didnt_happened | F8: 0 | H8: Interviewee No Show
A9: AIX10971 | B9: Agenda: Career advice OR Career related doubt | C9: 44773.625 | D9: 44773.661 | E9: complete | F9: 47 | G9: 5 | H9: Session Ended
A10: AIX11321 | B10: Agenda: Career advice OR Career related doubt | C10: 44773.458 | D10: 44773.486 | E10: complete | F10: 37 | G10: 5 | H10: Session Ended
A11: AIX10617 | B11: Agenda: Career advice OR Career related doubt | C11: 44772.917 | D11: 44772.948 | E11: complete | F11: 41 | G11: 4 | H11: Session Ended
A12: AIX10875 | B12: Agenda: Career advice OR Career related doubt | C12: 44772.875 | D12: 44772.894 | E12: complete | F12: 24 | G12: 5 | H12: Session Ended
A13: AIX10653 | B13: Agenda: Career advice OR Career related doubt | C13: 44772.667 | D13: 44772.689 | E13: didnt_happened | F13: 0 | G13: 1 | H13: Interviewer No Show
A14: AIX11590 | B14: Agenda: Career advice OR Career related doubt | C14: 44772.542 | D14: 44772.574 | E14: complete | F14: 47 | G14: 5 | H14: Session Ended
A15: AIX11036 | B15: Agenda: Career advice OR Career related doubt | C15: 44772.438 | D15: 44772.482 | E15: complete | F15: 59 | G15: 5 | H15: Session Ended
A16: AIX11075 | B16: Agenda: Career advice OR Career related doubt | C16: 44772.438 | D16: 44772.462 | E16: complete | F16: 30 | G16: 5 | H16: Session Ended
A17: AIX10993 | B17: Agenda: Career advice OR Career related doubt | C17: 44772.417 | D17: 44772.436 | E17: complete | F17: 26 | G17: 5 | H17: Session Ended
A18: AIX11633 | B18: Agenda: Career advice OR Career related doubt | C18: 44772 | D18: 44772.021 | E18: complete | F18: 29 | G18: 5 | H18: Session Ended
A19: AIX11020 | B19: Agenda: Resume review session | C19: 44771.729 | D19: 44771.747 | E19: didnt_happened | F19: 0 | H19: Interviewee No Show
A20: AIX10894 | B20: Agenda: Career advice OR Career related doubt | C20: 44771.708 | D20: 44771.742 | E20: complete | F20: 36 | G20: 5 | H20: Session Ended
A21: AIX11549 | B21: Agenda: Career advice OR Career related doubt | C21: 44771.542 | D21: 44771.587 | E21: complete | F21: 56 | G21: 5 | H21: Session Ended
A22: AIX11433 | B22: Agenda: Career advice OR Career related doubt | C22: 44771.521 | D22: 44771.544 | E22: complete | F22: 23 | G22: 4 | H22: Session Ended
A23: AIX11230 | B23: Agenda: Career advice OR Career related doubt | C23: 44771.417 | D23: 44771.46 | E23: complete | F23: 22 | G23: 5 | H23: Session Ended | N23: 50 | O23: 0.5
A24: AIX11374 | B24: Agenda: Career advice OR Career related doubt | C24: 44770.917 | D24: 44770.943 | E24: complete | F24: 34 | H24: Session Ended | N24: 30 | O24: 0.8
A25: AIX10187 | B25: Agenda: Career advice OR Career related doubt | C25: 44770.896 | D25: 44770.937 | E25: complete | F25: 56 | H25: Session Ended | N25: 15 | O25: 2
A26: AIX11473 | B26: Agenda: Career advice OR Career related doubt | C26: 44770.833 | D26: 44770.856 | E26: complete | F26: 31 | G26: 5 | H26: Session Ended | N26: 5 | O26: 5
A27: AIX10617 | B27: Agenda: Career advice OR Career related doubt | C27: 44769.979 | D27: 44769.983 | E27: didnt_happened | F27: 0 | H27: Interviewee No Show
A28: AIX10509 | B28: Agenda: Career advice OR Career related doubt | C28: 44769.896 | D28: 44769.955 | E28: complete | F28: 80 | G28: 5 | H28: Session Ended
A29: AIX10579 | B29: Agenda: Career advice OR Career related doubt | C29: 44769.812 | D29: 44769.847 | E29: complete | F29: 49 | G29: 5 | H29: Session Ended
A30: AIX10884 | B30: Agenda: Career advice OR Career related doubt | C30: 44769.583 | D30: 44769.605 | E30: complete | F30: 30 | G30: 5 | H30: Session Ended
A31: AIX10488 | B31: Agenda: Career advice OR Career related doubt | C31: 44769.5 | D31: 44769.507 | E31: complete | F31: 5 | G31: 5 | H31: Session Ended
A32: AIX11536 | B32: Agenda: Career advice OR Career related doubt | C32: 44769.417 | D32: 44769.441 | E32: complete | F32: 32 | G32: 4 | H32: Session Ended
A33: AIX11631 | B33: Agenda: Career advice OR Career related doubt | C33: 44769.354 | D33: 44769.387 | E33: complete | F33: 45 | H33: Session Ended
A34: AIX11385 | B34: Agenda: Career advice OR Career related doubt | C34: 44768.896 | D34: 44768.938 | E34: complete | F34: 61 | G34: 5 | H34: Session Ended
A35: AIX11026 | B35: Agenda: Career advice OR Career related doubt | C35: 44768.833 | D35: 44768.883 | E35: complete | F35: 67 | H35: Session Ended
A36: AIX10992 | B36: Agenda: Resume review session | C36: 44767.708 | D36: 44767.732 | E36: complete | F36: 32 | G36: 4 | H36: Session Ended
A37: AIX11202 | B37: Agenda: Career advice OR Career related doubt | C37: 44767.396 | D37: 44767.41 | E37: complete | F37: 15 | G37: 4 | H37: Session Ended
A38: AIX10497 | B38: Agenda: Career advice OR Career related doubt | C38: 44766.875 | D38: 44766.919 | E38: complete | F38: 63 | H38: Session Ended
A39: AIX10712 | B39: Agenda: Help with coping up with the course | C39: 44766.854 | D39: 44766.908 | E39: complete | F39: 77 | H39: Session Ended
A40: AIX11344 | B40: Agenda: Career advice OR Career related doubt | C40: 44766.792 | D40: 44766.82 | E40: complete | F40: 40 | G40: 5 | H40: Session Ended
A41: AIX10683 | B41: Agenda: Career advice OR Career related doubt | C41: 44766.625 | D41: 44766.662 | E41: complete | F41: 52 | G41: 5 | H41: Session Ended
A42: AIX10590 | B42: Agenda: Career advice OR Career related doubt | C42: 44766.521 | D42: 44766.539 | E42: complete | F42: 24 | G42: 5 | H42: Session Ended
A43: AIX11432 | B43: Agenda: Career advice OR Career related doubt | C43: 44766.5 | D43: 44766.52 | E43: complete | F43: 28 | G43: 4 | H43: Session Ended
A44: AIX10797 | B44: Agenda: Career advice OR Career related doubt | C44: 44766.458 | D44: 44766.489 | E44: complete | F44: 41 | G44: 5 | H44: Session Ended
A45: AIX10243 | B45: Agenda: Help with the next career choice / offer negotiation | C45: 44766 | D45: 44766.028 | E45: complete | F45: 37 | G45: 3 | H45: Session Ended
A46: AIX10243 | B46: Agenda: Career advice OR Career related doubt | C46: 44765.917 | D46: 44765.979 | E46: complete | F46: 79 | G46: 3 | H46: Session Ended
A47: AIX11188 | B47: Agenda: Career advice OR Career related doubt | C47: 44765.833 | D47: 44765.895 | E47: complete | F47: 80 | G47: 5 | H47: Session Ended
A48: AIX10527 | B48: Agenda: Career advice OR Career related doubt | C48: 44765.708 | D48: 44765.746 | E48: complete | F48: 39 | G48: 1 | H48: Session Ended
A49: AIX10433 | B49: Agenda: Career advice OR Career related doubt | C49: 44765.667 | D49: 44765.737 | E49: complete | F49: 98 | G49: 5 | H49: Session Ended
A50: AIX10605 | B50: Agenda: Career advice OR Career related doubt | C50: 44765.646 | D50: 44765.718 | E50: complete | F50: 89 | G50: 4 | H50: Session Ended
A51: AIX11583 | B51: Agenda: Career advice OR Career related doubt | C51: 44765.646 | D51: 44765.665 | E51: complete | F51: 26 | G51: 5 | H51: Session Ended
A52: AIX10918 | B52: Agenda: Career advice OR Career related doubt | C52: 44765.583 | D52: 44765.612 | E52: complete | F52: 23 | G52: 5 | H52: Session Ended
A53: AIX11278 | B53: Agenda: Career advice OR Career related doubt | C53: 44765.583 | D53: 44765.606 | E53: didnt_happened | F53: 0 | H53: Interviewee No Show
A54: AIX11610 | B54: Agenda: Career advice OR Career related doubt | C54: 44765.458 | D54: 44765.48 | E54: complete | F54: 28 | G54: 4 | H54: Session Ended
A55: AIX10056 | B55: Agenda: Career advice OR Career related doubt | C55: 44765.438 | D55: 44765.473 | E55: complete | F55: 44 | G55: 5 | H55: Session Ended
A56: AIX11459 | B56: Agenda: Help with coping up with the course | C56: 44765.438 | D56: 44765.488 | E56: complete | F56: 27 | G56: 1 | H56: Session Ended
A57: AIX10980 | B57: Agenda: Career advice OR Career related doubt | C57: 44765.438 | D57: 44765.459 | E57: complete | F57: 30 | G57: 5 | H57: Session Ended
A58: AIX10753 | B58: Agenda: Career advice OR Career related doubt | C58: 44765.396 | D58: 44765.422 | E58: complete | F58: 36 | H58: Session Ended
A59: AIX10374 | B59: Agenda: Resume review session | C59: 44765.354 | D59: 44765.381 | E59: complete | F59: 27 | G59: 3 | H59: Session Ended
A60: AIX10567 | B60: Agenda: Help with communication skills | C60: 44764.958 | D60: 44764.988 | E60: complete | F60: 38 | H60: Session Ended
A61: AIX10497 | B61: Agenda: Career advice OR Career related doubt | C61: 44764.896 | D61: 44764.918 | E61: didnt_happened | F61: 0 | H61: Interviewer No Show
A62: AIX10992 | B62: Agenda: Resume review session | C62: 44764.875 | D62: 44764.897 | E62: didnt_happened | F62: 0 | H62: Interviewer No Show
A63: AIX11458 | B63: Agenda: Career advice OR Career related doubt | C63: 44764.875 | D63: 44764.901 | E63: complete | F63: 34 | G63: 4 | H63: Session Ended
A64: AIX10467 | B64: Agenda: Career advice OR Career related doubt | C64: 44764.854 | D64: 44764.884 | E64: complete | F64: 42 | G64: 4 | H64: Session Ended
A65: AIX11238 | B65: Agenda: Career advice OR Career related doubt | C65: 44764.854 | D65: 44764.887 | E65: complete | F65: 45 | H65: Session Ended
A66: AIX11473 | B66: Agenda: Help with coping up with the course | C66: 44764.792 | D66: 44764.814 | E66: didnt_happened | F66: 0 | H66: Interviewer No Show
A67: AIX10388 | B67: Agenda: Career advice OR Career related doubt | C67: 44764.729 | D67: 44764.752 | E67: complete | F67: 32 | G67: 5 | H67: Session Ended
A68: AIX10877 | B68: Agenda: Career advice OR Career related doubt | C68: 44764.667 | D68: 44764.693 | E68: didnt_happened | F68: 0 | H68: Interviewer No Show
A69: AIX10908 | B69: Agenda: Career advice OR Career related doubt | C69: 44764.562 | D69: 44764.603 | E69: complete | F69: 25 | G69: 5 | H69: Session Ended
A70: AIX11197 | B70: Agenda: Career advice OR Career related doubt | C70: 44764.417 | D70: 44764.46 | E70: complete | F70: 31 | G70: 4 | H70: Session Ended
A71: AIX10151 | B71: Agenda: Career advice OR Career related doubt | C71: 44764.396 | D71: 44764.421 | E71: complete | F71: 35 | G71: 5 | H71: Session Ended
A72: AIX11642 | B72: Agenda: Career advice OR Career related doubt | C72: 44763.875 | D72: 44763.904 | E72: complete | F72: 28 | G72: 4 | H72: Session Ended
A73: AIX10687 | B73: Agenda: Career advice OR Career related doubt | C73: 44763.875 | D73: 44763.9 | E73: complete | F73: 30 | G73: 3 | H73: Session Ended
A74: AIX11641 | B74: Agenda: Career advice OR Career related doubt | C74: 44763.833 | D74: 44763.856 | E74: complete | F74: 20 | G74: 4 | H74: Session Ended
A75: AIX10880 | B75: Agenda: Career advice OR Career related doubt | C75: 44763.812 | D75: 44763.861 | E75: complete | F75: 64 | H75: Session Ended
A76: AIX10705 | B76: Agenda: Career advice OR Career related doubt | C76: 44763.812 | D76: 44763.825 | E76: complete | F76: 17 | G76: 4 | H76: Session Ended
A77: AIX10868 | B77: Agenda: Career advice OR Career related doubt | C77: 44763.792 | D77: 44763.811 | E77: complete | F77: 25 | G77: 5 | H77: Session Ended
A78: AIX11198 | B78: Agenda: Career advice OR Career related doubt | C78: 44763.792 | D78: 44763.83 | E78: complete | F78: 54 | G78: 5 | H78: Session Ended
A79: AIX10889 | B79: Agenda: Career advice OR Career related doubt | C79: 44763.771 | D79: 44763.788 | E79: complete | F79: 22 | G79: 3 | H79: Session Ended
A80: AIX11405 | B80: Agenda: Career advice OR Career related doubt | C80: 44763.708 | D80: 44763.734 | E80: didnt_happened | F80: 0 | G80: 1 | H80: Interviewer No Show
A81: AIX10104 | B81: Agenda: Help with coping up with the course | C81: 44763.708 | D81: 44763.752 | E81: complete | F81: 15 | G81: 4 | H81: Session Ended
A82: AIX10788 | B82: Agenda: Help with the next career choice / offer negotiation | C82: 44763.667 | D82: 44763.693 | E82: didnt_happened | F82: 0 | G82: 1 | H82: Interviewer No Show
A83: AIX10199 | B83: Agenda: Career advice OR Career related doubt | C83: 44763.604 | D83: 44763.63 | E83: complete | F83: 36 | G83: 5 | H83: Session Ended
A84: AIX11299 | B84: Agenda: Career advice OR Career related doubt | C84: 44763.5 | D84: 44763.52 | E84: complete | F84: 20 | G84: 5 | H84: Session Ended
A85: AIX10615 | B85: Agenda: Career advice OR Career related doubt | C85: 44762.979 | D85: 44763.011 | E85: complete | F85: 44 | G85: 3 | H85: Session Ended
A86: AIX10509 | B86: Agenda: Career advice OR Career related doubt | C86: 44762.896 | D86: 44762.94 | E86: complete | F86: 59 | G86: 3 | H86: Session Ended
A87: AIX10243 | B87: Agenda: Help with the next career choice / offer negotiation | C87: 44762.896 | D87: 44762.978 | E87: complete | F87: 114 | G87: 4 | H87: Session Ended
... A89: AIX10684 | B89: Agenda: Career advice OR Career related doubt | C89: 44762.833 | D89: 44762.867 | E89: complete | F89: 47 | G89: 5 | H89: Session Ended
A90: AIX10695 | B90: Agenda: Career advice OR Career related doubt | C90: 44762.792 | D90: 44762.815 | E90: complete | F90: 17 | H90: Session Ended
A91: AIX11057 | B91: Agenda: Career advice OR Career related doubt | C91: 44762.729 | D91: 44762.763 | E91: complete | F91: 42 | G91: 5 | H91: Session Ended
A92: AIX10309 | B92: Agenda: Career advice OR Career related doubt | C92: 44762.667 | D92: 44762.709 | E92: complete | F92: 58 | H92: Session Ended
A93: AIX11344 | B93: Agenda: Career advice OR Career related doubt | C93: 44762.667 | D93: 44762.689 | E93: complete | F93: 25 | H93: Session Ended
A94: AIX10410 | B94: Agenda: Career advice OR Career related doubt | C94: 44761.917 | D94: 44761.969 | E94: complete | F94: 73 | G94: 5 | H94: Session Ended
A95: AIX11045 | B95: Agenda: Career advice OR Career related doubt | C95: 44761.854 | D95: 44761.872 | E95: complete | F95: 24 | H95: Session Ended
A96: AIX10066 | B96: Agenda: Career advice OR Career related doubt | C96: 44761.833 | D96: 44761.878 | E96: complete | F96: 60 | G96: 5 | H96: Session Ended
A97: AIX10374 | B97: Agenda: Help with the next career choice / offer negotiation | C97: 44761.833 | D97: 44761.861 | E97: complete | F97: 28 | G97: 5 | H97: Session Ended
A98: AIX10692 | B98: Agenda: Career advice OR Career related doubt | C98: 44761.812 | D98: 44761.837 | E98: complete | F98: 27 | H98: Session Ended
A99: AIX11645 | B99: Agenda: Resume review session | C99: 44761.792 | D99: 44761.815 | E99: didnt_happened | F99: 0 | G99: 1 | H99: Interviewer No Show
A100: AIX10058 | B100: Agenda: Career advice OR Career related doubt | C100: 44761.771 | D100: 44761.793 | E100: complete | F100: 28 | G100: 5 | H100: Session Ended
A101: AIX11332 | B101: Agenda: Career advice OR Career related doubt | C101: 44761.708 | D101: 44761.732 | E101: complete | F101: 32 | G101: 4 | H101: Session Ended
...
